Workbook

Sheet Read Me
A1: Nifty 500 AI signals - daily run for Fri 23-Oct-2026
A2: NSE data to the close of Fri 23-Oct-2026. Market regime: FALLING (Nifty 50 below its 50- and 200-DMA). Breadth: 10% of Nifty 500 stocks above their 50-DMA, 27% above their 200-DMA.
A3: Research output for paper trading and education - not investment advice; not a SEBI-registered adviser. Every probability is a historical frequency, not a promise.
A4: Track record of these daily calls: 34% of 406 completed calls were right (since 2026-09-25); days whose calls have all finished: 39% of 348. Full detail on the last sheet, 'Success Rate'.
A6: Today's calls in one line per timeframe
A7: • Short term (up to 2 weeks): 29 buy calls (20 Strong Buy), 74 avoid/reduce, the rest hold.
A8: • Mid term (up to 3 months): 1 buy calls (0 Strong Buy), 81 avoid/reduce, the rest hold.
A9: • Long term (up to 1 year): 2 buy calls (0 Strong Buy), 121 avoid/reduce, the rest hold.
A11: What goes into every run
A12: • 454 indicator values per stock per day: the complete TA-Lib library (136 functions) plus 60+ tools it lacks - Ichimoku, Supertrend, Renko, Kagi, three-line break, Heikin-Ashi, point & figure, volume profile, anchored VWAPs, pivot points, Laguerre/Connors RSI, Fisher, Schaff, KST, Klinger, Hurst, NSE delivery-% analytics, relative strength vs Nifty and sector, market breadth, calendar effects. Every value uses only past data.
A13: • 137 chart-pattern types found by a swing engine at three swing sizes: head & shoulders, double/triple tops & bottoms, cup & handle, triangles, wedges, flags, pennants, rectangles, channels, broadening formations, diamonds, rounding tops/bottoms, V-reversals, islands, gaps, Darvas boxes, VCP, flat bases, high-tight flags, Wyckoff springs/upthrusts, 2B/turtle soup, Dow-theory reversals, Elliott 5-wave counts, three drives, harmonics (Gartley, Bat, Butterfly, Crab, Deep crab, Cypher, AB=CD), Wolfe waves, Quasimodo, Fibonacci pull-backs, trendline and support/resistance breaks, divergences, pipes & horns, point & figure signals.
A14: • 104 classic indicator signals and 177 candlestick signals (all 61 TA-Lib patterns, raw and in trend context, plus tweezers, pin bars, outside bars).
... A28: Trade rules per timeframe (levels are multiples of the 14-day ATR, the stock's average daily range)
A29: Timeframe | B29: Stop (x ATR) | C29: Target (x ATR) | D29: No-chase (x ATR) | E29: Max days | F29: Reward : risk | G29: Notes
A30: Short term (up to 2 weeks) | B30: 1.5 | C30: 3 | D30: 1 | E30: 10 | F30: =C30/B30 | G30: Blue cells are inputs: change them and every Entry/Target/Stop on 'Signals' recalculates. The success-rate tracker always uses the published levels.
A31: Mid term (up to 3 months) | B31: 3 | C31: 6 | D31: 1.5 | E31: 60 | F31: =C31/B31 | G31: Blue cells are inputs: change them and every Entry/Target/Stop on 'Signals' recalculates. The success-rate tracker always uses the published levels.
A32: Long term (up to 1 year) | B32: 5 | C32: 10 | D32: 2 | E32: 250 | F32: =C32/B32 | G32: Blue cells are inputs: change them and every Entry/Target/Stop on 'Signals' recalculates. The success-rate tracker always uses the published levels.
A34: What the research evidence says (read before trading)
A35: • Short term is where the model is most reliable: its daily ranking beat chance in 7 of 7 years (rank correlation 0.036); the top 5% beat the same-day average stock by +0.33% per 2-week trade overall and +0.14% in falling markets. Small per trade - costs and discipline matter.
A36: • Mid and long term: the model's buy ranking did NOT beat the average stock in falling markets (its favourites lagged, beaten-down stocks rebounded more), so mid/long-term buys today come only from proven setups. Its warnings (likely underperformers) held up in rising, mixed and falling markets and in 19 of 20 test years across the three horizons - the most dependable output.
A37: • Chart patterns alone: only 2 of 137 pattern types beat the average stock reliably over 3 months (Fibonacci 38-62% rally failure in a downtrend, Wyckoff upthrust - both bearish warnings); 14 worked in reverse; 'buy after a crash' looked like a winner but was a survivorship illusion (below). Textbook patterns did not beat the average stock on NSE in 2017-26: double bottom (t -2.2), symmetrical-triangle breakout (t -2.2), ascending-triangle breakout (t -0.5), bull flag (t -0.3), cup breakout (t +0.0), head & shoulders top (t -0.1); inverse head & shoulders (t -3.4) and Wyckoff springs (t -4.8) did reliably worse than average (3-month t-stats; |t| >= 3 needed).
A38: • What did work: buying orderly pullbacks inside strong uptrends (Holy Grail, three lower closes, RSI(2) < 5; IBS < 0.2 and Double 7s too, with smaller effects), stocks whose relative-strength line makes a 52-week high or whose moving averages newly stack bullish, and avoiding stocks in stage-4 downtrends or with RSI(2) > 95 in a downtrend. Late trend-following buy flips (Supertrend, Parabolic SAR, volatility stop, Renko/three-line-break reversals, 20-day breakouts) tended to underperform afterwards.
A39: • Survivorship check on the full NSE universe as it stood each day: an average 3-month trade hit target 28% vs 30% on today's constituents; 1-year 38% vs 43%. All long-side confidences here are corrected for this.
A40: • 'Buy after a 15% two-day crash' looked great on today's list (+7.4% vs average over a year) but not on the full universe (median -14.7%; 57% of such crashes were in stocks that later left the index) - so it is NOT used as a buy reason.
A42: Market on Fri 23-Oct-2026 (computed from NSE data)
A43: • Nifty 50 closed at 22,600.00 (-0.39% on the day, -3.1% over one month, -12.1% over one year); -3.4% from its 50-DMA and -6.3% from its 200-DMA.
A44: • Breadth: 10% of Nifty 500 stocks above their 50-DMA (-5 pts in 10 sessions) and 27% above their 200-DMA; 8% of stocks rose on the day; 52-week highs minus lows: -20.8% of stocks.
A45: • Mid caps (Nifty Midcap 150) vs Nifty 50 over one month: -6.5 pts; small caps (Nifty Smallcap 250): -7.1 pts.
A47: Data checks for this run
... A51: Data: NSE bhavcopy and index closes (nsearchives.nseindia.com; GitHub mirrors tilak999/NSE-Data-bank and Chaudharyrohit2506/nse-daily-ohlcv as fallback), history from kaushikghoshindia/NSE500Tracker. Splits, bonuses and demergers are adjusted automatically from NSE's adjusted previous close. Research tool - not investment advice.

Sheet Signals
A1: Symbol | B1: Company | C1: Sector | D1: Timeframe | E1: AI recommendation | F1: Recommendation type | G1: AI confidence - buy side | H1: AI confidence - short side | I1: Chance of profit (recommended side) | J1: Expected return per trade | K1: Edge vs average stock | L1: Current price Rs | M1: ATR 14 Rs | N1: Entry Rs (buy up to) | O1: Target Rs (sell at) | P1: Stop loss Rs | Q1: Potential profit | R1: Potential loss | S1: Days to hold (max) | T1: Typical days to target | U1: Current trend | V1: Evidence (AI model rank + proven signals) | W1: Active chart patterns (last 10 sessions) [3-mth verdict] | X1: Latest results check | Y1: Remarks
A2: KOTAKBANK | B2: Kotak Mahindra Bank Ltd. | C2: Financial Services | D2: Short term (up to 2 weeks) | E2: Buy | F2: Buy | G2: 0.17817111 | H2: 0.14315289 | I2: 0.43614344 | J2: 0.0054175239 | K2: 2.4210056 | L2: 430.5 | M2: 9.5389728 | N2: =ROUND(L2+'Read Me'!$D$30*M2,2) | O2: =ROUND(L2+'Read Me'!$C$30*M2,2) | P2: =ROUND(L2-'Read Me'!$B$30*M2,2) | Q2: =ABS(O2-L2)/L2 | R2: =ABS(L2-P2)/L2 | S2: 10 | T2: 6 | U2: Sideways | V2: Model rank: top 34% buy side / top 15% short side (buy bucket: 50-70%); + Holy Grail: ADX > 30 and pullback to 20 EMA (23-Oct): +0.4% vs avg stock, t 4.6; + RSI(2) below 5 in an uptrend (Connors) (23-Oct): +0.2% vs avg stock, t 3.6 | W2: ▼ 2B top / Turtle soup 19-Oct [weak edge]; ▼ Bearish AB=CD 19-Oct [no edge]; ▼ Wyckoff upthrust 16-Oct [works]; ▲ Pocket pivot 15-Oct [no edge] | X2: Supportive | Y2: Proven setup active: Holy Grail: ADX > 30 and pullback to 20 EMA (23-Oct) - historically +0.4% vs the average stock over 2 weeks (t 4.6, also positive in falling markets). Buy confidence 18% vs 15% for an average stock; expected +0.5% per trade after costs. Technicals: RSI 52; RS rating 82; -5% from 52-wk high; below 20-EMA. Results Q1 FY27 (Apr-Jun 2026) - revenue: NII +9%; profit: Standalone +26% to Rs 4,123 Cr; consolidated +23% to Rs 5,480 Cr (supportive).
A3: KOTAKBANK | B3: Kotak Mahindra Bank Ltd. | C3: Financial Services | D3: Mid term (up to 3 months) | E3: Buy | F3: Buy | G3: 0.31279249 | H3: 0.12952211 | I3: 0.50460817 | J3: 0.054241333 | K3: 3.8472033 | L3: 430.5 | M3: 9.5389728 | N3: =ROUND(L3+'Read Me'!$D$31*M3,2) | O3: =ROUND(L3+'Read Me'!$C$31*M3,2) | P3: =ROUND(L3-'Read Me'!$B$31*M3,2) | Q3: =ABS(O3-L3)/L3 | R3: =ABS(L3-P3)/L3 | S3: 60 | T3: 29 | U3: Up | V3: Model rank: top 18% buy side / top 27% short side (buy bucket: 70-85%); + Holy Grail: ADX > 30 and pullback to 20 EMA (23-Oct): +1.3% vs avg stock, t 6.1; + Three lower closes in an uptrend (21-Oct): +0.5% vs avg stock, t 6.7 | W3: ▼ 2B top / Turtle soup 19-Oct [weak edge]; ▼ Bearish AB=CD 19-Oct [no edge]; ▼ Wyckoff upthrust 16-Oct [works]; ▲ Pocket pivot 15-Oct [no edge] | X3: Supportive | Y3: Proven setup active: Holy Grail: ADX > 30 and pullback to 20 EMA (23-Oct) - historically +1.3% vs the average stock over 3 months (t 6.1, also positive in falling markets). Buy confidence 31% vs 27% for an average stock; expected +5.4% per trade after costs. Technicals: RSI 52; RS rating 82; -5% from 52-wk high; above a rising 50-DMA. Results Q1 FY27 (Apr-Jun 2026) - revenue: NII +9%; profit: Standalone +26% to Rs 4,123 Cr; consolidated +23% to Rs 5,480 Cr (supportive).
A4: KOTAKBANK | B4: Kotak Mahindra Bank Ltd. | C4: Financial Services | D4: Long term (up to 1 year) | E4: Accumulate | F4: Accumulate (buy on dips) | G4: 0.39511908 | H4: 0.085280983 | I4: 0.5305555 | J4: 0.15576886 | K4: 1.9765596 | L4: 430.5 | M4: 9.5389728 | N4: =ROUND(L4+'Read Me'!$D$32*M4,2) | O4: =ROUND(L4+'Read Me'!$C$32*M4,2) | P4: =ROUND(L4-'Read Me'!$B$32*M4,2) | Q4: =ABS(O4-L4)/L4 | R4: =ABS(L4-P4)/L4 | S4: 250 | T4: 86 | U4: Sideways | V4: Model rank: top 9% buy side / top 25% short side (buy bucket: Top 15% (85-95%)); + Holy Grail: ADX > 30 and pullback to 20 EMA (23-Oct): +3.1% vs avg stock, t 6.4; + Three lower closes in an uptrend (21-Oct): +1.8% vs avg stock, t 6.9 | W4: ▼ 2B top / Turtle soup 19-Oct [weak edge]; ▼ Bearish AB=CD 19-Oct [no edge]; ▼ Wyckoff upthrust 16-Oct [works]; ▲ Pocket pivot 15-Oct [no edge] | X4: Supportive | Y4: Proven setup active: Holy Grail: ADX > 30 and pullback to 20 EMA (23-Oct) - historically +3.1% vs the average stock over 1 year (t 6.4, also positive in falling markets). Buy confidence 40% vs 38% for an average stock; expected +15.6% per trade after costs. Build the position in parts on dips toward the 20/50-DMA rather than all at once. Technicals: RSI 52; RS rating 82; -5% from 52-wk high; above a falling 200-DMA. Results Q1 FY27 (Apr-Jun 2026) - revenue: NII +9%; profit: Standalone +26% to Rs 4,123 Cr; consolidated +23% to Rs 5,480 Cr (supportive).
A5: JWL | B5: Jupiter Wagons Ltd. | C5: Industrial Manufacturing | D5: Short term (up to 2 weeks) | E5: Buy | F5: Strong Buy | G5: 0.21183931 | H5: 0.084306981 | I5: 0.42819519 | J5: 0.0018773479 | K5: 5.7878251 | L5: 173.39 | M5: 8.4435707 | N5: =ROUND(L5+'Read Me'!$D$30*M5,2) | O5: =ROUND(L5+'Read Me'!$C$30*M5,2) | P5: =ROUND(L5-'Read Me'!$B$30*M5,2) | Q5: =ABS(O5-L5)/L5 | R5: =ABS(L5-P5)/L5 | S5: 10 | T5: 6 | U5: Down | V5: Model rank: top 1% buy side / bottom 7% short side (buy bucket: Top 5%) | W5: ▼ Descending broadening wedge - down breakout 14-Oct [no edge]; ▼ Falling wedge - down breakout 09-Oct [no edge] | X5: Not checked | Y5: AI model ranks it in the top 1% of stocks for a 2-week buy. Historically, top-5% names hit the target 21% of the time vs 15% for the average stock (weighted to falling markets like now), averaging +0.2% per trade after costs. Technicals: RSI 19; RS rating 1; -52% from 52-wk high; below 20-EMA.
A6: JWL | B6: Jupiter Wagons Ltd. | C6: Industrial Manufacturing | D6: Mid term (up to 3 months) | E6: Hold | F6: Hold / No fresh trade | G6: 0.29501647 | H6: 0.099596779 | I6: 0.49617973 | J6: 0.039061651 | K6: 2.0696017 | L6: 173.39 | M6: 8.4435707 | U6: Down | V6: Model rank: top 5% buy side / bottom 28% short side (buy bucket: Top 15% (85-95%)) | W6: ▼ Descending broadening wedge - down breakout 14-Oct [no edge]; ▼ Falling wedge - down breakout 09-Oct [no edge] | X6: Not checked | Y6: The model ranks it in the top 5% for a 3-month buy, but at this horizon its top ranks have not beaten the average stock in falling markets, so that is not counted; no proven signal active. Holders can keep; no fresh entry. Technicals: RSI 19; RS rating 1; -52% from 52-wk high; below a falling 50-DMA.
A7: JWL | B7: Jupiter Wagons Ltd. | C7: Industrial Manufacturing | D7: Long term (up to 1 year) | E7: Hold | F7: Hold / No fresh trade | G7: 0.35529798 | H7: 0.037138628 | I7: 0.51111196 | J7: 0.10959171 | K7: -2.00555 | L7: 173.39 | M7: 8.4435707 | U7: Down | V7: Model rank: top 43% buy side / bottom 8% short side (buy bucket: 50-70%); - RSI(14) rises back above 30 - fades (16-Oct): -1.6% vs avg stock, t 4.1 | W7: ▼ Descending broadening wedge - down breakout 14-Oct [no edge]; ▼ Falling wedge - down breakout 09-Oct [no edge] | X7: Not checked | Y7: No edge either way for 1 year (buy-side model rank: 57th percentile; no proven signal active). Holders can keep; no fresh entry. Technicals: RSI 19; RS rating 1; -52% from 52-wk high; below a falling 200-DMA.
A8: JBMA | B8: JBM Auto Ltd. | C8: Automobile | D8: Short term (up to 2 weeks) | E8: Buy | F8: Strong Buy | G8: 0.21183931 | H8: 0.11425674 | I8: 0.42819519 | J8: 0.0018773479 | K8: 5.7878251 | L8: 487.15 | M8: 17.653738 | N8: =ROUND(L8+'Read Me'!$D$30*M8,2) | O8: =ROUND(L8+'Read Me'!$C$30*M8,2) | P8: =ROUND(L8-'Read Me'!$B$30*M8,2) | Q8: =ABS(O8-L8)/L8 | R8: =ABS(L8-P8)/L8 | S8: 10 | T8: 6 | U8: Down | V8: Model rank: top 1% buy side / bottom 42% short side (buy bucket: Top 5%) | W8: ▼ Bear flag 21-Oct [works in reverse]; ▲ 2B bottom / Turtle soup 12-Oct [no edge] | X8: Not checked | Y8: AI model ranks it in the top 1% of stocks for a 2-week buy. Historically, top-5% names hit the target 21% of the time vs 15% for the average stock (weighted to falling markets like now), averaging +0.2% per trade after costs. Technicals: RSI 22; RS rating 13; -34% from 52-wk high; below 20-EMA.
A9: JBMA | B9: JBM Auto Ltd. | C9: Automobile | D9: Mid term (up to 3 months) | E9: Hold | F9: Hold / No fresh trade | G9: 0.29501647 | H9: 0.11434533 | I9: 0.49617973 | J9: 0.039061651 | K9: 2.0696017 | L9: 487.15 | M9: 17.653738 | U9: Down | V9: Model rank: top 8% buy side / top 49% short side (buy bucket: Top 15% (85-95%)) | W9: ▼ Bear flag 21-Oct [works in reverse]; ▲ 2B bottom / Turtle soup 12-Oct [no edge] | X9: Not checked | Y9: The model ranks it in the top 8% for a 3-month buy, but at this horizon its top ranks have not beaten the average stock in falling markets, so that is not counted; no proven signal active. Holders can keep; no fresh entry. Technicals: RSI 22; RS rating 13; -34% from 52-wk high; below a falling 50-DMA.
A10: JBMA | B10: JBM Auto Ltd. | C10: Automobile | D10: Long term (up to 1 year) | E10: Hold | F10: Hold / No fresh trade | G10: 0.3356492 | H10: 0.055927815 | I10: 0.49884743 | J10: 0.099800505 | K10: -3.9704276 | L10: 487.15 | M10: 17.653738 | U10: Down | V10: Model rank: top 20% buy side / bottom 27% short side (buy bucket: 70-85%); - RSI(14) rises back above 30 - fades (12-Oct): -1.6% vs avg stock, t 4.1 | W10: ▼ Bear flag 21-Oct [works in reverse]; ▲ 2B bottom / Turtle soup 12-Oct [no edge] | X10: Not checked | Y10: No edge either way for 1 year (buy-side model rank: 80th percentile; no proven signal active). Holders can keep; no fresh entry. Technicals: RSI 22; RS rating 13; -34% from 52-wk high; below a falling 200-DMA.
A11: RPOWER | B11: Reliance Power Ltd. | C11: Energy | D11: Short term (up to 2 weeks) | E11: Buy | F11: Strong Buy | G11: 0.21183931 | H11: 0.11425674 | I11: 0.42819519 | J11: 0.0018773479 | K11: 5.7878251 | L11: 16.43 | M11: 0.73021845 | N11: =ROUND(L11+'Read Me'!$D$30*M11,2) | O11: =ROUND(L11+'Read Me'!$C$30*M11,2) | P11: =ROUND(L11-'Read Me'!$B$30*M11,2) | Q11: =ABS(O11-L11)/L11 | R11: =ABS(L11-P11)/L11 | S11: 10 | T11: 6 | U11: Down | V11: Model rank: top 1% buy side / bottom 41% short side (buy bucket: Top 5%) | W11: ▼ Falling wedge - down breakout 19-Oct [no edge]; ▼ P&F bearish descending breakdown 15-Oct [works in reverse]; ▼ Wave-3 / ABC breakdown 15-Oct [no edge] | X11: Not checked | Y11: AI model ranks it in the top 1% of stocks for a 2-week buy. Historically, top-5% names hit the target 21% of the time vs 15% for the average stock (weighted to falling markets like now), averaging +0.2% per trade after costs. Technicals: RSI 17; RS rating 1; -66% from 52-wk high; below 20-EMA.
A12: RPOWER | B12: Reliance Power Ltd. | C12: Energy | D12: Mid term (up to 3 months) | E12: Hold | F12: Hold / No fresh trade | G12: 0.29501647 | H12: 0.11434533 | I12: 0.49617973 | J12: 0.039061651 | K12: 2.0696017 | L12: 16.43 | M12: 0.73021845 | U12: Down | V12: Model rank: top 8% buy side / top 50% short side (buy bucket: Top 15% (85-95%)) | W12: ▼ Falling wedge - down breakout 19-Oct [no edge]; ▼ P&F bearish descending breakdown 15-Oct [works in reverse]; ▼ Wave-3 / ABC breakdown 15-Oct [no edge] | X12: Not checked | Y12: The model ranks it in the top 8% for a 3-month buy, but at this horizon its top ranks have not beaten the average stock in falling markets, so that is not counted; no proven signal active. Holders can keep; no fresh entry. Technicals: RSI 17; RS rating 1; -66% from 52-wk high; below a falling 50-DMA.
A13: RPOWER | B13: Reliance Power Ltd. | C13: Energy | D13: Long term (up to 1 year) | E13: Hold | F13: Hold / No fresh trade | G13: 0.37136452 | H13: 0.037138628 | I13: 0.51670509 | J13: 0.11597254 | K13: -0.39889565 | L13: 16.43 | M13: 0.73021845 | U13: Down | V13: Model rank: top 22% buy side / bottom 3% short side (buy bucket: 70-85%) | W13: ▼ Falling wedge - down breakout 19-Oct [no edge]; ▼ P&F bearish descending breakdown 15-Oct [works in reverse]; ▼ Wave-3 / ABC breakdown 15-Oct [no edge] | X13: Not checked | Y13: No edge either way for 1 year (buy-side model rank: 78th percentile; no proven signal active). Holders can keep; no fresh entry. Technicals: RSI 17; RS rating 1; -66% from 52-wk high; below a falling 200-DMA.
A14: TRITURBINE | B14: Triveni Turbine Ltd. | C14: Industrial Manufacturing | D14: Short term (up to 2 weeks) | E14: Buy | F14: Strong Buy | G14: 0.21183931 | H14: 0.11425674 | I14: 0.42819519 | J14: 0.0018773479 | K14: 5.7878251 | L14: 445.05 | M14: 17.831958 | N14: =ROUND(L14+'Read Me'!$D$30*M14,2) | O14: =ROUND(L14+'Read Me'!$C$30*M14,2) | P14: =ROUND(L14-'Read Me'!$B$30*M14,2) | Q14: =ABS(O14-L14)/L14 | R14: =ABS(L14-P14)/L14 | S14: 10 | T14: 6 | U14: Down | V14: Model rank: top 1% buy side / bottom 32% short side (buy bucket: Top 5%) | W14: ▼ Falling wedge - down breakout 19-Oct [no edge]; ▲ 2B bottom / Turtle soup 15-Oct [no edge]; ▲ Wyckoff spring 15-Oct [works in reverse]; ▲ Bullish AB=CD 13-Oct [no edge] | X14: Mixed | Y14: AI model ranks it in the top 1% of stocks for a 2-week buy. Historically, top-5% names hit the target 21% of the time vs 15% for the average stock (weighted to falling markets like now), averaging +0.2% per trade after costs. Technicals: RSI 20; RS rating 19; -43% from 52-wk high; below 20-EMA. Results Q1 FY27 (Apr-Jun 2026) - revenue: +19.2% to Rs 443 Cr; profit: -21% to Rs 51 Cr (mixed).
A15: TRITURBINE | B15: Triveni Turbine Ltd. | C15: Industrial Manufacturing | D15: Mid term (up to 3 months) | E15: Hold | F15: Hold / No fresh trade | G15: 0.31745648 | H15: 0.07441852 | I15: 0.50235869 | J15: 0.043229003 | K15: 4.3136018 | L15: 445.05 | M15: 17.831958 | U15: Down | V15: Model rank: top 2% buy side / bottom 18% short side (buy bucket: Top 5%) | W15: ▼ Falling wedge - down breakout 19-Oct [no edge]; ▲ 2B bottom / Turtle soup 15-Oct [no edge]; ▲ Wyckoff spring 15-Oct [works in reverse]; ▲ Bullish AB=CD 13-Oct [no edge] | X15: Mixed | Y15: The model ranks it in the top 2% for a 3-month buy, but at this horizon its top ranks have not beaten the average stock in falling markets, so that is not counted; no proven signal active. Holders can keep; no fresh entry. Technicals: RSI 20; RS rating 19; -43% from 52-wk high; below a falling 50-DMA. Results Q1 FY27 (Apr-Jun 2026) - revenue: +19.2% to Rs 443 Cr; profit: -21% to Rs 51 Cr (mixed).
A16: TRITURBINE | B16: Triveni Turbine Ltd. | C16: Industrial Manufacturing | D16: Long term (up to 1 year) | E16: Hold | F16: Hold / No fresh trade | G16: 0.38248096 | H16: 0.055927815 | I16: 0.53353852 | J16: 0.1286861 | K16: 0.71274827 | L16: 445.05 | M16: 17.831958 | U16: Down | V16: Model rank: bottom 43% buy side / bottom 26% short side (buy bucket: 20-50%) | W16: ▼ Falling wedge - down breakout 19-Oct [no edge]; ▲ 2B bottom / Turtle soup 15-Oct [no edge]; ▲ Wyckoff spring 15-Oct [works in reverse]; ▲ Bullish AB=CD 13-Oct [no edge] | X16: Mixed | Y16: No edge either way for 1 year (buy-side model rank: 43rd percentile; no proven signal active). Holders can keep; no fresh entry. Technicals: RSI 20; RS rating 19; -43% from 52-wk high; below a falling 200-DMA. Results Q1 FY27 (Apr-Jun 2026) - revenue: +19.2% to Rs 443 Cr; profit: -21% to Rs 51 Cr (mixed).
A17: EIDPARRY | B17: E.I.D. Parry (India) Ltd. | C17: Fertilisers & Pesticides | D17: Short term (up to 2 weeks) | E17: Buy | F17: Strong Buy | G17: 0.21183931 | H17: 0.14315289 | I17: 0.42819519 | J17: 0.0018773479 | K17: 5.7878251 | L17: 627.5 | M17: 20.020187 | N17: =ROUND(L17+'Read Me'!$D$30*M17,2) | O17: =ROUND(L17+'Read Me'!$C$30*M17,2) | P17: =ROUND(L17-'Read Me'!$B$30*M17,2) | Q17: =ABS(O17-L17)/L17 | R17: =ABS(L17-P17)/L17 | S17: 10 | T17: 6 | U17: Down | V17: Model rank: top 1% buy side / top 25% short side (buy bucket: Top 5%) | W17: ▼ P&F bearish descending breakdown 21-Oct [works in reverse]; ▲ 2B bottom / Turtle soup 19-Oct [no edge]; ▲ Downtrend-line breakout 12-Oct [works in reverse] | X17: Not checked | Y17: AI model ranks it in the top 1% of stocks for a 2-week buy. Historically, top-5% names hit the target 21% of the time vs 15% for the average stock (weighted to falling markets like now), averaging +0.2% per trade after costs. Technicals: RSI 28; RS rating 7; -44% from 52-wk high; below 20-EMA.
A18: EIDPARRY | B18: E.I.D. Parry (India) Ltd. | C18: Fertilisers & Pesticides | D18: Mid term (up to 3 months) | E18: Hold | F18: Hold / No fresh trade | G18: 0.28474942 | H18: 0.099596779 | I18: 0.49058663 | J18: 0.03589876 | K18: 1.0428963 | L18: 627.5 | M18: 20.020187 | U18: Down | V18: Model rank: top 20% buy side / bottom 37% short side (buy bucket: 70-85%) | W18: ▼ P&F bearish descending breakdown 21-Oct [works in reverse]; ▲ 2B bottom / Turtle soup 19-Oct [no edge]; ▲ Downtrend-line breakout 12-Oct [works in reverse] | X18: Not checked | Y18: No edge either way for 3 months (buy-side model rank: 80th percentile; no proven signal active). Holders can keep; no fresh entry. Technicals: RSI 28; RS rating 7; -44% from 52-wk high; below a falling 50-DMA.
A19: EIDPARRY | B19: E.I.D. Parry (India) Ltd. | C19: Fertilisers & Pesticides | D19: Long term (up to 1 year) | E19: Hold | F19: Hold / No fresh trade | G19: 0.37136452 | H19: 0.055927815 | I19: 0.51670509 | J19: 0.11597254 | K19: -0.39889565 | L19: 627.5 | M19: 20.020187 | U19: Down | V19: Model rank: top 27% buy side / bottom 43% short side (buy bucket: 70-85%) | W19: ▼ P&F bearish descending breakdown 21-Oct [works in reverse]; ▲ 2B bottom / Turtle soup 19-Oct [no edge]; ▲ Downtrend-line breakout 12-Oct [works in reverse] | X19: Not checked | Y19: No edge either way for 1 year (buy-side model rank: 73rd percentile; no proven signal active). Holders can keep; no fresh entry. Technicals: RSI 28; RS rating 7; -44% from 52-wk high; below a falling 200-DMA.
A20: NBCC | B20: NBCC (India) Ltd. | C20: Construction | D20: Short term (up to 2 weeks) | E20: Buy | F20: Strong Buy | G20: 0.21183931 | H20: 0.14315289 | I20: 0.42819519 | J20: 0.0018773479 | K20: 5.7878251 | L20: 67.9 | M20: 2.0767964 | N20: =ROUND(L20+'Read Me'!$D$30*M20,2) | O20: =ROUND(L20+'Read Me'!$C$30*M20,2) | P20: =ROUND(L20-'Read Me'!$B$30*M20,2) | Q20: =ABS(O20-L20)/L20 | R20: =ABS(L20-P20)/L20 | S20: 10 | T20: 6 | U20: Down | V20: Model rank: top 1% buy side / top 26% short side (buy bucket: Top 5%) | X20: Not checked | Y20: AI model ranks it in the top 1% of stocks for a 2-week buy. Historically, top-5% names hit the target 21% of the time vs 15% for the average stock (weighted to falling markets like now), averaging +0.2% per trade after costs. Technicals: RSI 22; RS rating 3; -46% from 52-wk high; below 20-EMA.
A21: NBCC | B21: NBCC (India) Ltd. | C21: Construction | D21: Mid term (up to 3 months) | E21: Hold | F21: Hold / No fresh trade | G21: 0.28353408 | H21: 0.099596779 | I21: 0.50020496 | J21: 0.038018651 | K21: 0.9213626 | L21: 67.9 | M21: 2.0767964 | U21: Down | V21: Model rank: top 36% buy side / bottom 25% short side (buy bucket: 50-70%) | X21: Not checked | Y21: No edge either way for 3 months (buy-side model rank: 64th percentile; no proven signal active). Holders can keep; no fresh entry. Technicals: RSI 22; RS rating 3; -46% from 52-wk high; below a falling 50-DMA.
A22: NBCC | B22: NBCC (India) Ltd. | C22: Construction | D22: Long term (up to 1 year) | E22: Hold | F22: Hold / No fresh trade | G22: 0.34676564 | H22: 0.055927815 | I22: 0.51568086 | J22: 0.11251406 | K22: -2.8587837 | L22: 67.9 | M22: 2.0767964 | U22: Down | V22: Model rank: bottom 43% buy side / bottom 24% short side (buy bucket: 20-50%); - RSI(14) rises back above 30 - fades (12-Oct): -1.6% vs avg stock, t 4.1 | X22: Not checked | Y22: No edge either way for 1 year (buy-side model rank: 43rd percentile; no proven signal active). Holders can keep; no fresh entry. Technicals: RSI 22; RS rating 3; -46% from 52-wk high; below a falling 200-DMA.
A23: GODFRYPHLP | B23: Godfrey Phillips India Ltd. | C23: Consumer Goods | D23: Short term (up to 2 weeks) | E23: Buy | F23: Strong Buy | G23: 0.21183931 | H23: 0.11425674 | I23: 0.42819519 | J23: 0.0018773479 | K23: 5.7878251 | L23: 1669 | M23: 55.242683 | N23: =ROUND(L23+'Read Me'!$D$30*M23,2) | O23: =ROUND(L23+'Read Me'!$C$30*M23,2) | P23: =ROUND(L23-'Read Me'!$B$30*M23,2) | Q23: =ABS(O23-L23)/L23 | R23: =ABS(L23-P23)/L23 | S23: 10 | T23: 6 | U23: Down | V23: Model rank: top 2% buy side / bottom 35% short side (buy bucket: Top 5%) | W23: ▼ Falling wedge - down breakout 22-Oct [no edge]; ▼ Hidden bearish divergence (MFI) 21-Oct [no edge]; ▼ Wave-3 / ABC breakdown 21-Oct [no edge]; ▲ Downtrend-line breakout 16-Oct [works in reverse] | X23: Not checked | Y23: AI model ranks it in the top 2% of stocks for a 2-week buy. Historically, top-5% names hit the target 21% of the time vs 15% for the average stock (weighted to falling markets like now), averaging +0.2% per trade after costs. Technicals: RSI 29; RS rating 7; -52% from 52-wk high; below 20-EMA.
A24: GODFRYPHLP | B24: Godfrey Phillips India Ltd. | C24: Consumer Goods | D24: Mid term (up to 3 months) | E24: Hold | F24: Hold / No fresh trade | G24: 0.28353408 | H24: 0.11434533 | I24: 0.50020496 | J24: 0.038018651 | K24: 0.9213626 | L24: 1669 | M24: 55.242683 | U24: Down | V24: Model rank: top 37% buy side / top 40% short side (buy bucket: 50-70%) | W24: ▼ Falling wedge - down breakout 22-Oct [no edge]; ▼ Hidden bearish divergence (MFI) 21-Oct [no edge]; ▼ Wave-3 / ABC breakdown 21-Oct [no edge]; ▲ Downtrend-line breakout 16-Oct [works in reverse] | X24: Not checked | Y24: No edge either way for 3 months (buy-side model rank: 63rd percentile; no proven signal active). Holders can keep; no fresh entry. Technicals: RSI 29; RS rating 7; -52% from 52-wk high; below a falling 50-DMA.
A25: GODFRYPHLP | B25: Godfrey Phillips India Ltd. | C25: Consumer Goods | D25: Long term (up to 1 year) | E25: Hold | F25: Hold / No fresh trade | G25: 0.34676564 | H25: 0.071868264 | I25: 0.51568086 | J25: 0.11251406 | K25: -2.8587837 | L25: 1669 | M25: 55.242683 | U25: Down | V25: Model rank: bottom 26% buy side / top 32% short side (buy bucket: 20-50%); - RSI(14) rises back above 30 - fades (09-Oct): -1.6% vs avg stock, t 4.1 | W25: ▼ Falling wedge - down breakout 22-Oct [no edge]; ▼ Hidden bearish divergence (MFI) 21-Oct [no edge]; ▼ Wave-3 / ABC breakdown 21-Oct [no edge]; ▲ Downtrend-line breakout 16-Oct [works in reverse] | X25: Not checked | Y25: No edge either way for 1 year (buy-side model rank: 26th percentile; no proven signal active). Holders can keep; no fresh entry. Technicals: RSI 29; RS rating 7; -52% from 52-wk high; below a falling 200-DMA.
A26: GMDCLTD | B26: Gujarat Mineral Development Corporation Ltd. | C26: Metals | D26: Short term (up to 2 weeks) | E26: Buy | F26: Strong Buy | G26: 0.21183931 | H26: 0.13461342 | I26: 0.42819519 | J26: 0.0018773479 | K26: 5.7878251 | L26: 424.6 | M26: 15.382904 | N26: =ROUND(L26+'Read Me'!$D$30*M26,2) | O26: =ROUND(L26+'Read Me'!$C$30*M26,2) | P26: =ROUND(L26-'Read Me'!$B$30*M26,2) | Q26: =ABS(O26-L26)/L26 | R26: =ABS(L26-P26)/L26 | S26: 10 | T26: 6 | U26: Down | V26: Model rank: top 2% buy side / top 47% short side (buy bucket: Top 5%) | W26: ▼ Bear flag 21-Oct [works in reverse]; ▲ 2B bottom / Turtle soup 19-Oct [no edge] | X26: Not checked | Y26: AI model ranks it in the top 2% of stocks for a 2-week buy. Historically, top-5% names hit the target 21% of the time vs 15% for the average stock (weighted to falling markets like now), averaging +0.2% per trade after costs. Technicals: RSI 21; RS rating 6; -45% from 52-wk high; below 20-EMA.
A27: GMDCLTD | B27: Gujarat Mineral Development Corporation Ltd. | C27: Metals | D27: Mid term (up to 3 months) | E27: Hold | F27: Hold / No fresh trade | G27: 0.28353408 | H27: 0.099596779 | I27: 0.50020496 | J27: 0.038018651 | K27: 0.9213626 | L27: 424.6 | M27: 15.382904 | U27: Down | V27: Model rank: top 32% buy side / bottom 42% short side (buy bucket: 50-70%) | W27: ▼ Bear flag 21-Oct [works in reverse]; ▲ 2B bottom / Turtle soup 19-Oct [no edge] | X27: Not checked | Y27: No edge either way for 3 months (buy-side model rank: 68th percentile; no proven signal active). Holders can keep; no fresh entry. Technicals: RSI 21; RS rating 6; -45% from 52-wk high; below a falling 50-DMA.
A28: GMDCLTD | B28: Gujarat Mineral Development Corporation Ltd. | C28: Metals | D28: Long term (up to 1 year) | E28: Hold | F28: Hold / No fresh trade | G28: 0.35529798 | H28: 0.055927815 | I28: 0.51111196 | J28: 0.10959171 | K28: -2.00555 | L28: 424.6 | M28: 15.382904 | U28: Down | V28: Model rank: top 38% buy side / bottom 22% short side (buy bucket: 50-70%); - RSI(14) rises back above 30 - fades (16-Oct): -1.6% vs avg stock, t 4.1 | W28: ▼ Bear flag 21-Oct [works in reverse]; ▲ 2B bottom / Turtle soup 19-Oct [no edge] | X28: Not checked | Y28: No edge either way for 1 year (buy-side model rank: 62nd percentile; no proven signal active). Holders can keep; no fresh entry. Technicals: RSI 21; RS rating 6; -45% from 52-wk high; below a falling 200-DMA.
A29: OLECTRA | B29: Olectra Greentech Ltd. | C29: Automobile | D29: Short term (up to 2 weeks) | E29: Buy | F29: Strong Buy | G29: 0.21183931 | H29: 0.11425674 | I29: 0.42819519 | J29: 0.0018773479 | K29: 5.7878251 | L29: 955.7 | M29: 36.002199 | N29: =ROUND(L29+'Read Me'!$D$30*M29,2) | O29: =ROUND(L29+'Read Me'!$C$30*M29,2) | P29: =ROUND(L29-'Read Me'!$B$30*M29,2) | Q29: =ABS(O29-L29)/L29 | R29: =ABS(L29-P29)/L29 | S29: 10 | T29: 6 | U29: Down | V29: Model rank: top 2% buy side / bottom 30% short side (buy bucket: Top 5%) | W29: ▼ Bear pennant 21-Oct [no edge] | X29: Not checked | Y29: AI model ranks it in the top 2% of stocks for a 2-week buy. Historically, top-5% names hit the target 21% of the time vs 15% for the average stock (weighted to falling markets like now), averaging +0.2% per trade after costs. Technicals: RSI 23; RS rating 9; -39% from 52-wk high; below 20-EMA.
A30: OLECTRA | B30: Olectra Greentech Ltd. | C30: Automobile | D30: Mid term (up to 3 months) | E30: Hold | F30: Hold / No fresh trade | G30: 0.31745648 | H30: 0.099596779 | I30: 0.50235869 | J30: 0.043229003 | K30: 4.3136018 | L30: 955.7 | M30: 36.002199 | U30: Down | V30: Model rank: top 1% buy side / bottom 26% short side (buy bucket: Top 5%) | W30: ▼ Bear pennant 21-Oct [no edge] | X30: Not checked | Y30: The model ranks it in the top 1% for a 3-month buy, but at this horizon its top ranks have not beaten the average stock in falling markets, so that is not counted; no proven signal active. Holders can keep; no fresh entry. Technicals: RSI 23; RS rating 9; -39% from 52-wk high; below a falling 50-DMA.
A31: OLECTRA | B31: Olectra Greentech Ltd. | C31: Automobile | D31: Long term (up to 1 year) | E31: Hold | F31: Hold / No fresh trade | G31: 0.35529798 | H31: 0.055927815 | I31: 0.51111196 | J31: 0.10959171 | K31: -2.00555 | L31: 955.7 | M31: 36.002199 | U31: Down | V31: Model rank: top 35% buy side / bottom 27% short side (buy bucket: 50-70%); - RSI(14) rises back above 30 - fades (13-Oct): -1.6% vs avg stock, t 4.1 | W31: ▼ Bear pennant 21-Oct [no edge] | X31: Not checked | Y31: No edge either way for 1 year (buy-side model rank: 65th percentile; no proven signal active). Holders can keep; no fresh entry. Technicals: RSI 23; RS rating 9; -39% from 52-wk high; below a falling 200-DMA.
A32: THERMAX | B32: Thermax Ltd. | C32: Industrial Manufacturing | D32: Short term (up to 2 weeks) | E32: Buy | F32: Strong Buy | G32: 0.21183931 | H32: 0.11425674 | I32: 0.42819519 | J32: 0.0018773479 | K32: 5.7878251 | L32: 3096 | M32: 112.3196 | N32: =ROUND(L32+'Read Me'!$D$30*M32,2) | O32: =ROUND(L32+'Read Me'!$C$30*M32,2) | P32: =ROUND(L32-'Read Me'!$B$30*M32,2) | Q32: =ABS(O32-L32)/L32 | R32: =ABS(L32-P32)/L32 | S32: 10 | T32: 6 | U32: Down | V32: Model rank: top 2% buy side / bottom 43% short side (buy bucket: Top 5%) | W32: ▼ P&F bearish descending breakdown 23-Oct [works in reverse]; ▲ 2B bottom / Turtle soup 21-Oct [no edge]; ▼ Hidden bearish divergence (MACD hist) 21-Oct [no edge]; ▼ Hidden bearish divergence (MFI) 21-Oct [no edge] | X32: Negative | Y32: AI model ranks it in the top 2% of stocks for a 2-week buy. Historically, top-5% names hit the target 21% of the time vs 15% for the average stock (weighted to falling markets like now), averaging +0.2% per trade after costs. Technicals: RSI 31; RS rating 28; -41% from 52-wk high; below 20-EMA. Results Q1 FY27 (Apr-Jun 2026) - revenue: +7% to Rs 2,303 Cr; profit: -83% to about Rs 25 Cr (negative).
A33: THERMAX | B33: Thermax Ltd. | C33: Industrial Manufacturing | D33: Mid term (up to 3 months) | E33: Hold | F33: Hold / No fresh trade | G33: 0.31745648 | H33: 0.099596779 | I33: 0.50235869 | J33: 0.043229003 | K33: 4.3136018 | L33: 3096 | M33: 112.3196 | U33: Down | V33: Model rank: top 4% buy side / bottom 27% short side (buy bucket: Top 5%) | W33: ▼ P&F bearish descending breakdown 23-Oct [works in reverse]; ▲ 2B bottom / Turtle soup 21-Oct [no edge]; ▼ Hidden bearish divergence (MACD hist) 21-Oct [no edge]; ▼ Hidden bearish divergence (MFI) 21-Oct [no edge] | X33: Negative | Y33: The model ranks it in the top 4% for a 3-month buy, but at this horizon its top ranks have not beaten the average stock in falling markets, so that is not counted; no proven signal active. Holders can keep; no fresh entry. Technicals: RSI 31; RS rating 28; -41% from 52-wk high; below a falling 50-DMA. Results Q1 FY27 (Apr-Jun 2026) - revenue: +7% to Rs 2,303 Cr; profit: -83% to about Rs 25 Cr (negative).
A34: THERMAX | B34: Thermax Ltd. | C34: Industrial Manufacturing | D34: Long term (up to 1 year) | E34: Hold | F34: Hold / No fresh trade | G34: 0.34676564 | H34: 0.055927815 | I34: 0.51568086 | J34: 0.11251406 | K34: -2.8587837 | L34: 3096 | M34: 112.3196 | U34: Sideways | V34: Model rank: bottom 38% buy side / bottom 48% short side (buy bucket: 20-50%); - RSI(14) rises back above 30 - fades (09-Oct): -1.6% vs avg stock, t 4.1 | W34: ▼ P&F bearish descending breakdown 23-Oct [works in reverse]; ▲ 2B bottom / Turtle soup 21-Oct [no edge]; ▼ Hidden bearish divergence (MACD hist) 21-Oct [no edge]; ▼ Hidden bearish divergence (MFI) 21-Oct [no edge] | X34: Negative | Y34: No edge either way for 1 year (buy-side model rank: 38th percentile; no proven signal active). Holders can keep; no fresh entry. Technicals: RSI 31; RS rating 28; -41% from 52-wk high; below a rising 200-DMA. Results Q1 FY27 (Apr-Jun 2026) - revenue: +7% to Rs 2,303 Cr; profit: -83% to about Rs 25 Cr (negative).
A35: VOLTAS | B35: Voltas Ltd. | C35: Consumer Goods | D35: Short term (up to 2 weeks) | E35: Buy | F35: Strong Buy | G35: 0.21183931 | H35: 0.13461342 | I35: 0.42819519 | J35: 0.0018773479 | K35: 5.7878251 | L35: 950 | M35: 31.002142 | N35: =ROUND(L35+'Read Me'!$D$30*M35,2) | O35: =ROUND(L35+'Read Me'!$C$30*M35,2) | P35: =ROUND(L35-'Read Me'!$B$30*M35,2) | Q35: =ABS(O35-L35)/L35 | R35: =ABS(L35-P35)/L35 | S35: 10 | T35: 6 | U35: Down | V35: Model rank: top 3% buy side / top 43% short side (buy bucket: Top 5%) | W35: ▼ Bear flag 21-Oct [works in reverse] | X35: Not checked | Y35: AI model ranks it in the top 3% of stocks for a 2-week buy. Historically, top-5% names hit the target 21% of the time vs 15% for the average stock (weighted to falling markets like now), averaging +0.2% per trade after costs. Technicals: RSI 24; RS rating 3; -40% from 52-wk high; below 20-EMA.
A36: VOLTAS | B36: Voltas Ltd. | C36: Consumer Goods | D36: Mid term (up to 3 months) | E36: Hold | F36: Hold / No fresh trade | G36: 0.28353408 | H36: 0.099596779 | I36: 0.50020496 | J36: 0.038018651 | K36: 0.9213626 | L36: 950 | M36: 31.002142 | U36: Down | V36: Model rank: top 46% buy side / bottom 25% short side (buy bucket: 50-70%) | W36: ▼ Bear flag 21-Oct [works in reverse] | X36: Not checked | Y36: No edge either way for 3 months (buy-side model rank: 54th percentile; no proven signal active). Holders can keep; no fresh entry. Technicals: RSI 24; RS rating 3; -40% from 52-wk high; below a falling 50-DMA.
A37: VOLTAS | B37: Voltas Ltd. | C37: Consumer Goods | D37: Long term (up to 1 year) | E37: Hold | F37: Hold / No fresh trade | G37: 0.32912876 | H37: 0.071868264 | I37: 0.51140418 | J37: 0.11040694 | K37: -4.6224715 | L37: 950 | M37: 31.002142 | U37: Down | V37: Model rank: bottom 6% buy side / top 48% short side (buy bucket: Bottom 20%); - RSI(14) rises back above 30 - fades (13-Oct): -1.6% vs avg stock, t 4.1 | W37: ▼ Bear flag 21-Oct [works in reverse] | X37: Not checked | Y37: No edge either way for 1 year (buy-side model rank: 6th percentile; no proven signal active). Holders can keep; no fresh entry. Technicals: RSI 24; RS rating 3; -40% from 52-wk high; below a falling 200-DMA.
A38: AVANTIFEED | B38: Avanti Feeds Ltd. | C38: Fast Moving Consumer Goods | D38: Short term (up to 2 weeks) | E38: Buy | F38: Strong Buy | G38: 0.21183931 | H38: 0.14315289 | I38: 0.42819519 | J38: 0.0018773479 | K38: 5.7878251 | L38: 675.7 | M38: 23.153853 | N38: =ROUND(L38+'Read Me'!$D$30*M38,2) | O38: =ROUND(L38+'Read Me'!$C$30*M38,2) | P38: =ROUND(L38-'Read Me'!$B$30*M38,2) | Q38: =ABS(O38-L38)/L38 | R38: =ABS(L38-P38)/L38 | S38: 10 | T38: 6 | U38: Down | V38: Model rank: top 3% buy side / top 16% short side (buy bucket: Top 5%) | W38: ▲ Downtrend-line breakout 14-Oct [works in reverse]; ▲ Falling wedge - up breakout 14-Oct [no edge]; ▲ 2B bottom / Turtle soup 12-Oct [no edge] | X38: Not checked | Y38: AI model ranks it in the top 3% of stocks for a 2-week buy. Historically, top-5% names hit the target 21% of the time vs 15% for the average stock (weighted to falling markets like now), averaging +0.2% per trade after costs. Technicals: RSI 28; RS rating 9; -58% from 52-wk high; below 20-EMA; delivery % falling (-6 pts vs 20-day).
A39: AVANTIFEED | B39: Avanti Feeds Ltd. | C39: Fast Moving Consumer Goods | D39: Mid term (up to 3 months) | E39: Hold | F39: Hold / No fresh trade | G39: 0.31745648 | H39: 0.099596779 | I39: 0.50235869 | J39: 0.043229003 | K39: 4.3136018 | L39: 675.7 | M39: 23.153853 | U39: Down | V39: Model rank: top 3% buy side / bottom 48% short side (buy bucket: Top 5%) | W39: ▲ Downtrend-line breakout 14-Oct [works in reverse]; ▲ Falling wedge - up breakout 14-Oct [no edge]; ▲ 2B bottom / Turtle soup 12-Oct [no edge] | X39: Not checked | Y39: The model ranks it in the top 3% for a 3-month buy, but at this horizon its top ranks have not beaten the average stock in falling markets, so that is not counted; no proven signal active. Holders can keep; no fresh entry. Technicals: RSI 28; RS rating 9; -58% from 52-wk high; below a falling 50-DMA; delivery % falling (-6 pts vs 20-day).
A40: AVANTIFEED | B40: Avanti Feeds Ltd. | C40: Fast Moving Consumer Goods | D40: Long term (up to 1 year) | E40: Hold | F40: Hold / No fresh trade | G40: 0.35529798 | H40: 0.071868264 | I40: 0.51111196 | J40: 0.10959171 | K40: -2.00555 | L40: 675.7 | M40: 23.153853 | U40: Down | V40: Model rank: top 46% buy side / top 36% short side (buy bucket: 50-70%); - RSI(14) rises back above 30 - fades (12-Oct): -1.6% vs avg stock, t 4.1 | W40: ▲ Downtrend-line breakout 14-Oct [works in reverse]; ▲ Falling wedge - up breakout 14-Oct [no edge]; ▲ 2B bottom / Turtle soup 12-Oct [no edge] | X40: Not checked | Y40: No edge either way for 1 year (buy-side model rank: 54th percentile; no proven signal active). Holders can keep; no fresh entry. Technicals: RSI 28; RS rating 9; -58% from 52-wk high; below a falling 200-DMA; delivery % falling (-6 pts vs 20-day).
A41: ATGL | B41: Adani Total Gas Ltd. | C41: Energy | D41: Short term (up to 2 weeks) | E41: Buy | F41: Strong Buy | G41: 0.21183931 | H41: 0.11425674 | I41: 0.42819519 | J41: 0.0018773479 | K41: 5.7878251 | L41: 529.5 | M41: 17.262044 | N41: =ROUND(L41+'Read Me'!$D$30*M41,2) | O41: =ROUND(L41+'Read Me'!$C$30*M41,2) | P41: =ROUND(L41-'Read Me'!$B$30*M41,2) | Q41: =ABS(O41-L41)/L41 | R41: =ABS(L41-P41)/L41 | S41: 10 | T41: 6 | U41: Down | V41: Model rank: top 3% buy side / bottom 35% short side (buy bucket: Top 5%) | W41: ▲ Bullish AB=CD 14-Oct [no edge]; ▲ Bullish Wolfe wave 14-Oct [no edge] | X41: Not checked | Y41: AI model ranks it in the top 3% of stocks for a 2-week buy. Historically, top-5% names hit the target 21% of the time vs 15% for the average stock (weighted to falling markets like now), averaging +0.2% per trade after costs. Technicals: RSI 28; RS rating 34; -38% from 52-wk high; below 20-EMA.
A42: ATGL | B42: Adani Total Gas Ltd. | C42: Energy | D42: Mid term (up to 3 months) | E42: Hold | F42: Hold / No fresh trade | G42: 0.28353408 | H42: 0.099596779 | I42: 0.50020496 | J42: 0.038018651 | K42: 0.9213626 | L42: 529.5 | M42: 17.262044 | U42: Down | V42: Model rank: top 31% buy side / bottom 25% short side (buy bucket: 50-70%) | W42: ▲ Bullish AB=CD 14-Oct [no edge]; ▲ Bullish Wolfe wave 14-Oct [no edge] | X42: Not checked | Y42: No edge either way for 3 months (buy-side model rank: 69th percentile; no proven signal active). Holders can keep; no fresh entry. Technicals: RSI 28; RS rating 34; -38% from 52-wk high; below a falling 50-DMA.
A43: ATGL | B43: Adani Total Gas Ltd. | C43: Energy | D43: Long term (up to 1 year) | E43: Hold | F43: Hold / No fresh trade | G43: 0.3910133 | H43: 0.055927815 | I43: 0.52896962 | J43: 0.12576374 | K43: 1.5659819 | L43: 529.5 | M43: 17.262044 | U43: Down | V43: Model rank: top 36% buy side / bottom 21% short side (buy bucket: 50-70%) | W43: ▲ Bullish AB=CD 14-Oct [no edge]; ▲ Bullish Wolfe wave 14-Oct [no edge] | X43: Not checked | Y43: No edge either way for 1 year (buy-side model rank: 64th percentile; no proven signal active). Holders can keep; no fresh entry. Technicals: RSI 28; RS rating 34; -38% from 52-wk high; below a falling 200-DMA.
A44: CESC | B44: CESC Ltd. | C44: Energy | D44: Short term (up to 2 weeks) | E44: Buy | F44: Strong Buy | G44: 0.21183931 | H44: 0.13461342 | I44: 0.42819519 | J44: 0.0018773479 | K44: 5.7878251 | L44: 124.79 | M44: 3.7883639 | N44: =ROUND(L44+'Read Me'!$D$30*M44,2) | O44: =ROUND(L44+'Read Me'!$C$30*M44,2) | P44: =ROUND(L44-'Read Me'!$B$30*M44,2) | Q44: =ABS(O44-L44)/L44 | R44: =ABS(L44-P44)/L44 | S44: 10 | T44: 6 | U44: Down | V44: Model rank: top 3% buy side / top 44% short side (buy bucket: Top 5%) | W44: ▼ P&F bearish descending breakdown 23-Oct [works in reverse]; ▲ 2B bottom / Turtle soup 09-Oct [no edge]; ▲ Downtrend-line breakout 09-Oct [works in reverse]; ▲ Falling wedge - up breakout 09-Oct [no edge] | X44: Not checked | Y44: AI model ranks it in the top 3% of stocks for a 2-week buy. Historically, top-5% names hit the target 21% of the time vs 15% for the average stock (weighted to falling markets like now), averaging +0.2% per trade after costs. Technicals: RSI 28; RS rating 9; -39% from 52-wk high; below 20-EMA.
A45: CESC | B45: CESC Ltd. | C45: Energy | D45: Mid term (up to 3 months) | E45: Hold | F45: Hold / No fresh trade | G45: 0.28353408 | H45: 0.099596779 | I45: 0.50020496 | J45: 0.038018651 | K45: 0.9213626 | L45: 124.79 | M45: 3.7883639 | U45: Down | V45: Model rank: top 36% buy side / bottom 33% short side (buy bucket: 50-70%) | W45: ▼ P&F bearish descending breakdown 23-Oct [works in reverse]; ▲ 2B bottom / Turtle soup 09-Oct [no edge]; ▲ Downtrend-line breakout 09-Oct [works in reverse]; ▲ Falling wedge - up breakout 09-Oct [no edge] | X45: Not checked | Y45: No edge either way for 3 months (buy-side model rank: 64th percentile; no proven signal active). Holders can keep; no fresh entry. Technicals: RSI 28; RS rating 9; -39% from 52-wk high; below a falling 50-DMA.
A46: CESC | B46: CESC Ltd. | C46: Energy | D46: Long term (up to 1 year) | E46: Hold | F46: Hold / No fresh trade | G46: 0.35529798 | H46: 0.055927815 | I46: 0.51111196 | J46: 0.10959171 | K46: -2.00555 | L46: 124.79 | M46: 3.7883639 | U46: Down | V46: Model rank: top 38% buy side / bottom 49% short side (buy bucket: 50-70%); - RSI(14) rises back above 30 - fades (09-Oct): -1.6% vs avg stock, t 4.1 | W46: ▼ P&F bearish descending breakdown 23-Oct [works in reverse]; ▲ 2B bottom / Turtle soup 09-Oct [no edge]; ▲ Downtrend-line breakout 09-Oct [works in reverse]; ▲ Falling wedge - up breakout 09-Oct [no edge] | X46: Not checked | Y46: No edge either way for 1 year (buy-side model rank: 62nd percentile; no proven signal active). Holders can keep; no fresh entry. Technicals: RSI 28; RS rating 9; -39% from 52-wk high; below a falling 200-DMA.
A47: KEC | B47: Kec International Ltd. | C47: Construction | D47: Short term (up to 2 weeks) | E47: Buy | F47: Strong Buy | G47: 0.21183931 | H47: 0.11425674 | I47: 0.42819519 | J47: 0.0018773479 | K47: 5.7878251 | L47: 327.75 | M47: 12.159844 | N47: =ROUND(L47+'Read Me'!$D$30*M47,2) | O47: =ROUND(L47+'Read Me'!$C$30*M47,2) | P47: =ROUND(L47-'Read Me'!$B$30*M47,2) | Q47: =ABS(O47-L47)/L47 | R47: =ABS(L47-P47)/L47 | S47: 10 | T47: 6 | U47: Down | V47: Model rank: top 4% buy side / bottom 36% short side (buy bucket: Top 5%) | W47: ▼ P&F bearish descending breakdown 19-Oct [works in reverse]; ▼ Wave-3 / ABC breakdown 19-Oct [no edge]; ▼ Hidden bearish divergence (MFI) 12-Oct [no edge]; ▼ Hidden bearish divergence (OBV) 12-Oct [no edge] | X47: Not checked | Y47: AI model ranks it in the top 4% of stocks for a 2-week buy. Historically, top-5% names hit the target 21% of the time vs 15% for the average stock (weighted to falling markets like now), averaging +0.2% per trade after costs. Technicals: RSI 25; RS rating 1; -62% from 52-wk high; below 20-EMA.
A48: KEC | B48: Kec International Ltd. | C48: Construction | D48: Mid term (up to 3 months) | E48: Hold | F48: Hold / No fresh trade | G48: 0.31745648 | H48: 0.07441852 | I48: 0.50235869 | J48: 0.043229003 | K48: 4.3136018 | L48: 327.75 | M48: 12.159844 | U48: Down | V48: Model rank: top 1% buy side / bottom 19% short side (buy bucket: Top 5%) | W48: ▼ P&F bearish descending breakdown 19-Oct [works in reverse]; ▼ Wave-3 / ABC breakdown 19-Oct [no edge]; ▼ Hidden bearish divergence (MFI) 12-Oct [no edge]; ▼ Hidden bearish divergence (OBV) 12-Oct [no edge] | X48: Not checked | Y48: The model ranks it in the top 1% for a 3-month buy, but at this horizon its top ranks have not beaten the average stock in falling markets, so that is not counted; no proven signal active. Holders can keep; no fresh entry. Technicals: RSI 25; RS rating 1; -62% from 52-wk high; below a falling 50-DMA.
A49: KEC | B49: Kec International Ltd. | C49: Construction | D49: Long term (up to 1 year) | E49: Hold | F49: Hold / No fresh trade | G49: 0.34676564 | H49: 0.055927815 | I49: 0.51568086 | J49: 0.11251406 | K49: -2.8587837 | L49: 327.75 | M49: 12.159844 | U49: Down | V49: Model rank: bottom 36% buy side / bottom 38% short side (buy bucket: 20-50%); - RSI(14) rises back above 30 - fades (09-Oct): -1.6% vs avg stock, t 4.1 | W49: ▼ P&F bearish descending breakdown 19-Oct [works in reverse]; ▼ Wave-3 / ABC breakdown 19-Oct [no edge]; ▼ Hidden bearish divergence (MFI) 12-Oct [no edge]; ▼ Hidden bearish divergence (OBV) 12-Oct [no edge] | X49: Not checked | Y49: No edge either way for 1 year (buy-side model rank: 36th percentile; no proven signal active). Holders can keep; no fresh entry. Technicals: RSI 25; RS rating 1; -62% from 52-wk high; below a falling 200-DMA.
A50: TITAGARH | B50: Titagarh Rail Systems Ltd. | C50: Industrial Manufacturing | D50: Short term (up to 2 weeks) | E50: Buy | F50: Strong Buy | G50: 0.21183931 | H50: 0.11425674 | I50: 0.42819519 | J50: 0.0018773479 | K50: 5.7878251 | L50: 663.35 | M50: 25.307721 | N50: =ROUND(L50+'Read Me'!$D$30*M50,2) | O50: =ROUND(L50+'Read Me'!$C$30*M50,2) | P50: =ROUND(L50-'Read Me'!$B$30*M50,2) | Q50: =ABS(O50-L50)/L50 | R50: =ABS(L50-P50)/L50 | S50: 10 | T50: 6 | U50: Down | V50: Model rank: top 4% buy side / bottom 40% short side (buy bucket: Top 5%) | W50: ▲ Wyckoff spring 13-Oct [works in reverse] | X50: Not checked | Y50: AI model ranks it in the top 4% of stocks for a 2-week buy. Historically, top-5% names hit the target 21% of the time vs 15% for the average stock (weighted to falling markets like now), averaging +0.2% per trade after costs. Technicals: RSI 14; RS rating 25; -32% from 52-wk high; below 20-EMA; delivery % rising (+6 pts vs 20-day).
A51: TITAGARH | B51: Titagarh Rail Systems Ltd. | C51: Industrial Manufacturing | D51: Mid term (up to 3 months) | E51: Hold | F51: Hold / No fresh trade | G51: 0.31745648 | H51: 0.11434533 | I51: 0.50235869 | J51: 0.043229003 | K51: 4.3136018 | L51: 663.35 | M51: 25.307721 | U51: Down | V51: Model rank: top 3% buy side / top 46% short side (buy bucket: Top 5%) | W51: ▲ Wyckoff spring 13-Oct [works in reverse] | X51: Not checked | Y51: The model ranks it in the top 3% for a 3-month buy, but at this horizon its top ranks have not beaten the average stock in falling markets, so that is not counted; no proven signal active. Holders can keep; no fresh entry. Technicals: RSI 14; RS rating 25; -32% from 52-wk high; below a falling 50-DMA; delivery % rising (+6 pts vs 20-day).
A52: TITAGARH | B52: Titagarh Rail Systems Ltd. | C52: Industrial Manufacturing | D52: Long term (up to 1 year) | E52: Hold | F52: Hold / No fresh trade | G52: 0.37136452 | H52: 0.071868264 | I52: 0.51670509 | J52: 0.11597254 | K52: -0.39889565 | L52: 663.35 | M52: 25.307721 | U52: Down | V52: Model rank: top 20% buy side / top 49% short side (buy bucket: 70-85%) | W52: ▲ Wyckoff spring 13-Oct [works in reverse] | X52: Not checked | Y52: No edge either way for 1 year (buy-side model rank: 80th percentile; no proven signal active). Holders can keep; no fresh entry. Technicals: RSI 14; RS rating 25; -32% from 52-wk high; below a falling 200-DMA; delivery % rising (+6 pts vs 20-day).
A53: RVNL | B53: Rail Vikas Nigam Ltd. | C53: Construction | D53: Short term (up to 2 weeks) | E53: Buy | F53: Strong Buy | G53: 0.21183931 | H53: 0.14315289 | I53: 0.42819519 | J53: 0.0018773479 | K53: 5.7878251 | L53: 181.31 | M53: 6.0295042 | N53: =ROUND(L53+'Read Me'!$D$30*M53,2) | O53: =ROUND(L53+'Read Me'!$C$30*M53,2) | P53: =ROUND(L53-'Read Me'!$B$30*M53,2) | Q53: =ABS(O53-L53)/L53 | R53: =ABS(L53-P53)/L53 | S53: 10 | T53: 6 | U53: Down | V53: Model rank: top 4% buy side / top 23% short side (buy bucket: Top 5%) | W53: ▼ Wave-3 / ABC breakdown 23-Oct [no edge]; ▼ P&F bearish descending breakdown 22-Oct [works in reverse]; ▲ 2B bottom / Turtle soup 21-Oct [no edge]; ▼ Hidden bearish divergence (MACD hist) 21-Oct [no edge] | X53: Not checked | Y53: AI model ranks it in the top 4% of stocks for a 2-week buy. Historically, top-5% names hit the target 21% of the time vs 15% for the average stock (weighted to falling markets like now), averaging +0.2% per trade after costs. Technicals: RSI 31; RS rating 2; -55% from 52-wk high; below 20-EMA.
A54: RVNL | B54: Rail Vikas Nigam Ltd. | C54: Construction | D54: Mid term (up to 3 months) | E54: Hold | F54: Hold / No fresh trade | G54: 0.29501647 | H54: 0.11434533 | I54: 0.49617973 | J54: 0.039061651 | K54: 2.0696017 | L54: 181.31 | M54: 6.0295042 | U54: Down | V54: Model rank: top 9% buy side / top 49% short side (buy bucket: Top 15% (85-95%)) | W54: ▼ Wave-3 / ABC breakdown 23-Oct [no edge]; ▼ P&F bearish descending breakdown 22-Oct [works in reverse]; ▲ 2B bottom / Turtle soup 21-Oct [no edge]; ▼ Hidden bearish divergence (MACD hist) 21-Oct [no edge] | X54: Not checked | Y54: The model ranks it in the top 9% for a 3-month buy, but at this horizon its top ranks have not beaten the average stock in falling markets, so that is not counted; no proven signal active. Holders can keep; no fresh entry. Technicals: RSI 31; RS rating 2; -55% from 52-wk high; below a falling 50-DMA.
A55: RVNL | B55: Rail Vikas Nigam Ltd. | C55: Construction | D55: Long term (up to 1 year) | E55: Hold | F55: Hold / No fresh trade | G55: 0.3910133 | H55: 0.055927815 | I55: 0.52896962 | J55: 0.12576374 | K55: 1.5659819 | L55: 181.31 | M55: 6.0295042 | U55: Down | V55: Model rank: top 42% buy side / bottom 22% short side (buy bucket: 50-70%) | W55: ▼ Wave-3 / ABC breakdown 23-Oct [no edge]; ▼ P&F bearish descending breakdown 22-Oct [works in reverse]; ▲ 2B bottom / Turtle soup 21-Oct [no edge]; ▼ Hidden bearish divergence (MACD hist) 21-Oct [no edge] | X55: Not checked | Y55: No edge either way for 1 year (buy-side model rank: 58th percentile; no proven signal active). Holders can keep; no fresh entry. Technicals: RSI 31; RS rating 2; -55% from 52-wk high; below a falling 200-DMA.
A56: AIAENG | B56: AIA Engineering Ltd. | C56: Industrial Manufacturing | D56: Short term (up to 2 weeks) | E56: Buy | F56: Strong Buy | G56: 0.21183931 | H56: 0.14315289 | I56: 0.42819519 | J56: 0.0018773479 | K56: 5.7878251 | L56: 3579.2 | M56: 110.56707 | N56: =ROUND(L56+'Read Me'!$D$30*M56,2) | O56: =ROUND(L56+'Read Me'!$C$30*M56,2) | P56: =ROUND(L56-'Read Me'!$B$30*M56,2) | Q56: =ABS(O56-L56)/L56 | R56: =ABS(L56-P56)/L56 | S56: 10 | T56: 6 | U56: Down | V56: Model rank: top 5% buy side / top 18% short side (buy bucket: Top 5%) | W56: ▲ 2B bottom / Turtle soup 15-Oct [no edge]; ▼ Horizontal support breakdown (3+ touches) 15-Oct [weak edge]; ▲ Bullish Wolfe wave 12-Oct [no edge]; ▼ P&F bearish descending breakdown 09-Oct [works in reverse] | X56: Not checked | Y56: AI model ranks it in the top 5% of stocks for a 2-week buy. Historically, top-5% names hit the target 21% of the time vs 15% for the average stock (weighted to falling markets like now), averaging +0.2% per trade after costs. Technicals: RSI 30; RS rating 47; -31% from 52-wk high; below 20-EMA.
A57: AIAENG | B57: AIA Engineering Ltd. | C57: Industrial Manufacturing | D57: Mid term (up to 3 months) | E57: Hold | F57: Hold / No fresh trade | G57: 0.28474942 | H57: 0.11434533 | I57: 0.49058663 | J57: 0.03589876 | K57: 1.0428963 | L57: 3579.2 | M57: 110.56707 | U57: Down | V57: Model rank: top 30% buy side / top 44% short side (buy bucket: 70-85%) | W57: ▲ 2B bottom / Turtle soup 15-Oct [no edge]; ▼ Horizontal support breakdown (3+ touches) 15-Oct [weak edge]; ▲ Bullish Wolfe wave 12-Oct [no edge]; ▼ P&F bearish descending breakdown 09-Oct [works in reverse] | X57: Not checked | Y57: No edge either way for 3 months (buy-side model rank: 70th percentile; no proven signal active). Holders can keep; no fresh entry. Technicals: RSI 30; RS rating 47; -31% from 52-wk high; below a falling 50-DMA.
A58: AIAENG | B58: AIA Engineering Ltd. | C58: Industrial Manufacturing | D58: Long term (up to 1 year) | E58: Hold | F58: Hold / No fresh trade | G58: 0.35529798 | H58: 0.085280983 | I58: 0.51111196 | J58: 0.10959171 | K58: -2.00555 | L58: 3579.2 | M58: 110.56707 | U58: Down | V58: Model rank: top 42% buy side / top 26% short side (buy bucket: 50-70%); - RSI(14) rises back above 30 - fades (22-Oct): -1.6% vs avg stock, t 4.1 | W58: ▲ 2B bottom / Turtle soup 15-Oct [no edge]; ▼ Horizontal support breakdown (3+ touches) 15-Oct [weak edge]; ▲ Bullish Wolfe wave 12-Oct [no edge]; ▼ P&F bearish descending breakdown 09-Oct [works in reverse] | X58: Not checked | Y58: No edge either way for 1 year (buy-side model rank: 58th percentile; no proven signal active). Holders can keep; no fresh entry. Technicals: RSI 30; RS rating 47; -31% from 52-wk high; below a falling 200-DMA.
A59: SJVN | B59: SJVN Ltd. | C59: Energy | D59: Short term (up to 2 weeks) | E59: Buy | F59: Strong Buy | G59: 0.21183931 | H59: 0.084306981 | I59: 0.42819519 | J59: 0.0018773479 | K59: 5.7878251 | L59: 47.4 | M59: 1.7941069 | N59: =ROUND(L59+'Read Me'!$D$30*M59,2) | O59: =ROUND(L59+'Read Me'!$C$30*M59,2) | P59: =ROUND(L59-'Read Me'!$B$30*M59,2) | Q59: =ABS(O59-L59)/L59 | R59: =ABS(L59-P59)/L59 | S59: 10 | T59: 6 | U59: Down | V59: Model rank: top 5% buy side / bottom 17% short side (buy bucket: Top 5%) | W59: ▲ 2B bottom / Turtle soup 16-Oct [no edge] | X59: Not checked | Y59: AI model ranks it in the top 5% of stocks for a 2-week buy. Historically, top-5% names hit the target 21% of the time vs 15% for the average stock (weighted to falling markets like now), averaging +0.2% per trade after costs. Technicals: RSI 17; RS rating 1; -48% from 52-wk high; below 20-EMA.
A60: SJVN | B60: SJVN Ltd. | C60: Energy | D60: Mid term (up to 3 months) | E60: Hold | F60: Hold / No fresh trade | G60: 0.28474942 | H60: 0.07441852 | I60: 0.49058663 | J60: 0.03589876 | K60: 1.0428963 | L60: 47.4 | M60: 1.7941069 | U60: Down | V60: Model rank: top 16% buy side / bottom 12% short side (buy bucket: 70-85%) | W60: ▲ 2B bottom / Turtle soup 16-Oct [no edge] | X60: Not checked | Y60: No edge either way for 3 months (buy-side model rank: 84th percentile; no proven signal active). Holders can keep; no fresh entry. Technicals: RSI 17; RS rating 1; -48% from 52-wk high; below a falling 50-DMA.
A61: SJVN | B61: SJVN Ltd. | C61: Energy | D61: Long term (up to 1 year) | E61: Hold | F61: Hold / No fresh trade | G61: 0.3356492 | H61: 0.037138628 | I61: 0.49884743 | J61: 0.099800505 | K61: -3.9704276 | L61: 47.4 | M61: 1.7941069 | U61: Down | V61: Model rank: top 23% buy side / bottom 9% short side (buy bucket: 70-85%); - RSI(14) rises back above 30 - fades (14-Oct): -1.6% vs avg stock, t 4.1 | W61: ▲ 2B bottom / Turtle soup 16-Oct [no edge] | X61: Not checked | Y61: No edge either way for 1 year (buy-side model rank: 77th percentile; no proven signal active). Holders can keep; no fresh entry. Technicals: RSI 17; RS rating 1; -48% from 52-wk high; below a falling 200-DMA.
A62: PGEL | B62: PG Electroplast Ltd. | C62: Consumer Goods | D62: Short term (up to 2 weeks) | E62: Buy | F62: Strong Buy | G62: 0.21183931 | H62: 0.11425674 | I62: 0.42819519 | J62: 0.0018773479 | K62: 5.7878251 | L62: 470.05 | M62: 17.017224 | N62: =ROUND(L62+'Read Me'!$D$30*M62,2) | O62: =ROUND(L62+'Read Me'!$C$30*M62,2) | P62: =ROUND(L62-'Read Me'!$B$30*M62,2) | Q62: =ABS(O62-L62)/L62 | R62: =ABS(L62-P62)/L62 | S62: 10 | T62: 6 | U62: Down | V62: Model rank: top 3% buy side / bottom 36% short side (buy bucket: Top 5%) | W62: ▼ Hidden bearish divergence (MACD hist) 23-Oct [no edge]; ▼ P&F bearish descending breakdown 23-Oct [works in reverse]; ▼ Hidden bearish divergence (MFI) 19-Oct [no edge]; ▼ Hidden bearish divergence (OBV) 19-Oct [no edge] | X62: Not checked | Y62: AI model ranks it in the top 3% of stocks for a 2-week buy. Historically, top-5% names hit the target 21% of the time vs 15% for the average stock (weighted to falling markets like now), averaging +0.2% per trade after costs. Technicals: RSI 29; RS rating 24; -27% from 52-wk high; below 20-EMA; delivery % rising (+5 pts vs 20-day).
A63: PGEL | B63: PG Electroplast Ltd. | C63: Consumer Goods | D63: Mid term (up to 3 months) | E63: Avoid | F63: Avoid (likely underperformer) | G63: 0.27001717 | H63: 0.15337475 | I63: 0.49932605 | J63: 0.040496912 | K63: -0.43032906 | L63: 470.05 | M63: 17.017224 | U63: Down | V63: Model rank: bottom 41% buy side / top 15% short side (buy bucket: 20-50%) | W63: ▼ Hidden bearish divergence (MACD hist) 23-Oct [no edge]; ▼ P&F bearish descending breakdown 23-Oct [works in reverse]; ▼ Hidden bearish divergence (MFI) 19-Oct [no edge]; ▼ Hidden bearish divergence (OBV) 19-Oct [no edge] | X63: Not checked | Y63: AI model flags a likely underperformer over 3 months (short-side rank top 15%): such stocks lagged the average stock by about 1.0% per trade. Holders: tighten stops or reduce; no fresh buying. Technicals: RSI 29; RS rating 24; -27% from 52-wk high; below a falling 50-DMA; delivery % rising (+5 pts vs 20-day).
A64: PGEL | B64: PG Electroplast Ltd. | C64: Consumer Goods | D64: Long term (up to 1 year) | E64: Hold | F64: Hold / No fresh trade | G64: 0.36484408 | H64: 0.071868264 | I64: 0.52926184 | J64: 0.12657897 | K64: -1.0509395 | L64: 470.05 | M64: 17.017224 | U64: Down | V64: Model rank: bottom 1% buy side / top 30% short side (buy bucket: Bottom 20%) | W64: ▼ Hidden bearish divergence (MACD hist) 23-Oct [no edge]; ▼ P&F bearish descending breakdown 23-Oct [works in reverse]; ▼ Hidden bearish divergence (MFI) 19-Oct [no edge]; ▼ Hidden bearish divergence (OBV) 19-Oct [no edge] | X64: Not checked | Y64: No edge either way for 1 year (buy-side model rank: 1st percentile; no proven signal active). Holders can keep; no fresh entry. Technicals: RSI 29; RS rating 24; -27% from 52-wk high; below a falling 200-DMA; delivery % rising (+5 pts vs 20-day).
A65: ATHERENERG | B65: Ather Energy Ltd. | C65: Automobile | D65: Short term (up to 2 weeks) | E65: Buy | F65: Buy | G65: 0.18398049 | H65: 0.13461342 | I65: 0.42801823 | J65: 0.0026079447 | K65: 3.0019431 | L65: 1380 | M65: 59.62175 | N65: =ROUND(L65+'Read Me'!$D$30*M65,2) | O65: =ROUND(L65+'Read Me'!$C$30*M65,2) | P65: =ROUND(L65-'Read Me'!$B$30*M65,2) | Q65: =ABS(O65-L65)/L65 | R65: =ABS(L65-P65)/L65 | S65: 10 | T65: 6 | U65: Down | V65: Model rank: top 24% buy side / top 42% short side (buy bucket: 70-85%); + Three lower closes in an uptrend (22-Oct): +0.2% vs avg stock, t 5.1; + RSI(2) below 5 in an uptrend (Connors) (22-Oct): +0.2% vs avg stock, t 3.6 | W65: ▲ 2B bottom / Turtle soup 23-Oct [no edge]; ▼ Bearish Quasimodo 14-Oct [no edge]; ▲ Bullish divergence (MACD hist) 12-Oct [no edge]; ▲ Bullish divergence (OBV) 12-Oct [no edge] | X65: Not checked | Y65: Proven setup active: Three lower closes in an uptrend (22-Oct) - historically +0.2% vs the average stock over 2 weeks (t 5.1, also positive in falling markets). Buy confidence 18% vs 15% for an average stock; expected +0.3% per trade after costs. Technicals: RSI 37; RS rating 97; -21% from 52-wk high; below 20-EMA.
A66: ATHERENERG | B66: Ather Energy Ltd. | C66: Automobile | D66: Mid term (up to 3 months) | E66: Hold | F66: Hold / No fresh trade | G66: 0.27614069 | H66: 0.099596779 | I66: 0.50238781 | J66: 0.045530003 | K66: 0.18202297 | L66: 1380 | M66: 59.62175 | U66: Sideways | V66: Model rank: bottom 39% buy side / bottom 37% short side (buy bucket: 20-50%); + Three lower closes in an uptrend (22-Oct): +0.5% vs avg stock, t 6.7 | W66: ▲ 2B bottom / Turtle soup 23-Oct [no edge]; ▼ Bearish Quasimodo 14-Oct [no edge]; ▲ Bullish divergence (MACD hist) 12-Oct [no edge]; ▲ Bullish divergence (OBV) 12-Oct [no edge] | X66: Not checked | Y66: No edge either way for 3 months (buy-side model rank: 39th percentile; no proven signal active). Holders can keep; no fresh entry. Technicals: RSI 37; RS rating 97; -21% from 52-wk high; below a rising 50-DMA.
A67: ATHERENERG | B67: Ather Energy Ltd. | C67: Automobile | D67: Long term (up to 1 year) | E67: Hold | F67: Hold / No fresh trade | G67: 0.39558736 | H67: 0.071868264 | I67: 0.54009172 | J67: 0.14656904 | K67: 2.0233876 | L67: 1380 | M67: 59.62175 | U67: Up | V67: Model rank: bottom 26% buy side / top 35% short side (buy bucket: 20-50%); + Three lower closes in an uptrend (22-Oct): +1.8% vs avg stock, t 6.9 | W67: ▲ 2B bottom / Turtle soup 23-Oct [no edge]; ▼ Bearish Quasimodo 14-Oct [no edge]; ▲ Bullish divergence (MACD hist) 12-Oct [no edge]; ▲ Bullish divergence (OBV) 12-Oct [no edge] | X67: Not checked | Y67: No edge either way for 1 year (buy-side model rank: 26th percentile; no proven signal active). Holders can keep; no fresh entry. Technicals: RSI 37; RS rating 97; -21% from 52-wk high; above a rising 200-DMA.
A68: RADICO | B68: Radico Khaitan Ltd | C68: Consumer Goods | D68: Short term (up to 2 weeks) | E68: Buy | F68: Buy | G68: 0.1722565 | H68: 0.14315289 | I68: 0.43318613 | J68: 0.0030396574 | K68: 1.8295446 | L68: 4157.3 | M68: 134.78817 | N68: =ROUND(L68+'Read Me'!$D$30*M68,2) | O68: =ROUND(L68+'Read Me'!$C$30*M68,2) | P68: =ROUND(L68-'Read Me'!$B$30*M68,2) | Q68: =ABS(O68-L68)/L68 | R68: =ABS(L68-P68)/L68 | S68: 10 | T68: 6 | U68: Down | V68: Model rank: top 40% buy side / top 22% short side (buy bucket: 50-70%); + Three lower closes in an uptrend (22-Oct): +0.2% vs avg stock, t 5.1; + RSI(2) below 5 in an uptrend (Connors) (22-Oct): +0.2% vs avg stock, t 3.6 | W68: ▼ P&F double-bottom sell 23-Oct [works in reverse]; ▼ Wave-3 / ABC breakdown 22-Oct [no edge]; ▼ Uptrend-line breakdown 22-Oct [no edge]; ▼ Horizontal support breakdown (3+ touches) 22-Oct [weak edge] | X68: Not checked | Y68: Proven setup active: Three lower closes in an uptrend (22-Oct) - historically +0.2% vs the average stock over 2 weeks (t 5.1, also positive in falling markets). Buy confidence 17% vs 15% for an average stock; expected +0.3% per trade after costs. Technicals: RSI 35; RS rating 90; -12% from 52-wk high; below 20-EMA.
A69: RADICO | B69: Radico Khaitan Ltd | C69: Consumer Goods | D69: Mid term (up to 3 months) | E69: Hold | F69: Hold / No fresh trade | G69: 0.2896576 | H69: 0.12952211 | I69: 0.50326672 | J69: 0.043051742 | K69: 1.5337146 | L69: 4157.3 | M69: 134.78817 | U69: Down | V69: Model rank: top 46% buy side / top 17% short side (buy bucket: 50-70%); + Three lower closes in an uptrend (22-Oct): +0.5% vs avg stock, t 6.7 | W69: ▼ P&F double-bottom sell 23-Oct [works in reverse]; ▼ Wave-3 / ABC breakdown 22-Oct [no edge]; ▼ Uptrend-line breakdown 22-Oct [no edge]; ▼ Horizontal support breakdown (3+ touches) 22-Oct [weak edge] | X69: Not checked | Y69: No edge either way for 3 months (buy-side model rank: 54th percentile; no proven signal active). Holders can keep; no fresh entry. Technicals: RSI 35; RS rating 90; -12% from 52-wk high; below a falling 50-DMA.
A70: RADICO | B70: Radico Khaitan Ltd | C70: Consumer Goods | D70: Long term (up to 1 year) | E70: Hold | F70: Hold / No fresh trade | G70: 0.39558736 | H70: 0.085280983 | I70: 0.54009172 | J70: 0.14656904 | K70: 2.0233876 | L70: 4157.3 | M70: 134.78817 | U70: Up | V70: Model rank: bottom 32% buy side / top 27% short side (buy bucket: 20-50%); + Three lower closes in an uptrend (22-Oct): +1.8% vs avg stock, t 6.9 | W70: ▼ P&F double-bottom sell 23-Oct [works in reverse]; ▼ Wave-3 / ABC breakdown 22-Oct [no edge]; ▼ Uptrend-line breakdown 22-Oct [no edge]; ▼ Horizontal support breakdown (3+ touches) 22-Oct [weak edge] | X70: Not checked | Y70: No edge either way for 1 year (buy-side model rank: 32nd percentile; no proven signal active). Holders can keep; no fresh entry. Technicals: RSI 35; RS rating 90; -12% from 52-wk high; above a rising 200-DMA.
A71: KPRMILL | B71: K.P.R. Mill Ltd. | C71: Textiles | D71: Short term (up to 2 weeks) | E71: Buy | F71: Buy | G71: 0.16342322 | H71: 0.13461342 | I71: 0.43804557 | J71: 0.0037491042 | K71: 0.9462162 | L71: 1024.6 | M71: 36.512023 | N71: =ROUND(L71+'Read Me'!$D$30*M71,2) | O71: =ROUND(L71+'Read Me'!$C$30*M71,2) | P71: =ROUND(L71-'Read Me'!$B$30*M71,2) | Q71: =ABS(O71-L71)/L71 | R71: =ABS(L71-P71)/L71 | S71: 10 | T71: 6 | U71: Down | V71: Model rank: bottom 47% buy side / top 36% short side (buy bucket: 20-50%); + Three lower closes in an uptrend (22-Oct): +0.2% vs avg stock, t 5.1; + RSI(2) below 5 in an uptrend (Connors) (22-Oct): +0.2% vs avg stock, t 3.6 | W71: ▲ Key reversal day (bullish) 23-Oct [no edge]; ▲ Wyckoff spring 23-Oct [works in reverse]; ▲ 2B bottom / Turtle soup 21-Oct [no edge]; ▼ P&F bearish descending breakdown 21-Oct [works in reverse] | X71: Not checked | Y71: Proven setup active: Three lower closes in an uptrend (22-Oct) - historically +0.2% vs the average stock over 2 weeks (t 5.1, also positive in falling markets). Buy confidence 16% vs 15% for an average stock; expected +0.4% per trade after costs. Technicals: RSI 37; RS rating 78; -23% from 52-wk high; below 20-EMA.
A72: KPRMILL | B72: K.P.R. Mill Ltd. | C72: Textiles | D72: Mid term (up to 3 months) | E72: Hold | F72: Hold / No fresh trade | G72: 0.28219231 | H72: 0.12952211 | I72: 0.49953407 | J72: 0.035369996 | K72: 0.78718531 | L72: 1024.6 | M72: 36.512023 | U72: Sideways | V72: Model rank: top 47% buy side / top 24% short side (buy bucket: 50-70%); + Three lower closes in an uptrend (22-Oct): +0.5% vs avg stock, t 6.7; - Wyckoff spring - fades (23-Oct): -0.8% vs avg stock, t 4.8 | W72: ▲ Key reversal day (bullish) 23-Oct [no edge]; ▲ Wyckoff spring 23-Oct [works in reverse]; ▲ 2B bottom / Turtle soup 21-Oct [no edge]; ▼ P&F bearish descending breakdown 21-Oct [works in reverse] | X72: Not checked | Y72: No edge either way for 3 months (buy-side model rank: 53rd percentile; no proven signal active). Holders can keep; no fresh entry. Technicals: RSI 37; RS rating 78; -23% from 52-wk high; below a rising 50-DMA.
A73: KPRMILL | B73: K.P.R. Mill Ltd. | C73: Textiles | D73: Long term (up to 1 year) | E73: Hold | F73: Hold / No fresh trade | G73: 0.37795048 | H73: 0.071868264 | I73: 0.53581504 | J73: 0.14446191 | K73: 0.25969983 | L73: 1024.6 | M73: 36.512023 | U73: Up | V73: Model rank: bottom 18% buy side / top 43% short side (buy bucket: Bottom 20%); + Three lower closes in an uptrend (22-Oct): +1.8% vs avg stock, t 6.9 | W73: ▲ Key reversal day (bullish) 23-Oct [no edge]; ▲ Wyckoff spring 23-Oct [works in reverse]; ▲ 2B bottom / Turtle soup 21-Oct [no edge]; ▼ P&F bearish descending breakdown 21-Oct [works in reverse] | X73: Not checked | Y73: No edge either way for 1 year (buy-side model rank: 18th percentile; no proven signal active). Holders can keep; no fresh entry. Technicals: RSI 37; RS rating 78; -23% from 52-wk high; above a rising 200-DMA.
A74: SOLARINDS | B74: Solar Industries India Ltd. | C74: Chemicals | D74: Short term (up to 2 weeks) | E74: Buy | F74: Buy | G74: 0.16342322 | H74: 0.13461342 | I74: 0.43804557 | J74: 0.0037491042 | K74: 0.9462162 | L74: 18365 | M74: 620.03834 | N74: =ROUND(L74+'Read Me'!$D$30*M74,2) | O74: =ROUND(L74+'Read Me'!$C$30*M74,2) | P74: =ROUND(L74-'Read Me'!$B$30*M74,2) | Q74: =ABS(O74-L74)/L74 | R74: =ABS(L74-P74)/L74 | S74: 10 | T74: 6 | U74: Down | V74: Model rank: bottom 38% buy side / top 36% short side (buy bucket: 20-50%); + Three lower closes in an uptrend (22-Oct): +0.2% vs avg stock, t 5.1; + RSI(2) below 5 in an uptrend (Connors) (22-Oct): +0.2% vs avg stock, t 3.6 | W74: ▼ Darvas box breakdown 23-Oct [tends to fail]; ▼ Dead-cat bounce breakdown 23-Oct [survivorship illusion]; ▼ Dow trend reversal down 23-Oct [no edge]; ▼ Horizontal support breakdown (3+ touches) 23-Oct [weak edge] | X74: Not checked | Y74: Proven setup active: Three lower closes in an uptrend (22-Oct) - historically +0.2% vs the average stock over 2 weeks (t 5.1, also positive in falling markets). Buy confidence 16% vs 15% for an average stock; expected +0.4% per trade after costs. Technicals: RSI 35; RS rating 88; -19% from 52-wk high; below 20-EMA.
A75: SOLARINDS | B75: Solar Industries India Ltd. | C75: Chemicals | D75: Mid term (up to 3 months) | E75: Hold | F75: Hold / No fresh trade | G75: 0.27614069 | H75: 0.11434533 | I75: 0.50238781 | J75: 0.045530003 | K75: 0.18202297 | L75: 18365 | M75: 620.03834 | U75: Sideways | V75: Model rank: bottom 30% buy side / top 34% short side (buy bucket: 20-50%); + Three lower closes in an uptrend (22-Oct): +0.5% vs avg stock, t 6.7 | W75: ▼ Darvas box breakdown 23-Oct [tends to fail]; ▼ Dead-cat bounce breakdown 23-Oct [survivorship illusion]; ▼ Dow trend reversal down 23-Oct [no edge]; ▼ Horizontal support breakdown (3+ touches) 23-Oct [weak edge] | X75: Not checked | Y75: No edge either way for 3 months (buy-side model rank: 30th percentile; no proven signal active). Holders can keep; no fresh entry. Technicals: RSI 35; RS rating 88; -19% from 52-wk high; below a rising 50-DMA.
A76: SOLARINDS | B76: Solar Industries India Ltd. | C76: Chemicals | D76: Long term (up to 1 year) | E76: Hold | F76: Hold / No fresh trade | G76: 0.39558736 | H76: 0.085280983 | I76: 0.54009172 | J76: 0.14656904 | K76: 2.0233876 | L76: 18365 | M76: 620.03834 | U76: Up | V76: Model rank: bottom 20% buy side / top 25% short side (buy bucket: 20-50%); + Three lower closes in an uptrend (22-Oct): +1.8% vs avg stock, t 6.9 | W76: ▼ Darvas box breakdown 23-Oct [tends to fail]; ▼ Dead-cat bounce breakdown 23-Oct [survivorship illusion]; ▼ Dow trend reversal down 23-Oct [no edge]; ▼ Horizontal support breakdown (3+ touches) 23-Oct [weak edge] | X76: Not checked | Y76: No edge either way for 1 year (buy-side model rank: 20th percentile; no proven signal active). Holders can keep; no fresh entry. Technicals: RSI 35; RS rating 88; -19% from 52-wk high; above a rising 200-DMA.
A77: APLAPOLLO | B77: APL Apollo Tubes Ltd. | C77: Metals | D77: Short term (up to 2 weeks) | E77: Buy | F77: Buy | G77: 0.16342322 | H77: 0.13461342 | I77: 0.43804557 | J77: 0.0037491042 | K77: 0.9462162 | L77: 2033.7 | M77: 60.812169 | N77: =ROUND(L77+'Read Me'!$D$30*M77,2) | O77: =ROUND(L77+'Read Me'!$C$30*M77,2) | P77: =ROUND(L77-'Read Me'!$B$30*M77,2) | Q77: =ABS(O77-L77)/L77 | R77: =ABS(L77-P77)/L77 | S77: 10 | T77: 6 | U77: Down | V77: Model rank: bottom 35% buy side / top 37% short side (buy bucket: 20-50%); + Three lower closes in an uptrend (22-Oct): +0.2% vs avg stock, t 5.1; + RSI(2) below 5 in an uptrend (Connors) (22-Oct): +0.2% vs avg stock, t 3.6 | W77: ▲ 2B bottom / Turtle soup 23-Oct [no edge]; ▼ P&F triple-bottom sell 23-Oct [no edge]; ▲ Wyckoff spring 23-Oct [works in reverse]; ▲ Bullish divergence (MFI) 12-Oct [tends to fail] | X77: Mixed | Y77: Proven setup active: Three lower closes in an uptrend (22-Oct) - historically +0.2% vs the average stock over 2 weeks (t 5.1, also positive in falling markets). Buy confidence 16% vs 15% for an average stock; expected +0.4% per trade after costs. Technicals: RSI 39; RS rating 81; -12% from 52-wk high; below 20-EMA. Results Q1 FY27 (Apr-Jun 2026) - revenue: Volumes -6% YoY; profit: +11% to Rs 263 Cr (mixed).
A78: APLAPOLLO | B78: APL Apollo Tubes Ltd. | C78: Metals | D78: Mid term (up to 3 months) | E78: Hold | F78: Hold / No fresh trade | G78: 0.28219231 | H78: 0.11434533 | I78: 0.49953407 | J78: 0.035369996 | K78: 0.78718531 | L78: 2033.7 | M78: 60.812169 | U78: Sideways | V78: Model rank: top 38% buy side / top 31% short side (buy bucket: 50-70%); + Three lower closes in an uptrend (22-Oct): +0.5% vs avg stock, t 6.7; - Wyckoff spring - fades (23-Oct): -0.8% vs avg stock, t 4.8 | W78: ▲ 2B bottom / Turtle soup 23-Oct [no edge]; ▼ P&F triple-bottom sell 23-Oct [no edge]; ▲ Wyckoff spring 23-Oct [works in reverse]; ▲ Bullish divergence (MFI) 12-Oct [tends to fail] | X78: Mixed | Y78: No edge either way for 3 months (buy-side model rank: 62nd percentile; no proven signal active). Holders can keep; no fresh entry. Technicals: RSI 39; RS rating 81; -12% from 52-wk high; below a rising 50-DMA. Results Q1 FY27 (Apr-Jun 2026) - revenue: Volumes -6% YoY; profit: +11% to Rs 263 Cr (mixed).
A79: APLAPOLLO | B79: APL Apollo Tubes Ltd. | C79: Metals | D79: Long term (up to 1 year) | E79: Hold | F79: Hold / No fresh trade | G79: 0.40411969 | H79: 0.055927815 | I79: 0.53552282 | J79: 0.14364669 | K79: 2.8766213 | L79: 2033.7 | M79: 60.812169 | U79: Up | V79: Model rank: top 34% buy side / bottom 28% short side (buy bucket: 50-70%); + Three lower closes in an uptrend (22-Oct): +1.8% vs avg stock, t 6.9 | W79: ▲ 2B bottom / Turtle soup 23-Oct [no edge]; ▼ P&F triple-bottom sell 23-Oct [no edge]; ▲ Wyckoff spring 23-Oct [works in reverse]; ▲ Bullish divergence (MFI) 12-Oct [tends to fail] | X79: Mixed | Y79: No edge either way for 1 year (buy-side model rank: 66th percentile; no proven signal active). Holders can keep; no fresh entry. Technicals: RSI 39; RS rating 81; -12% from 52-wk high; above a rising 200-DMA. Results Q1 FY27 (Apr-Jun 2026) - revenue: Volumes -6% YoY; profit: +11% to Rs 263 Cr (mixed).
A80: RKFORGE | B80: Ramkrishna Forgings Ltd. | C80: Automobile | D80: Short term (up to 2 weeks) | E80: Buy | F80: Buy | G80: 0.16342322 | H80: 0.084306981 | I80: 0.43804557 | J80: 0.0037491042 | K80: 0.9462162 | L80: 591.1 | M80: 25.716918 | N80: =ROUND(L80+'Read Me'!$D$30*M80,2) | O80: =ROUND(L80+'Read Me'!$C$30*M80,2) | P80: =ROUND(L80-'Read Me'!$B$30*M80,2) | Q80: =ABS(O80-L80)/L80 | R80: =ABS(L80-P80)/L80 | S80: 10 | T80: 6 | U80: Down | V80: Model rank: bottom 29% buy side / bottom 8% short side (buy bucket: 20-50%); + Three lower closes in an uptrend (22-Oct): +0.2% vs avg stock, t 5.1; + RSI(2) below 5 in an uptrend (Connors) (22-Oct): +0.2% vs avg stock, t 3.6 | W80: ▼ Double top 21-Oct [no edge]; ▼ Dow trend reversal down 21-Oct [no edge]; ▼ Wave-3 / ABC breakdown 21-Oct [no edge]; ▲ Key reversal day (bullish) 16-Oct [no edge] | X80: Supportive | Y80: Proven setup active: Three lower closes in an uptrend (22-Oct) - historically +0.2% vs the average stock over 2 weeks (t 5.1, also positive in falling markets). Buy confidence 16% vs 15% for an average stock; expected +0.4% per trade after costs. Technicals: RSI 26; RS rating 80; -24% from 52-wk high; below 20-EMA. Results Q1 FY27 (Apr-Jun 2026) - revenue: +19.8% to Rs 1,217 Cr; profit: about 4x to Rs 47 Cr (supportive).
A81: RKFORGE | B81: Ramkrishna Forgings Ltd. | C81: Automobile | D81: Mid term (up to 3 months) | E81: Hold | F81: Hold / No fresh trade | G81: 0.2896576 | H81: 0.07441852 | I81: 0.50326672 | J81: 0.043051742 | K81: 1.5337146 | L81: 591.1 | M81: 25.716918 | U81: Down | V81: Model rank: top 37% buy side / bottom 12% short side (buy bucket: 50-70%); + Three lower closes in an uptrend (22-Oct): +0.5% vs avg stock, t 6.7 | W81: ▼ Double top 21-Oct [no edge]; ▼ Dow trend reversal down 21-Oct [no edge]; ▼ Wave-3 / ABC breakdown 21-Oct [no edge]; ▲ Key reversal day (bullish) 16-Oct [no edge] | X81: Supportive | Y81: No edge either way for 3 months (buy-side model rank: 63rd percentile; no proven signal active). Holders can keep; no fresh entry. Technicals: RSI 26; RS rating 80; -24% from 52-wk high; below a falling 50-DMA. Results Q1 FY27 (Apr-Jun 2026) - revenue: +19.8% to Rs 1,217 Cr; profit: about 4x to Rs 47 Cr (supportive).
A82: RKFORGE | B82: Ramkrishna Forgings Ltd. | C82: Automobile | D82: Long term (up to 1 year) | E82: Hold | F82: Hold / No fresh trade | G82: 0.39558736 | H82: 0.037138628 | I82: 0.54009172 | J82: 0.14656904 | K82: 2.0233876 | L82: 591.1 | M82: 25.716918 | U82: Sideways | V82: Model rank: bottom 49% buy side / bottom 13% short side (buy bucket: 20-50%); + Three lower closes in an uptrend (22-Oct): +1.8% vs avg stock, t 6.9 | W82: ▼ Double top 21-Oct [no edge]; ▼ Dow trend reversal down 21-Oct [no edge]; ▼ Wave-3 / ABC breakdown 21-Oct [no edge]; ▲ Key reversal day (bullish) 16-Oct [no edge] | X82: Supportive | Y82: No edge either way for 1 year (buy-side model rank: 49th percentile; no proven signal active). Holders can keep; no fresh entry. Technicals: RSI 26; RS rating 80; -24% from 52-wk high; below a rising 200-DMA. Results Q1 FY27 (Apr-Jun 2026) - revenue: +19.8% to Rs 1,217 Cr; profit: about 4x to Rs 47 Cr (supportive).
A83: ACMESOLAR | B83: ACME Solar Holdings Ltd. | C83: Energy | D83: Short term (up to 2 weeks) | E83: Buy | F83: Buy | G83: 0.16342322 | H83: 0.084306981 | I83: 0.43804557 | J83: 0.0037491042 | K83: 0.9462162 | L83: 371.85 | M83: 18.531699 | N83: =ROUND(L83+'Read Me'!$D$30*M83,2) | O83: =ROUND(L83+'Read Me'!$C$30*M83,2) | P83: =ROUND(L83-'Read Me'!$B$30*M83,2) | Q83: =ABS(O83-L83)/L83 | R83: =ABS(L83-P83)/L83 | S83: 10 | T83: 6 | U83: Down | V83: Model rank: bottom 26% buy side / bottom 3% short side (buy bucket: 20-50%); + Three lower closes in an uptrend (23-Oct): +0.2% vs avg stock, t 5.1; + RSI(2) below 5 in an uptrend (Connors) (23-Oct): +0.2% vs avg stock, t 3.6 | W83: ▼ P&F double-bottom sell 22-Oct [works in reverse]; ▲ Bullish AB=CD 19-Oct [no edge]; ▲ Pocket pivot 19-Oct [no edge]; ▲ 2B bottom / Turtle soup 16-Oct [no edge] | X83: Not checked | Y83: Proven setup active: Three lower closes in an uptrend (23-Oct) - historically +0.2% vs the average stock over 2 weeks (t 5.1, also positive in falling markets). Buy confidence 16% vs 15% for an average stock; expected +0.4% per trade after costs. Technicals: RSI 32; RS rating 92; -22% from 52-wk high; below 20-EMA.
A84: ACMESOLAR | B84: ACME Solar Holdings Ltd. | C84: Energy | D84: Mid term (up to 3 months) | E84: Hold | F84: Hold / No fresh trade | G84: 0.27614069 | H84: 0.07441852 | I84: 0.50238781 | J84: 0.045530003 | K84: 0.18202297 | L84: 371.85 | M84: 18.531699 | U84: Sideways | V84: Model rank: bottom 32% buy side / bottom 5% short side (buy bucket: 20-50%); + Three lower closes in an uptrend (23-Oct): +0.5% vs avg stock, t 6.7 | W84: ▼ P&F double-bottom sell 22-Oct [works in reverse]; ▲ Bullish AB=CD 19-Oct [no edge]; ▲ Pocket pivot 19-Oct [no edge]; ▲ 2B bottom / Turtle soup 16-Oct [no edge] | X84: Not checked | Y84: No edge either way for 3 months (buy-side model rank: 32nd percentile; no proven signal active). Holders can keep; no fresh entry. Technicals: RSI 32; RS rating 92; -22% from 52-wk high; below a rising 50-DMA.
A85: ACMESOLAR | B85: ACME Solar Holdings Ltd. | C85: Energy | D85: Long term (up to 1 year) | E85: Hold | F85: Hold / No fresh trade | G85: 0.39558736 | H85: 0.055927815 | I85: 0.54009172 | J85: 0.14656904 | K85: 2.0233876 | L85: 371.85 | M85: 18.531699 | U85: Up | V85: Model rank: bottom 28% buy side / bottom 31% short side (buy bucket: 20-50%); + Three lower closes in an uptrend (23-Oct): +1.8% vs avg stock, t 6.9 | W85: ▼ P&F double-bottom sell 22-Oct [works in reverse]; ▲ Bullish AB=CD 19-Oct [no edge]; ▲ Pocket pivot 19-Oct [no edge]; ▲ 2B bottom / Turtle soup 16-Oct [no edge] | X85: Not checked | Y85: No edge either way for 1 year (buy-side model rank: 28th percentile; no proven signal active). Holders can keep; no fresh entry. Technicals: RSI 32; RS rating 92; -22% from 52-wk high; above a rising 200-DMA.
A86: TDPOWERSYS | B86: TD Power Systems Ltd. | C86: Capital Goods | D86: Short term (up to 2 weeks) | E86: Hold | F86: Hold / No fresh trade | G86: 0.13135207 | H86: 0.084306981 | I86: 0.43613026 | J86: 0.00036019541 | K86: -2.2608984 | L86: 639.55 | M86: 41.745506 | U86: Down | V86: Model rank: bottom 2% buy side / bottom 6% short side (buy bucket: Bottom 20%); + Three lower closes in an uptrend (23-Oct): +0.2% vs avg stock, t 5.1 | W86: ▼ Elliott 5-wave advance complete 23-Oct [works in reverse]; ▼ P&F double-bottom sell 15-Oct [works in reverse]; ▼ Ascending triangle - down breakout 14-Oct [no edge]; ▼ Uptrend-line breakdown 14-Oct [no edge] | X86: Not checked | Y86: No edge either way for 2 weeks (buy-side model rank: 2nd percentile; no proven signal active). Holders can keep; no fresh entry. Technicals: RSI 32; RS rating 97; -25% from 52-wk high; below 20-EMA; delivery % rising (+5 pts vs 20-day); volatile (6.5% daily range).
A87: TDPOWERSYS | B87: TD Power Systems Ltd. | C87: Capital Goods | D87: Mid term (up to 3 months) | E87: Hold | F87: Hold / No fresh trade | G87: 0.24593537 | H87: 0.07441852 | I87: 0.52193714 | J87: 0.051224254 | K87: -2.8385086 | L87: 639.55 | M87: 41.745506 | U87: Sideways | V87: Model rank: bottom 4% buy side / bottom 4% short side (buy bucket: Bottom 20%); + Three lower closes in an uptrend (23-Oct): +0.5% vs avg stock, t 6.7 | W87: ▼ Elliott 5-wave advance complete 23-Oct [works in reverse]; ▼ P&F double-bottom sell 15-Oct [works in reverse]; ▼ Ascending triangle - down breakout 14-Oct [no edge]; ▼ Uptrend-line breakdown 14-Oct [no edge] | X87: Not checked | Y87: No edge either way for 3 months (buy-side model rank: 4th percentile; no proven signal active). Holders can keep; no fresh entry. Technicals: RSI 32; RS rating 97; -25% from 52-wk high; below a rising 50-DMA; delivery % rising (+5 pts vs 20-day); volatile (6.5% daily range).
A88: TDPOWERSYS | B88: TD Power Systems Ltd. | C88: Capital Goods | D88: Long term (up to 1 year) | E88: Accumulate | F88: Accumulate (buy on dips) | G88: 0.42260949 | H88: 0.037138628 | I88: 0.55360279 | J88: 0.17754366 | K88: 4.725601 | L88: 639.55 | M88: 41.745506 | N88: =ROUND(L88+'Read Me'!$D$32*M88,2) | O88: =ROUND(L88+'Read Me'!$C$32*M88,2) | P88: =ROUND(L88-'Read Me'!$B$32*M88,2) | Q88: =ABS(O88-L88)/L88 | R88: =ABS(L88-P88)/L88 | S88: 250 | T88: 86 | U88: Up | V88: Model rank: bottom 29% buy side / bottom 2% short side (buy bucket: 20-50%); + Holy Grail: ADX > 30 and pullback to 20 EMA (14-Oct): +3.1% vs avg stock, t 6.4; + Three lower closes in an uptrend (23-Oct): +1.8% vs avg stock, t 6.9 | W88: ▼ Elliott 5-wave advance complete 23-Oct [works in reverse]; ▼ P&F double-bottom sell 15-Oct [works in reverse]; ▼ Ascending triangle - down breakout 14-Oct [no edge]; ▼ Uptrend-line breakdown 14-Oct [no edge] | X88: Not checked | Y88: Proven setup active: Holy Grail: ADX > 30 and pullback to 20 EMA (14-Oct) - historically +3.1% vs the average stock over 1 year (t 6.4, also positive in falling markets). Buy confidence 42% vs 38% for an average stock; expected +17.8% per trade after costs. Build the position in parts on dips toward the 20/50-DMA rather than all at once. Technicals: RSI 32; RS rating 97; -25% from 52-wk high; above a rising 200-DMA; delivery % rising (+5 pts vs 20-day); volatile (6.5% daily range).
A89: NETWEB | B89: Netweb Technologies India Ltd. | C89: IT | D89: Short term (up to 2 weeks) | E89: Buy | F89: Buy | G89: 0.1722565 | H89: 0.11425674 | I89: 0.43318613 | J89: 0.0030396574 | K89: 1.8295446 | L89: 4335.8 | M89: 216.4465 | N89: =ROUND(L89+'Read Me'!$D$30*M89,2) | O89: =ROUND(L89+'Read Me'!$C$30*M89,2) | P89: =ROUND(L89-'Read Me'!$B$30*M89,2) | Q89: =ABS(O89-L89)/L89 | R89: =ABS(L89-P89)/L89 | S89: 10 | T89: 6 | U89: Down | V89: Model rank: top 34% buy side / bottom 41% short side (buy bucket: 50-70%); + Three lower closes in an uptrend (22-Oct): +0.2% vs avg stock, t 5.1; + RSI(2) below 5 in an uptrend (Connors) (23-Oct): +0.2% vs avg stock, t 3.6 | W89: ▼ Descending triangle - down breakout 23-Oct [no edge]; ▼ Dow trend reversal down 23-Oct [no edge]; ▼ Uptrend-line breakdown 23-Oct [no edge]; ▼ P&F double-bottom sell 23-Oct [works in reverse] | X89: Not checked | Y89: Proven setup active: Three lower closes in an uptrend (22-Oct) - historically +0.2% vs the average stock over 2 weeks (t 5.1, also positive in falling markets). Buy confidence 17% vs 15% for an average stock; expected +0.3% per trade after costs. Technicals: RSI 35; RS rating 83; -25% from 52-wk high; below 20-EMA.
A90: NETWEB | B90: Netweb Technologies India Ltd. | C90: IT | D90: Mid term (up to 3 months) | E90: Hold | F90: Hold / No fresh trade | G90: 0.24593537 | H90: 0.11434533 | I90: 0.52193714 | J90: 0.051224254 | K90: -2.8385086 | L90: 4335.8 | M90: 216.4465 | U90: Sideways | V90: Model rank: bottom 2% buy side / top 42% short side (buy bucket: Bottom 20%); + Three lower closes in an uptrend (22-Oct): +0.5% vs avg stock, t 6.7 | W90: ▼ Descending triangle - down breakout 23-Oct [no edge]; ▼ Dow trend reversal down 23-Oct [no edge]; ▼ Uptrend-line breakdown 23-Oct [no edge]; ▼ P&F double-bottom sell 23-Oct [works in reverse] | X90: Not checked | Y90: No edge either way for 3 months (buy-side model rank: 2nd percentile; no proven signal active). Holders can keep; no fresh entry. Technicals: RSI 35; RS rating 83; -25% from 52-wk high; below a rising 50-DMA.
A91: NETWEB | B91: Netweb Technologies India Ltd. | C91: IT | D91: Long term (up to 1 year) | E91: Reduce | F91: Reduce / Avoid | G91: 0.36785522 | H91: 0.08341266 | I91: 0.53076741 | J91: 0.12393185 | K91: -0.74982611 | L91: 4335.8 | M91: 216.4465 | U91: Up | V91: Model rank: bottom 3% buy side / top 9% short side (buy bucket: Bottom 20%); + Three lower closes in an uptrend (22-Oct): +1.8% vs avg stock, t 6.9; - Supertrend (10,3) turns up - fades (14-Oct): -2.1% vs avg stock, t 5.0 | W91: ▼ Descending triangle - down breakout 23-Oct [no edge]; ▼ Dow trend reversal down 23-Oct [no edge]; ▼ Uptrend-line breakdown 23-Oct [no edge]; ▼ P&F double-bottom sell 23-Oct [works in reverse] | X91: Not checked | Y91: AI model flags a likely underperformer over 1 year (short-side rank top 9%): such stocks lagged the average stock by about 1.0% per trade. Warning signal: Supertrend (10,3) turns up (14-Oct) has been followed by underperformance (-2.1% vs average over 1 year). Holders: tighten stops or reduce; no fresh buying. Technicals: RSI 35; RS rating 83; -25% from 52-wk high; above a rising 200-DMA.
A92: ENDURANCE | B92: Endurance Technologies Ltd. | C92: Automobile | D92: Short term (up to 2 weeks) | E92: Hold | F92: Hold / No fresh trade | G92: 0.17962269 | H92: 0.13461342 | I92: 0.42134438 | J92: -1.4028279e-05 | K92: 2.5661631 | L92: 2237.4 | M92: 70.85926 | U92: Down | V92: Model rank: top 5% buy side / top 41% short side (buy bucket: Top 15% (85-95%)) | W92: ▼ Bear flag 19-Oct [works in reverse] | X92: Not checked | Y92: The model ranks it in the top 5% for a 2-week buy, but at this horizon its top ranks have not beaten the average stock in falling markets, so that is not counted; no proven signal active. Holders can keep; no fresh entry. Technicals: RSI 16; RS rating 34; -27% from 52-wk high; below 20-EMA.
A93: ENDURANCE | B93: Endurance Technologies Ltd. | C93: Automobile | D93: Mid term (up to 3 months) | E93: Hold | F93: Hold / No fresh trade | G93: 0.28474942 | H93: 0.099596779 | I93: 0.49058663 | J93: 0.03589876 | K93: 1.0428963 | L93: 2237.4 | M93: 70.85926 | U93: Down | V93: Model rank: top 20% buy side / bottom 47% short side (buy bucket: 70-85%) | W93: ▼ Bear flag 19-Oct [works in reverse] | X93: Not checked | Y93: No edge either way for 3 months (buy-side model rank: 80th percentile; no proven signal active). Holders can keep; no fresh entry. Technicals: RSI 16; RS rating 34; -27% from 52-wk high; below a falling 50-DMA.
A94: ENDURANCE | B94: Endurance Technologies Ltd. | C94: Automobile | D94: Long term (up to 1 year) | E94: Hold | F94: Hold / No fresh trade | G94: 0.3910133 | H94: 0.055927815 | I94: 0.52896962 | J94: 0.12576374 | K94: 1.5659819 | L94: 2237.4 | M94: 70.85926 | U94: Down | V94: Model rank: top 32% buy side / bottom 45% short side (buy bucket: 50-70%) | W94: ▼ Bear flag 19-Oct [works in reverse] | X94: Not checked | Y94: No edge either way for 1 year (buy-side model rank: 68th percentile; no proven signal active). Holders can keep; no fresh entry. Technicals: RSI 16; RS rating 34; -27% from 52-wk high; below a falling 200-DMA.
A95: CDSL | B95: Central Depository Services (India) Ltd. | C95: Financial Services | D95: Short term (up to 2 weeks) | E95: Hold | F95: Hold / No fresh trade | G95: 0.17962269 | H95: 0.14315289 | I95: 0.42134438 | J95: -1.4028279e-05 | K95: 2.5661631 | L95: 1188.5 | M95: 32.13693 | U95: Down | V95: Model rank: top 5% buy side / top 18% short side (buy bucket: Top 15% (85-95%)) | W95: ▼ Wave-3 / ABC breakdown 23-Oct [no edge]; ▲ 2B bottom / Turtle soup 22-Oct [no edge]; ▲ Wyckoff spring 22-Oct [works in reverse]; ▼ Hidden bearish divergence (MACD hist) 21-Oct [no edge] | X95: Not checked | Y95: The model ranks it in the top 5% for a 2-week buy, but at this horizon its top ranks have not beaten the average stock in falling markets, so that is not counted; no proven signal active. Holders can keep; no fresh entry. Technicals: RSI 29; RS rating 34; -29% from 52-wk high; below 20-EMA.
A96: CDSL | B96: Central Depository Services (India) Ltd. | C96: Financial Services | D96: Mid term (up to 3 months) | E96: Hold | F96: Hold / No fresh trade | G96: 0.30999118 | H96: 0.11434533 | I96: 0.49862604 | J96: 0.035547256 | K96: 3.5670725 | L96: 1188.5 | M96: 32.13693 | U96: Down | V96: Model rank: top 4% buy side / top 33% short side (buy bucket: Top 5%); - Wyckoff spring - fades (22-Oct): -0.8% vs avg stock, t 4.8 | W96: ▼ Wave-3 / ABC breakdown 23-Oct [no edge]; ▲ 2B bottom / Turtle soup 22-Oct [no edge]; ▲ Wyckoff spring 22-Oct [works in reverse]; ▼ Hidden bearish divergence (MACD hist) 21-Oct [no edge] | X96: Not checked | Y96: The model ranks it in the top 4% for a 3-month buy, but at this horizon its top ranks have not beaten the average stock in falling markets, so that is not counted; no proven signal active. Holders can keep; no fresh entry. Technicals: RSI 29; RS rating 34; -29% from 52-wk high; below a falling 50-DMA.
A97: CDSL | B97: Central Depository Services (India) Ltd. | C97: Financial Services | D97: Long term (up to 1 year) | E97: Hold | F97: Hold / No fresh trade | G97: 0.38471235 | H97: 0.055927815 | I97: 0.53464091 | J97: 0.12500429 | K97: 0.93588749 | L97: 1188.5 | M97: 32.13693 | U97: Down | V97: Model rank: top 5% buy side / bottom 23% short side (buy bucket: Top 5%) | W97: ▼ Wave-3 / ABC breakdown 23-Oct [no edge]; ▲ 2B bottom / Turtle soup 22-Oct [no edge]; ▲ Wyckoff spring 22-Oct [works in reverse]; ▼ Hidden bearish divergence (MACD hist) 21-Oct [no edge] | X97: Not checked | Y97: The model ranks it in the top 5% for a 1-year buy, but at this horizon its top ranks have not beaten the average stock in falling markets, so that is not counted; no proven signal active. Holders can keep; no fresh entry. Technicals: RSI 29; RS rating 34; -29% from 52-wk high; below a falling 200-DMA.
A98: ASHOKLEY | B98: Ashok Leyland Ltd. | C98: Automobile | D98: Short term (up to 2 weeks) | E98: Hold | F98: Hold / No fresh trade | G98: 0.17962269 | H98: 0.14315289 | I98: 0.42134438 | J98: -1.4028279e-05 | K98: 2.5661631 | L98: 144.95 | M98: 3.9339567 | U98: Down | V98: Model rank: top 6% buy side / top 18% short side (buy bucket: Top 15% (85-95%)) | W98: ▲ 2B bottom / Turtle soup 22-Oct [no edge]; ▼ Hidden bearish divergence (MACD hist) 22-Oct [no edge]; ▼ Hidden bearish divergence (MFI) 22-Oct [no edge]; ▲ Bullish divergence (MACD hist) 15-Oct [no edge] | X98: Not checked | Y98: The model ranks it in the top 6% for a 2-week buy, but at this horizon its top ranks have not beaten the average stock in falling markets, so that is not counted; no proven signal active. Holders can keep; no fresh entry. Technicals: RSI 35; RS rating 53; -33% from 52-wk high; below 20-EMA.
A99: ASHOKLEY | B99: Ashok Leyland Ltd. | C99: Automobile | D99: Mid term (up to 3 months) | E99: Hold | F99: Hold / No fresh trade | G99: 0.28474942 | H99: 0.12952211 | I99: 0.49058663 | J99: 0.03589876 | K99: 1.0428963 | L99: 144.95 | M99: 3.9339567 | U99: Down | V99: Model rank: top 20% buy side / top 26% short side (buy bucket: 70-85%) | W99: ▲ 2B bottom / Turtle soup 22-Oct [no edge]; ▼ Hidden bearish divergence (MACD hist) 22-Oct [no edge]; ▼ Hidden bearish divergence (MFI) 22-Oct [no edge]; ▲ Bullish divergence (MACD hist) 15-Oct [no edge] | X99: Not checked | Y99: No edge either way for 3 months (buy-side model rank: 80th percentile; no proven signal active). Holders can keep; no fresh entry. Technicals: RSI 35; RS rating 53; -33% from 52-wk high; below a falling 50-DMA.
A100: ASHOKLEY | B100: Ashok Leyland Ltd. | C100: Automobile | D100: Long term (up to 1 year) | E100: Hold | F100: Hold / No fresh trade | G100: 0.35529798 | H100: 0.071868264 | I100: 0.51111196 | J100: 0.10959171 | K100: -2.00555 | L100: 144.95 | M100: 3.9339567 | U100: Down | V100: Model rank: top 32% buy side / top 44% short side (buy bucket: 50-70%); - RSI(14) rises back above 30 - fades (13-Oct): -1.6% vs avg stock, t 4.1 | W100: ▲ 2B bottom / Turtle soup 22-Oct [no edge]; ▼ Hidden bearish divergence (MACD hist) 22-Oct [no edge]; ▼ Hidden bearish divergence (MFI) 22-Oct [no edge]; ▲ Bullish divergence (MACD hist) 15-Oct [no edge] | X100: Not checked | Y100: No edge either way for 1 year (buy-side model rank: 68th percentile; no proven signal active). Holders can keep; no fresh entry. Technicals: RSI 35; RS rating 53; -33% from 52-wk high; below a falling 200-DMA.
...

Sheet By Stock
A1: Symbol | B1: Company | C1: Sector | D1: Current price Rs | E1: Short-term call | F1: Short-term buy confidence | G1: Mid-term call | H1: Mid-term buy confidence | I1: Long-term call | J1: Long-term buy confidence | K1: Short-term trend | L1: Mid-term trend | M1: Long-term trend | N1: RS rating (1-99) | O1: % from 52-wk high | P1: Active chart patterns (last 10 sessions) | Q1: Results / news check
A2: KOTAKBANK | B2: Kotak Mahindra Bank Ltd. | C2: Financial Services | D2: 430.5 | E2: Buy | F2: 0.17817111 | G2: Buy | H2: 0.31279249 | I2: Accumulate (buy on dips) | J2: 0.39511908 | K2: Sideways | L2: Up | M2: Sideways | N2: 82 | O2: -0.050088263 | P2: ▼ 2B top / Turtle soup 19-Oct [weak edge]; ▼ Bearish AB=CD 19-Oct [no edge]; ▼ Wyckoff upthrust 16-Oct [works] | Q2: Supportive: Steady earnings growth.
A3: JWL | B3: Jupiter Wagons Ltd. | C3: Industrial Manufacturing | D3: 173.39 | E3: Strong Buy | F3: 0.21183931 | G3: Hold / No fresh trade | H3: 0.29501647 | I3: Hold / No fresh trade | J3: 0.35529798 | K3: Down | L3: Down | M3: Down | N3: 1 | O3: -0.51600838 | P3: ▼ Descending broadening wedge - down breakout 14-Oct [no edge]; ▼ Falling wedge - down breakout 09-Oct [no edge] | Q3: Not checked
A4: JBMA | B4: JBM Auto Ltd. | C4: Automobile | D4: 487.15 | E4: Strong Buy | F4: 0.21183931 | G4: Hold / No fresh trade | H4: 0.29501647 | I4: Hold / No fresh trade | J4: 0.3356492 | K4: Down | L4: Down | M4: Down | N4: 13 | O4: -0.34035206 | P4: ▼ Bear flag 21-Oct [works in reverse]; ▲ 2B bottom / Turtle soup 12-Oct [no edge] | Q4: Not checked
A5: RPOWER | B5: Reliance Power Ltd. | C5: Energy | D5: 16.43 | E5: Strong Buy | F5: 0.21183931 | G5: Hold / No fresh trade | H5: 0.29501647 | I5: Hold / No fresh trade | J5: 0.37136452 | K5: Down | L5: Down | M5: Down | N5: 1 | O5: -0.65591621 | P5: ▼ Falling wedge - down breakout 19-Oct [no edge]; ▼ P&F bearish descending breakdown 15-Oct [works in reverse]; ▼ Wave-3 / ABC breakdown 15-Oct [no edge] | Q5: Not checked
A6: TRITURBINE | B6: Triveni Turbine Ltd. | C6: Industrial Manufacturing | D6: 445.05 | E6: Strong Buy | F6: 0.21183931 | G6: Hold / No fresh trade | H6: 0.31745648 | I6: Hold / No fresh trade | J6: 0.38248096 | K6: Down | L6: Down | M6: Down | N6: 19 | O6: -0.43492889 | P6: ▼ Falling wedge - down breakout 19-Oct [no edge]; ▲ 2B bottom / Turtle soup 15-Oct [no edge]; ▲ Wyckoff spring 15-Oct [works in reverse] | Q6: Mixed: Margins compressed; export and aftermarket orders strong.
A7: EIDPARRY | B7: E.I.D. Parry (India) Ltd. | C7: Fertilisers & Pesticides | D7: 627.5 | E7: Strong Buy | F7: 0.21183931 | G7: Hold / No fresh trade | H7: 0.28474942 | I7: Hold / No fresh trade | J7: 0.37136452 | K7: Down | L7: Down | M7: Down | N7: 7 | O7: -0.43872986 | P7: ▼ P&F bearish descending breakdown 21-Oct [works in reverse]; ▲ 2B bottom / Turtle soup 19-Oct [no edge]; ▲ Downtrend-line breakout 12-Oct [works in reverse] | Q7: Not checked
A8: NBCC | B8: NBCC (India) Ltd. | C8: Construction | D8: 67.9 | E8: Strong Buy | F8: 0.21183931 | G8: Hold / No fresh trade | H8: 0.28353408 | I8: Hold / No fresh trade | J8: 0.34676564 | K8: Down | L8: Down | M8: Down | N8: 3 | O8: -0.46046883 | Q8: Not checked
A9: GODFRYPHLP | B9: Godfrey Phillips India Ltd. | C9: Consumer Goods | D9: 1669 | E9: Strong Buy | F9: 0.21183931 | G9: Hold / No fresh trade | H9: 0.28353408 | I9: Hold / No fresh trade | J9: 0.34676564 | K9: Down | L9: Down | M9: Down | N9: 7 | O9: -0.51649815 | P9: ▼ Falling wedge - down breakout 22-Oct [no edge]; ▼ Hidden bearish divergence (MFI) 21-Oct [no edge]; ▼ Wave-3 / ABC breakdown 21-Oct [no edge] | Q9: Not checked
A10: GMDCLTD | B10: Gujarat Mineral Development Corporation Ltd. | C10: Metals | D10: 424.6 | E10: Strong Buy | F10: 0.21183931 | G10: Hold / No fresh trade | H10: 0.28353408 | I10: Hold / No fresh trade | J10: 0.35529798 | K10: Down | L10: Down | M10: Down | N10: 6 | O10: -0.44992874 | P10: ▼ Bear flag 21-Oct [works in reverse]; ▲ 2B bottom / Turtle soup 19-Oct [no edge] | Q10: Not checked
A11: OLECTRA | B11: Olectra Greentech Ltd. | C11: Automobile | D11: 955.7 | E11: Strong Buy | F11: 0.21183931 | G11: Hold / No fresh trade | H11: 0.31745648 | I11: Hold / No fresh trade | J11: 0.35529798 | K11: Down | L11: Down | M11: Down | N11: 9 | O11: -0.39274368 | P11: ▼ Bear pennant 21-Oct [no edge] | Q11: Not checked
A12: THERMAX | B12: Thermax Ltd. | C12: Industrial Manufacturing | D12: 3096 | E12: Strong Buy | F12: 0.21183931 | G12: Hold / No fresh trade | H12: 0.31745648 | I12: Hold / No fresh trade | J12: 0.34676564 | K12: Down | L12: Down | M12: Sideways | N12: 28 | O12: -0.41339195 | P12: ▼ P&F bearish descending breakdown 23-Oct [works in reverse]; ▲ 2B bottom / Turtle soup 21-Oct [no edge]; ▼ Hidden bearish divergence (MACD hist) 21-Oct [no edge] | Q12: Negative: Rs 91 Cr one-off project cost overrun; order book Rs 14,045 Cr.
A13: VOLTAS | B13: Voltas Ltd. | C13: Consumer Goods | D13: 950 | E13: Strong Buy | F13: 0.21183931 | G13: Hold / No fresh trade | H13: 0.28353408 | I13: Hold / No fresh trade | J13: 0.32912876 | K13: Down | L13: Down | M13: Down | N13: 3 | O13: -0.39968403 | P13: ▼ Bear flag 21-Oct [works in reverse] | Q13: Not checked
A14: AVANTIFEED | B14: Avanti Feeds Ltd. | C14: Fast Moving Consumer Goods | D14: 675.7 | E14: Strong Buy | F14: 0.21183931 | G14: Hold / No fresh trade | H14: 0.31745648 | I14: Hold / No fresh trade | J14: 0.35529798 | K14: Down | L14: Down | M14: Down | N14: 9 | O14: -0.57604465 | P14: ▲ Downtrend-line breakout 14-Oct [works in reverse]; ▲ Falling wedge - up breakout 14-Oct [no edge]; ▲ 2B bottom / Turtle soup 12-Oct [no edge] | Q14: Not checked
A15: ATGL | B15: Adani Total Gas Ltd. | C15: Energy | D15: 529.5 | E15: Strong Buy | F15: 0.21183931 | G15: Hold / No fresh trade | H15: 0.28353408 | I15: Hold / No fresh trade | J15: 0.3910133 | K15: Down | L15: Down | M15: Down | N15: 34 | O15: -0.38419491 | P15: ▲ Bullish AB=CD 14-Oct [no edge]; ▲ Bullish Wolfe wave 14-Oct [no edge] | Q15: Not checked
A16: CESC | B16: CESC Ltd. | C16: Energy | D16: 124.79 | E16: Strong Buy | F16: 0.21183931 | G16: Hold / No fresh trade | H16: 0.28353408 | I16: Hold / No fresh trade | J16: 0.35529798 | K16: Down | L16: Down | M16: Down | N16: 9 | O16: -0.38977997 | P16: ▼ P&F bearish descending breakdown 23-Oct [works in reverse]; ▲ 2B bottom / Turtle soup 09-Oct [no edge]; ▲ Downtrend-line breakout 09-Oct [works in reverse] | Q16: Not checked
A17: KEC | B17: Kec International Ltd. | C17: Construction | D17: 327.75 | E17: Strong Buy | F17: 0.21183931 | G17: Hold / No fresh trade | H17: 0.31745648 | I17: Hold / No fresh trade | J17: 0.34676564 | K17: Down | L17: Down | M17: Down | N17: 1 | O17: -0.62258175 | P17: ▼ P&F bearish descending breakdown 19-Oct [works in reverse]; ▼ Wave-3 / ABC breakdown 19-Oct [no edge]; ▼ Hidden bearish divergence (MFI) 12-Oct [no edge] | Q17: Not checked
A18: TITAGARH | B18: Titagarh Rail Systems Ltd. | C18: Industrial Manufacturing | D18: 663.35 | E18: Strong Buy | F18: 0.21183931 | G18: Hold / No fresh trade | H18: 0.31745648 | I18: Hold / No fresh trade | J18: 0.37136452 | K18: Down | L18: Down | M18: Down | N18: 25 | O18: -0.3168383 | P18: ▲ Wyckoff spring 13-Oct [works in reverse] | Q18: Not checked
A19: RVNL | B19: Rail Vikas Nigam Ltd. | C19: Construction | D19: 181.31 | E19: Strong Buy | F19: 0.21183931 | G19: Hold / No fresh trade | H19: 0.29501647 | I19: Hold / No fresh trade | J19: 0.3910133 | K19: Down | L19: Down | M19: Down | N19: 2 | O19: -0.54751686 | P19: ▼ Wave-3 / ABC breakdown 23-Oct [no edge]; ▼ P&F bearish descending breakdown 22-Oct [works in reverse]; ▲ 2B bottom / Turtle soup 21-Oct [no edge] | Q19: Not checked
A20: AIAENG | B20: AIA Engineering Ltd. | C20: Industrial Manufacturing | D20: 3579.2 | E20: Strong Buy | F20: 0.21183931 | G20: Hold / No fresh trade | H20: 0.28474942 | I20: Hold / No fresh trade | J20: 0.35529798 | K20: Down | L20: Down | M20: Down | N20: 47 | O20: -0.30903475 | P20: ▲ 2B bottom / Turtle soup 15-Oct [no edge]; ▼ Horizontal support breakdown (3+ touches) 15-Oct [weak edge]; ▲ Bullish Wolfe wave 12-Oct [no edge] | Q20: Not checked
... A44: DIXON | B44: Dixon Technologies (India) Ltd. | C44: Consumer Goods | D44: 11191 | E44: Hold / No fresh trade | F44: 0.17962269 | G44: Hold / No fresh trade | H44: 0.27614069 | I44: Hold / No fresh trade | J44: 0.37795048 | K44: Down | L44: Down | M44: Down | N44: 38 | O44: -0.34166718 | P44: ▼ Uptrend-line breakdown 19-Oct [no edge]; ▲ Wyckoff spring 13-Oct [works in reverse]; ▲ 2B bottom / Turtle soup 09-Oct [no edge] | Q44: Not checked
A45: EXIDEIND | B45: Exide Industries Ltd. | C45: Automobile | D45: 331.95 | E45: Hold / No fresh trade | F45: 0.17962269 | G45: Hold / No fresh trade | H45: 0.28474942 | I45: Hold / No fresh trade | J45: 0.38447092 | K45: Down | L45: Down | M45: Sideways | N45: 34 | O45: -0.33128525 | Q45: Not checked
A46: SCHNEIDER | B46: Schneider Electric Infrastructure Ltd. | C46: Industrial Manufacturing | D46: 1114.1 | E46: Hold / No fresh trade | F46: 0.17962269 | G46: Hold / No fresh trade | H46: 0.28219231 | I46: Hold / No fresh trade | J46: 0.39558736 | K46: Down | L46: Down | M46: Up | N46: 86 | O46: -0.28029716 | P46: ▲ Key reversal day (bullish) 22-Oct [no edge]; ▲ Wyckoff spring 22-Oct [works in reverse]; ▼ Horizontal support breakdown (3+ touches) 19-Oct [weak edge] | Q46: Mixed: Record order inflow but margin pressure.
A47: AMBER | B47: Amber Enterprises India Ltd. | C47: Consumer Goods | D47: 6004.5 | E47: Hold / No fresh trade | F47: 0.17962269 | G47: Hold / No fresh trade | H47: 0.27001717 | I47: Hold / No fresh trade | J47: 0.36484408 | K47: Down | L47: Down | M47: Down | N47: 25 | O47: -0.33090038 | P47: ▼ Channel down - down breakout 23-Oct [no edge]; ▼ Hidden bearish divergence (MACD hist) 21-Oct [no edge]; ▼ Hidden bearish divergence (MFI) 21-Oct [no edge] | Q47: Not checked
A48: ZEEL | B48: Zee Entertainment Enterprises Ltd. | C48: Media & Entertainment | D48: 65.42 | E48: Hold / No fresh trade | F48: 0.17962269 | G48: Hold / No fresh trade | H48: 0.28353408 | I48: Hold / No fresh trade | J48: 0.32912876 | K48: Down | L48: Down | M48: Down | N48: 2 | O48: -0.44723278 | P48: ▼ 52-week low breakdown 23-Oct [no edge]; ▼ P&F bearish descending breakdown 23-Oct [works in reverse]; ▼ Hidden bearish divergence (MACD hist) 22-Oct [no edge] | Q48: Not checked
A49: SUMICHEM | B49: Sumitomo Chemical India Ltd. | C49: Fertilisers & Pesticides | D49: 360.6 | E49: Hold / No fresh trade | F49: 0.17962269 | G49: Hold / No fresh trade | H49: 0.27001717 | I49: Hold / No fresh trade | J49: 0.3910133 | K49: Down | L49: Down | M49: Down | N49: 7 | O49: -0.36963551 | P49: ▼ 52-week low breakdown 23-Oct [no edge]; ▼ Bear flag 14-Oct [works in reverse]; ▼ Horizontal support breakdown (3+ touches) 14-Oct [weak edge] | Q49: Not checked
A50: KALYANKJIL | B50: Kalyan Jewellers India Ltd. | C50: Consumer Goods | D50: 512 | E50: Hold / No fresh trade | F50: 0.19087561 | G50: Hold / No fresh trade | H50: 0.27614069 | I50: Hold / No fresh trade | J50: 0.37795048 | K50: Down | L50: Down | M50: Up | N50: 73 | O50: -0.21103321 | P50: ▼ P&F bearish descending breakdown 23-Oct [works in reverse]; ▼ Dow trend reversal down 22-Oct [no edge]; ▼ Hidden bearish divergence (MACD hist) 22-Oct [no edge] | Q50: Not checked
A51: GODREJPROP | B51: Godrej Properties Ltd. | C51: Construction | D51: 1496.5 | E51: Hold / No fresh trade | F51: 0.17962269 | G51: Hold / No fresh trade | H51: 0.28353408 | I51: Hold / No fresh trade | J51: 0.34676564 | K51: Down | L51: Down | M51: Down | N51: 11 | O51: -0.36373299 | P51: ▼ Hidden bearish divergence (MACD hist) 21-Oct [no edge]; ▲ Bullish divergence (MACD hist) 15-Oct [no edge]; ▲ Bullish Quasimodo 13-Oct [tends to fail] | Q51: Not checked
A52: DLF | B52: DLF Ltd. | C52: Construction | D52: 657 | E52: Hold / No fresh trade | F52: 0.1843059 | G52: Hold / No fresh trade | H52: 0.27614069 | I52: Hold / No fresh trade | J52: 0.39558736 | K52: Sideways | L52: Sideways | M52: Sideways | N52: 70 | O52: -0.16465353 | P52: ▼ Bearish divergence (MACD hist) 21-Oct [tends to fail]; ▼ Bearish divergence (OBV) 21-Oct [no edge]; ▼ Bearish divergence (RSI) 21-Oct [works in reverse] | Q52: Not checked
A53: BHARATFORG | B53: Bharat Forge Ltd. | C53: Industrial Manufacturing | D53: 1711.2 | E53: Hold / No fresh trade | F53: 0.17962269 | G53: Hold / No fresh trade | H53: 0.27728413 | I53: Hold / No fresh trade | J53: 0.3910133 | K53: Down | L53: Down | M53: Sideways | N53: 71 | O53: -0.25437908 | P53: ▼ Wave-3 / ABC breakdown 22-Oct [no edge]; ▲ 2B bottom / Turtle soup 21-Oct [no edge]; ▲ Wyckoff spring 21-Oct [works in reverse] | Q53: Not checked
A54: GPIL | B54: Godawari Power and Ispat Ltd. | C54: Metals | D54: 192.34 | E54: Hold / No fresh trade | F54: 0.17962269 | G54: Hold / No fresh trade | H54: 0.28353408 | I54: Hold / No fresh trade | J54: 0.35529798 | K54: Down | L54: Down | M54: Down | N54: 10 | O54: -0.39893749 | P54: ▼ Bear flag 21-Oct [works in reverse] | Q54: Not checked
A55: DATAPATTNS | B55: Data Patterns (India) Ltd. | C55: Industrial Manufacturing | D55: 3792.2 | E55: Hold / No fresh trade | F55: 0.1843059 | G55: Hold / No fresh trade | H55: 0.27614069 | I55: Hold / No fresh trade | J55: 0.39558736 | K55: Down | L55: Down | M55: Sideways | N55: 83 | O55: -0.24156 | P55: ▼ Horizontal support breakdown (3+ touches) 09-Oct [weak edge]; ▼ Triple top 09-Oct [no edge] | Q55: Not checked
A56: CUMMINSIND | B56: Cummins India Ltd. | C56: Industrial Manufacturing | D56: 4344.2 | E56: Hold / No fresh trade | F56: 0.17962269 | G56: Hold / No fresh trade | H56: 0.27606879 | I56: Hold / No fresh trade | J56: 0.35499055 | K56: Down | L56: Down | M56: Sideways | N56: 51 | O56: -0.28783607 | P56: ▼ P&F double-bottom sell 23-Oct [works in reverse]; ▲ Wyckoff spring 22-Oct [works in reverse]; ▲ Bullish Wolfe wave 19-Oct [no edge] | Q56: Not checked
A57: GRAVITA | B57: Gravita India Ltd. | C57: Metals | D57: 1343.2 | E57: Hold / No fresh trade | F57: 0.17962269 | G57: Hold / No fresh trade | H57: 0.29501647 | I57: Hold / No fresh trade | J57: 0.37136452 | K57: Down | L57: Down | M57: Down | N57: 22 | O57: -0.29807692 | P57: ▼ Wave-3 / ABC breakdown 22-Oct [no edge]; ▲ 2B bottom / Turtle soup 21-Oct [no edge]; ▼ P&F bearish descending breakdown 21-Oct [works in reverse] | Q57: Not checked
... A314: GODREJCP | B314: Godrej Consumer Products Ltd. | C314: Consumer Goods | D314: 856.35 | E314: Avoid (likely underperformer) | F314: 0.17962269 | G314: Hold / No fresh trade | H314: 0.27001717 | I314: Hold / No fresh trade | J314: 0.38248096 | K314: Down | L314: Down | M314: Down | N314: 14 | O314: -0.32777298 | P314: ▼ Bearish divergence (OBV) 16-Oct [no edge]; ▲ Hidden bullish divergence (OBV) 15-Oct [no edge]; ▲ Downtrend-line breakout 14-Oct [works in reverse] | Q314: Not checked
A315: M&M | B315: Mahindra & Mahindra Ltd. | C315: Automobile | D315: 2861.2 | E315: Avoid (likely underperformer) | F315: 0.16804434 | G315: Hold / No fresh trade | H315: 0.28474942 | I315: Hold / No fresh trade | J315: 0.31927523 | K315: Down | L315: Down | M315: Down | N315: 35 | O315: -0.25487642 | Q315: Not checked
A316: TMCV | B316: Tata Motors Ltd. (commercial vehicles) | C316: Automobile | D316: 396 | E316: Avoid (likely underperformer) | F316: 0.16804434 | G316: Hold / No fresh trade | H316: 0.29501647 | I316: Hold / No fresh trade | J316: 0.37136452 | K316: Down | L316: Down | M316: Sideways | N316: 56 | O316: -0.22200394 | P316: ▼ Hidden bearish divergence (MACD hist) 23-Oct [no edge]; ▼ Horizontal support breakdown (3+ touches) 23-Oct [weak edge]; ▼ Wave-3 / ABC breakdown 23-Oct [no edge] | Q316: Not checked
A317: MARUTI | B317: Maruti Suzuki India Ltd. | C317: Automobile | D317: 11230 | E317: Avoid (likely underperformer) | F317: 0.16804434 | G317: Hold / No fresh trade | H317: 0.29501647 | I317: Hold / No fresh trade | J317: 0.31927523 | K317: Down | L317: Down | M317: Down | N317: 16 | O317: -0.35348301 | P317: ▲ 2B bottom / Turtle soup 22-Oct [no edge]; ▼ Hidden bearish divergence (MACD hist) 21-Oct [no edge]; ▲ Bullish divergence (MACD hist) 15-Oct [no edge] | Q317: Not checked
A318: SUZLON | B318: Suzlon Energy Ltd. | C318: Industrial Manufacturing | D318: 37.4 | E318: Hold / No fresh trade | F318: 0.16804434 | G318: Hold / No fresh trade | H318: 0.25519244 | I318: Reduce / Avoid | J318: 0.30470688 | K318: Down | L318: Down | M318: Down | N318: 5 | O318: -0.39186993 | P318: ▼ Hidden bearish divergence (MACD hist) 23-Oct [no edge]; ▼ V-top (spike) 23-Oct [tends to fail]; ▼ Hidden bearish divergence (MFI) 21-Oct [no edge] | Q318: Not checked
A319: TRENT | B319: Trent Ltd. | C319: Consumer Goods | D319: 2727.5 | E319: Hold / No fresh trade | F319: 0.16804434 | G319: Hold / No fresh trade | H319: 0.25176674 | I319: Reduce / Avoid | J319: 0.36484408 | K319: Down | L319: Down | M319: Sideways | N319: 60 | O319: -0.19772333 | P319: ▼ Hidden bearish divergence (MACD hist) 22-Oct [no edge]; ▼ Hidden bearish divergence (RSI) 22-Oct [no edge]; ▼ Fibonacci 38-62% rally failure (downtrend) 19-Oct [works] | Q319: Not checked
A320: IRCON | B320: IRCON International Ltd. | C320: Construction | D320: 97.62 | E320: Hold / No fresh trade | F320: 0.16804434 | G320: Avoid (likely underperformer) | H320: 0.27001717 | I320: Hold / No fresh trade | J320: 0.36484408 | K320: Down | L320: Down | M320: Down | N320: 2 | O320: -0.47639992 | P320: ▼ P&F triple-bottom sell 22-Oct [no edge]; ▼ Descending triangle - down breakout 21-Oct [no edge]; ▼ Dow trend reversal down 21-Oct [no edge] | Q320: Negative: Revenue up but consolidated profit fell sharply; order book Rs 23,366 Cr.
A321: DEEPAKNTR | B321: Deepak Nitrite Ltd. | C321: Chemicals | D321: 1446.8 | E321: Hold / No fresh trade | F321: 0.16804434 | G321: Hold / No fresh trade | H321: 0.28353408 | I321: Reduce / Avoid | J321: 0.3723857 | K321: Down | L321: Down | M321: Down | N321: 39 | O321: -0.23768375 | P321: ▼ Descending triangle - down breakout 23-Oct [no edge]; ▼ P&F bearish descending breakdown 23-Oct [works in reverse]; ▼ Wave-3 / ABC breakdown 23-Oct [no edge] | Q321: Not checked
A322: TATAINVEST | B322: Tata Investment Corporation Ltd. | C322: Financial Services | D322: 548.5 | E322: Hold / No fresh trade | F322: 0.16804434 | G322: Hold / No fresh trade | H322: 0.27001717 | I322: Reduce / Avoid | J322: 0.33283382 | K322: Down | L322: Down | M322: Down | N322: 15 | O322: -0.42565445 | P322: ▼ Bear flag 21-Oct [works in reverse]; ▼ Hidden bearish divergence (MACD hist) 21-Oct [no edge]; ▼ Hidden bearish divergence (MFI) 21-Oct [no edge] | Q322: Not checked
A323: SBIN | B323: State Bank of India | C323: Financial Services | D323: 958.6 | E323: Avoid (likely underperformer) | F323: 0.16804434 | G323: Hold / No fresh trade | H323: 0.31745648 | I323: Hold / No fresh trade | J323: 0.34899703 | K323: Down | L323: Down | M323: Down | N323: 60 | O323: -0.22361708 | P323: ▼ Hidden bearish divergence (MACD hist) 22-Oct [no edge]; ▼ Hidden bearish divergence (MFI) 22-Oct [no edge]; ▼ Hidden bearish divergence (OBV) 22-Oct [no edge] | Q323: Not checked
A324: AXISBANK | B324: Axis Bank Ltd. | C324: Financial Services | D324: 1217.5 | E324: Hold / No fresh trade | F324: 0.16804434 | G324: Hold / No fresh trade | H324: 0.29501647 | I324: Reduce / Avoid | J324: 0.37461709 | K324: Sideways | L324: Sideways | M324: Down | N324: 63 | O324: -0.14157795 | P324: ▼ Hidden bearish divergence (MFI) 21-Oct [no edge]; ▼ Bearish Quasimodo 19-Oct [no edge] | Q324: Not checked
A325: SIGNATURE | B325: Signatureglobal (India) Ltd. | C325: Construction | D325: 710.75 | E325: Hold / No fresh trade | F325: 0.16804434 | G325: Avoid (likely underperformer) | H325: 0.28353408 | I325: Hold / No fresh trade | J325: 0.36484408 | K325: Down | L325: Down | M325: Down | N325: 26 | O325: -0.38404541 | P325: ▼ Bearish Quasimodo 19-Oct [no edge] | Q325: Not checked
A326: JUBLINGREA | B326: Jubilant Ingrevia Ltd. | C326: Chemicals | D326: 601.9 | E326: Avoid (likely underperformer) | F326: 0.16804434 | G326: Hold / No fresh trade | H326: 0.28353408 | I326: Hold / No fresh trade | J326: 0.38248096 | K326: Down | L326: Down | M326: Down | N326: 30 | O326: -0.24289309 | P326: ▼ Hidden bearish divergence (MFI) 21-Oct [no edge]; ▼ Hidden bearish divergence (RSI) 21-Oct [no edge]; ▼ Horizontal support breakdown (3+ touches) 21-Oct [weak edge] | Q326: Not checked
A327: RHIM | B327: RHI Magnesita India Ltd. | C327: Industrial Manufacturing | D327: 351.3 | E327: Hold / No fresh trade | F327: 0.16804434 | G327: Avoid (likely underperformer) | H327: 0.28474942 | I327: Hold / No fresh trade | J327: 0.37136452 | K327: Down | L327: Down | M327: Down | N327: 29 | O327: -0.29683746 | P327: ▼ P&F bearish descending breakdown 21-Oct [works in reverse] | Q327: Not checked
... A403: GALLANTT | B403: Gallantt Ispat Ltd. | C403: Metals | D403: 541.85 | E403: Hold / No fresh trade | F403: 0.12666885 | G403: Hold / No fresh trade | H403: 0.23981185 | I403: Reduce / Avoid | J403: 0.33667038 | K403: Sideways | L403: Down | M403: Down | N403: 45 | O403: -0.42842827 | P403: ▼ Pipe top (weekly) 23-Oct [tends to fail]; ▼ V-top (spike) 22-Oct [tends to fail]; ▼ P&F double-bottom sell 22-Oct [works in reverse] | Q403: Not checked
A404: TENNIND | B404: Tenneco Clean Air India Ltd. | C404: Automobile | D404: 439.65 | E404: Avoid (likely underperformer) | F404: 0.21183931 | G404: Avoid (likely underperformer) | H404: 0.28474942 | I404: Hold / No fresh trade | J404: 0.3910133 | K404: Down | L404: Down | M404: Down | N404: 21 | O404: -0.33082191 | Q404: Not checked
A405: MRF | B405: MRF Ltd. | C405: Automobile | D405: 117915 | E405: Avoid (likely underperformer) | F405: 0.21183931 | G405: Avoid (likely underperformer) | H405: 0.28353408 | I405: Hold / No fresh trade | J405: 0.37136452 | K405: Down | L405: Down | M405: Down | N405: 32 | O405: -0.27924816 | P405: ▼ 52-week low breakdown 21-Oct [no edge]; ▼ P&F double-bottom sell 21-Oct [works in reverse]; ▲ Wyckoff spring 15-Oct [works in reverse] | Q405: Not checked
A406: IEX | B406: Indian Energy Exchange Ltd. | C406: Financial Services | D406: 101.2 | E406: Hold / No fresh trade | F406: 0.17962269 | G406: Avoid (likely underperformer) | H406: 0.31745648 | I406: Reduce / Avoid | J406: 0.28600206 | K406: Down | L406: Down | M406: Down | N406: 17 | O406: -0.36856556 | P406: ▲ 2B bottom / Turtle soup 21-Oct [no edge]; ▲ Bullish divergence (MACD hist) 14-Oct [no edge]; ▲ Bullish divergence (MFI) 14-Oct [tends to fail] | Q406: Not checked
A407: HONAUT | B407: Honeywell Automation India Ltd. | C407: Industrial Manufacturing | D407: 31470 | E407: Avoid (likely underperformer) | F407: 0.17962269 | G407: Avoid (likely underperformer) | H407: 0.27728413 | I407: Hold / No fresh trade | J407: 0.35529798 | K407: Down | L407: Down | M407: Down | N407: 44 | O407: -0.24159536 | P407: ▼ Falling wedge - down breakout 21-Oct [no edge]; ▲ Wyckoff spring 16-Oct [works in reverse]; ▲ Bullish AB=CD 14-Oct [no edge] | Q407: Not checked
A408: AFFLE | B408: Affle (India) Ltd. | C408: IT | D408: 1326.2 | E408: Hold / No fresh trade | F408: 0.17962269 | G408: Avoid (likely underperformer) | H408: 0.23981185 | I408: Reduce / Avoid | J408: 0.32912876 | K408: Down | L408: Down | M408: Down | N408: 30 | O408: -0.32972809 | P408: ▼ Horizontal support breakdown (3+ touches) 22-Oct [weak edge]; ▲ 2B bottom / Turtle soup 21-Oct [no edge]; ▼ Hidden bearish divergence (MACD hist) 21-Oct [no edge] | Q408: Not checked
A409: ECLERX | B409: eClerx Services Ltd. | C409: IT | D409: 1891.7 | E409: Hold / No fresh trade | F409: 0.17962269 | G409: Avoid (likely underperformer) | H409: 0.23981185 | I409: Reduce / Avoid | J409: 0.36484408 | K409: Sideways | L409: Sideways | M409: Sideways | N409: 70 | O409: -0.24256256 | P409: ▲ Pocket pivot 22-Oct [no edge]; ▼ Bearish divergence (MFI) 21-Oct [works in reverse]; ▼ 2B top / Turtle soup 14-Oct [weak edge] | Q409: Supportive: Margins dipped on wage hikes (EBITDA margin 24.2%); zero debt, Rs 1,259 Cr cash; Rs 1 interim dividend.
A410: ASIANPAINT | B410: Asian Paints Ltd. | C410: Consumer Goods | D410: 2307 | E410: Avoid (likely underperformer) | F410: 0.17962269 | G410: Hold / No fresh trade | H410: 0.27728413 | I410: Reduce / Avoid | J410: 0.33283382 | K410: Down | L410: Down | M410: Down | N410: 45 | O410: -0.22731688 | P410: ▲ Wyckoff spring 23-Oct [works in reverse]; ▲ 2B bottom / Turtle soup 19-Oct [no edge]; ▲ Elliott 5-wave decline complete 13-Oct [tends to fail] | Q410: Not checked
A411: INDUSTOWER | B411: Indus Towers Ltd. | C411: Telecom | D411: 380 | E411: Hold / No fresh trade | F411: 0.17962269 | G411: Avoid (likely underperformer) | H411: 0.27001717 | I411: Reduce / Avoid | J411: 0.38248096 | K411: Sideways | L411: Sideways | M411: Down | N411: 63 | O411: -0.21079958 | P411: ▼ Hidden bearish divergence (MFI) 22-Oct [no edge]; ▲ Bullish Quasimodo 16-Oct [tends to fail] | Q411: Not checked
A412: LLOYDSME | B412: Lloyds Metals and Energy Ltd. | C412: Metals | D412: 1781.5 | E412: Avoid (likely underperformer) | F412: 0.17962269 | G412: Avoid (likely underperformer) | H412: 0.28474942 | I412: Hold / No fresh trade | J412: 0.3910133 | K412: Down | L412: Down | M412: Up | N412: 85 | O412: -0.16164705 | P412: ▲ 2B bottom / Turtle soup 23-Oct [no edge]; ▼ Hidden bearish divergence (MACD hist) 23-Oct [no edge]; ▼ Hidden bearish divergence (MFI) 23-Oct [no edge] | Q412: Not checked
A413: HINDUNILVR | B413: Hindustan Unilever Ltd. | C413: Consumer Goods | D413: 1814.7 | E413: Avoid (likely underperformer) | F413: 0.17962269 | G413: Hold / No fresh trade | H413: 0.27606879 | I413: Reduce / Avoid | J413: 0.34136615 | K413: Down | L413: Down | M413: Down | N413: 17 | O413: -0.31962358 | P413: ▲ Wyckoff spring 23-Oct [works in reverse]; ▲ 2B bottom / Turtle soup 22-Oct [no edge]; ▲ Horn bottom (weekly) 16-Oct [works in reverse] | Q413: Not checked
A414: MSUMI | B414: Motherson Sumi Wiring India Ltd. | C414: Automobile | D414: 34.6 | E414: Avoid (likely underperformer) | F414: 0.17962269 | G414: Avoid (likely underperformer) | H414: 0.28353408 | I414: Hold / No fresh trade | J414: 0.35529798 | K414: Down | L414: Down | M414: Down | N414: 24 | O414: -0.35435715 | P414: ▼ Hidden bearish divergence (MACD hist) 23-Oct [no edge]; ▼ Hidden bearish divergence (MFI) 23-Oct [no edge]; ▼ Hidden bearish divergence (RSI) 23-Oct [no edge] | Q414: Not checked
A415: ESCORTS | B415: Escorts Ltd. | C415: Automobile | D415: 2627 | E415: Avoid (likely underperformer) | F415: 0.16804434 | G415: Avoid (likely underperformer) | H415: 0.29501647 | I415: Hold / No fresh trade | J415: 0.37136452 | K415: Down | L415: Down | M415: Down | N415: 22 | O415: -0.34124077 | P415: ▼ Dow trend reversal down 22-Oct [no edge]; ▼ Hidden bearish divergence (MACD hist) 22-Oct [no edge]; ▼ Symmetrical triangle - down breakout 22-Oct [no edge] | Q415: Not checked
A416: IGL | B416: Indraprastha Gas Ltd. | C416: Energy | D416: 141.71 | E416: Avoid (likely underperformer) | F416: 0.16804434 | G416: Avoid (likely underperformer) | H416: 0.27728413 | I416: Hold / No fresh trade | J416: 0.37136452 | K416: Down | L416: Down | M416: Down | N416: 29 | O416: -0.3532177 | P416: ▲ 2B bottom / Turtle soup 23-Oct [no edge]; ▲ Key reversal day (bullish) 23-Oct [no edge]; ▲ Wyckoff spring 23-Oct [works in reverse] | Q416: Not checked
... A426: WAAREEENER | B426: Waaree Energies Ltd. | C426: Energy | D426: 2354.9 | E426: Hold / No fresh trade | F426: 0.15632036 | G426: Avoid (likely underperformer) | H426: 0.26992539 | I426: Reduce / Avoid | J426: 0.28248096 | K426: Sideways | L426: Down | M426: Down | N426: 21 | O426: -0.36675808 | P426: ▼ Hidden bearish divergence (MACD hist) 22-Oct [no edge]; ▼ V-top (spike) 22-Oct [tends to fail]; ▼ 2B top / Turtle soup 19-Oct [weak edge] | Q426: Not checked
A427: OIL | B427: Oil India Ltd. | C427: Energy | D427: 447.85 | E427: Avoid (likely underperformer) | F427: 0.14748707 | G427: Avoid (likely underperformer) | H427: 0.28474942 | I427: Hold / No fresh trade | J427: 0.38248096 | K427: Down | L427: Down | M427: Sideways | N427: 68 | O427: -0.15659134 | Q427: Not checked
A428: UBL | B428: United Breweries Ltd. | C428: Consumer Goods | D428: 1142.6 | E428: Hold / No fresh trade | F428: 0.14748707 | G428: Avoid (likely underperformer) | H428: 0.27001717 | I428: Reduce / Avoid | J428: 0.38248096 | K428: Down | L428: Down | M428: Down | N428: 12 | O428: -0.38036877 | P428: ▲ 2B bottom / Turtle soup 23-Oct [no edge]; ▼ Bearish divergence (MFI) 21-Oct [works in reverse]; ▼ Bearish divergence (OBV) 21-Oct [no edge] | Q428: Not checked
A429: NAUKRI | B429: Info Edge (India) Ltd. | C429: IT | D429: 1186.5 | E429: Hold / No fresh trade | F429: 0.14748707 | G429: Avoid (likely underperformer) | H429: 0.23234656 | I429: Reduce / Avoid | J429: 0.36484408 | K429: Down | L429: Down | M429: Sideways | N429: 66 | O429: -0.16437777 | P429: ▲ 2B bottom / Turtle soup 23-Oct [no edge]; ▲ Wyckoff spring 23-Oct [works in reverse]; ▼ Bearish AB=CD 19-Oct [no edge] | Q429: Not checked
A430: ITCHOTELS | B430: ITC Hotels Ltd. | C430: Services | D430: 156.25 | E430: Avoid (likely underperformer) | F430: 0.14441592 | G430: Hold / No fresh trade | H430: 0.25519244 | I430: Reduce / Avoid | J430: 0.33086869 | K430: Sideways | L430: Down | M430: Down | N430: 45 | O430: -0.31055023 | P430: ▼ Hidden bearish divergence (MFI) 21-Oct [no edge]; ▼ Hidden bearish divergence (OBV) 21-Oct [no edge]; ▲ Bullish divergence (MFI) 15-Oct [tends to fail] | Q430: Not checked
A431: PIDILITIND | B431: Pidilite Industries Ltd. | C431: Chemicals | D431: 1487.7 | E431: Avoid (likely underperformer) | F431: 0.14748707 | G431: Hold / No fresh trade | H431: 0.27728413 | I431: Reduce / Avoid | J431: 0.37136452 | K431: Down | L431: Down | M431: Sideways | N431: 67 | O431: -0.12872621 | P431: ▲ Bullish AB=CD 23-Oct [no edge]; ▲ Channel down - up breakout 23-Oct [no edge]; ▲ Descending triangle - up breakout 23-Oct [no edge] | Q431: Not checked
A432: PNB | B432: Punjab National Bank | C432: Financial Services | D432: 120.37 | E432: Hold / No fresh trade | F432: 0.14748707 | G432: Avoid (likely underperformer) | H432: 0.31474808 | I432: Reduce / Avoid | J432: 0.37461709 | K432: Up | L432: Up | M432: Sideways | N432: 75 | O432: -0.10935997 | P432: ▼ Bearish AB=CD 23-Oct [no edge]; ▲ Pocket pivot 21-Oct [no edge]; ▲ Ascending broadening wedge - up breakout 19-Oct [no edge] | Q432: Not checked
A433: BSOFT | B433: Birlasoft Ltd. | C433: IT | D433: 303.75 | E433: Hold / No fresh trade | F433: 0.14748707 | G433: Avoid (likely underperformer) | H433: 0.21025487 | I433: Reduce / Avoid | J433: 0.31425299 | K433: Up | L433: Sideways | M433: Down | N433: 50 | O433: -0.35917721 | P433: ▼ Bearish Crab 23-Oct [rare]; ▼ Wyckoff upthrust 21-Oct [works]; ▲ Triple bottom 15-Oct [no edge] | Q433: Not checked
A434: TATAELXSI | B434: Tata Elxsi Ltd. | C434: IT | D434: 3700 | E434: Hold / No fresh trade | F434: 0.14748707 | G434: Avoid (likely underperformer) | H434: 0.23981185 | I434: Reduce / Avoid | J434: 0.26484408 | K434: Up | L434: Sideways | M434: Down | N434: 42 | O434: -0.37815125 | P434: ▼ Key reversal day (bearish) 23-Oct [no edge]; ▲ P&F triple-top buy 19-Oct [no edge]; ▲ Bullish divergence (OBV) 13-Oct [no edge] | Q434: Not checked
A435: ZENSARTECH | B435: Zensar Technolgies Ltd. | C435: IT | D435: 493.7 | E435: Hold / No fresh trade | F435: 0.14748707 | G435: Avoid (likely underperformer) | H435: 0.23981185 | I435: Reduce / Avoid | J435: 0.31425299 | K435: Up | L435: Sideways | M435: Down | N435: 31 | O435: -0.39939175 | P435: ▼ Bearish Crab 22-Oct [rare]; ▼ Wyckoff upthrust 19-Oct [works]; ▲ Falling wedge - up breakout 14-Oct [no edge] | Q435: Not checked
A436: ZYDUSLIFE | B436: Zydus Lifesciences Ltd. | C436: Pharma | D436: 1129.4 | E436: Hold / No fresh trade | F436: 0.14748707 | G436: Avoid (likely underperformer) | H436: 0.23981185 | I436: Reduce / Avoid | J436: 0.38248096 | K436: Down | L436: Down | M436: Up | N436: 85 | O436: -0.083353624 | P436: ▲ Bullish divergence (MACD hist) 23-Oct [no edge]; ▲ Bullish divergence (RSI) 23-Oct [no edge]; ▲ 2B bottom / Turtle soup 22-Oct [no edge] | Q436: Not checked
A437: DIVISLAB | B437: Divi's Laboratories Ltd. | C437: Pharma | D437: 8950 | E437: Hold / No fresh trade | F437: 0.12666885 | G437: Avoid (likely underperformer) | H437: 0.23981185 | I437: Reduce / Avoid | J437: 0.36484408 | K437: Down | L437: Sideways | M437: Up | N437: 94 | O437: -0.081108828 | P437: ▲ 2B bottom / Turtle soup 23-Oct [no edge]; ▼ Descending triangle - down breakout 23-Oct [no edge]; ▼ P&F double-bottom sell 23-Oct [works in reverse] | Q437: Not checked
A438: OFSS | B438: Oracle Financial Services Software Ltd. | C438: IT | D438: 9677 | E438: Hold / No fresh trade | F438: 0.12666885 | G438: Avoid (likely underperformer) | H438: 0.23981185 | I438: Reduce / Avoid | J438: 0.31519694 | K438: Down | L438: Down | M438: Up | N438: 77 | O438: -0.2283094 | P438: ▼ Three drives top 22-Oct [no edge]; ▲ 2B bottom / Turtle soup 16-Oct [no edge]; ▼ Hidden bearish divergence (MACD hist) 15-Oct [no edge] | Q438: Not checked
A439: JSWCEMENT | B439: JSW Cement Ltd. | C439: Cement & Cement Products | D439: 116.98 | E439: Avoid (likely underperformer) | F439: 0.12666885 | G439: Avoid (likely underperformer) | H439: 0.230121 | I439: Hold / No fresh trade | J439: 0.35499055 | K439: Sideways | L439: Down | M439: Down | N439: 48 | O439: -0.18423988 | P439: ▲ Ascending triangle - up breakout 23-Oct [no edge]; ▲ Descending broadening wedge - up breakout 23-Oct [no edge]; ▼ Bearish AB=CD 21-Oct [no edge] | Q439: Not checked
... A477: TTML | B477: Tata Teleservices (Maharashtra) Ltd. | C477: Telecom | D477: 37.68 | E477: Avoid (likely underperformer) | F477: 0.11526987 | G477: Avoid (likely underperformer) | H477: 0.26721699 | I477: Reduce / Avoid | J477: 0.35474882 | K477: Up | L477: Sideways | M477: Down | N477: 33 | O477: -0.35313305 | P477: ▼ 2B top / Turtle soup 23-Oct [weak edge]; ▲ Bullish divergence (MACD hist) 23-Oct [no edge]; ▲ Bullish divergence (MFI) 23-Oct [tends to fail] | Q477: Mixed: Losses shrinking but still loss-making; RPS redemption extended.
A478: AIIL | B478: Authum Investment & Infrastructure Ltd. | C478: Financial Services | D478: 496.75 | E478: Not rated | G478: Not rated | I478: Not rated | K478: Down | L478: Down | M478: Down | N478: 43 | O478: -0.272694 | P478: ▼ Wave-3 / ABC breakdown 23-Oct [no edge]; ▼ Uptrend-line breakdown 23-Oct [no edge]; ▼ Horizontal support breakdown (3+ touches) 23-Oct [weak edge] | Q478: Not checked
A479: ASAHIINDIA | B479: Asahi India Glass Ltd. | C479: Automobile | D479: 894.3 | E479: Not rated | G479: Not rated | I479: Not rated | K479: Down | L479: Sideways | M479: Down | N479: 71 | O479: -0.16731844 | P479: ▲ Wyckoff spring 23-Oct [works in reverse]; ▼ P&F double-bottom sell 21-Oct [works in reverse]; ▼ Uptrend-line breakdown 21-Oct [no edge] | Q479: Not checked
A480: BATAINDIA | B480: Bata India Ltd. | C480: Consumer Goods | D480: 633.85 | E480: Not rated | G480: Not rated | I480: Not rated | K480: Sideways | L480: Down | M480: Down | N480: 19 | O480: -0.4695816 | P480: ▼ Hidden bearish divergence (MACD hist) 23-Oct [no edge]; ▲ 2B bottom / Turtle soup 09-Oct [no edge] | Q480: Supportive: Margin gains from premiumisation drove the profit beat; Rs 25 interim dividend; top-line growth still slow.
A481: BHARATCOAL | B481: Bharat Coking Coal Ltd. | C481: Oil Gas & Consumable Fuels | D481: 29.76 | E481: Not rated | G481: Not rated | I481: Not rated | K481: Down | L481: Down | M481: Sideways | P481: ▼ Channel down - down breakout 22-Oct [no edge]; ▼ P&F bearish descending breakdown 22-Oct [works in reverse]; ▼ Hidden bearish divergence (MFI) 16-Oct [no edge] | Q481: Not checked
A482: CIEINDIA | B482: CIE Automotive India Ltd. | C482: Automobile | D482: 351.55 | E482: Not rated | G482: Not rated | I482: Not rated | K482: Down | L482: Down | M482: Down | N482: 27 | O482: -0.33165398 | P482: ▼ Breakaway gap down 23-Oct [weak edge]; ▼ 52-week low breakdown 22-Oct [no edge]; ▼ P&F bearish descending breakdown 22-Oct [works in reverse] | Q482: Not checked
A483: CLEANMAX | B483: Clean Max Enviro Energy Solutions Ltd. | C483: Power | D483: 1175.9 | E483: Not rated | G483: Not rated | I483: Not rated | K483: Down | L483: Down | M483: Sideways | P483: ▲ 2B bottom / Turtle soup 16-Oct [no edge]; ▼ Horizontal support breakdown (3+ touches) 15-Oct [weak edge]; ▼ Bearish divergence (MACD hist) 13-Oct [tends to fail] | Q483: Not checked
A484: CMPDI | B484: Central Mine Planning & Design Institute Ltd. | C484: Services | D484: 183.97 | E484: Not rated | G484: Not rated | I484: Not rated | K484: Down | L484: Down | M484: Sideways | P484: ▼ P&F bearish descending breakdown 21-Oct [works in reverse]; ▲ 2B bottom / Turtle soup 19-Oct [no edge]; ▼ Hidden bearish divergence (MACD hist) 19-Oct [no edge] | Q484: Not checked
A485: DOMS | B485: DOMS Industries Ltd. | C485: Consumer Goods | D485: 1874.2 | E485: Not rated | G485: Not rated | I485: Not rated | K485: Down | L485: Down | M485: Down | N485: 17 | O485: -0.31970963 | P485: ▼ 52-week low breakdown 21-Oct [no edge]; ▼ Broadening formation - down breakout 21-Oct [rare]; ▼ Horizontal support breakdown (3+ touches) 21-Oct [weak edge] | Q485: Not checked
A486: FACT | B486: Fertilisers and Chemicals Travancore Ltd. | C486: Fertilisers & Pesticides | D486: 670.7 | E486: Not rated | G486: Not rated | I486: Not rated | K486: Down | L486: Down | M486: Down | N486: 18 | O486: -0.36642735 | P486: ▼ Ascending triangle - down breakout 21-Oct [no edge]; ▼ Uptrend-line breakdown 21-Oct [no edge]; ▲ Downtrend-line breakout 15-Oct [works in reverse] | Q486: Not checked
A487: FRACTAL | B487: Fractal Analytics Ltd. | C487: Information Technology | D487: 728.4 | E487: Not rated | G487: Not rated | I487: Not rated | K487: Sideways | L487: Down | M487: Sideways | P487: ▼ Hidden bearish divergence (MACD hist) 23-Oct [no edge]; ▼ Hidden bearish divergence (MFI) 23-Oct [no edge]; ▼ Hidden bearish divergence (OBV) 23-Oct [no edge] | Q487: Not checked
A488: ICICIAMC | B488: ICICI Prudential Asset Management Company Ltd. | C488: Financial Services | D488: 2651.8 | E488: Not rated | G488: Not rated | I488: Not rated | K488: Down | L488: Down | M488: Sideways | N488: 31 | O488: -0.26563278 | P488: ▼ Channel down - down breakout 16-Oct [no edge]; ▼ P&F bearish descending breakdown 14-Oct [works in reverse]; ▲ Wyckoff spring 13-Oct [works in reverse] | Q488: Not checked
A489: INDIAMART | B489: Indiamart Intermesh Ltd. | C489: Consumer Goods | D489: 1572.8 | E489: Not rated | G489: Not rated | I489: Not rated | K489: Down | L489: Down | M489: Down | N489: 14 | O489: -0.37733086 | P489: ▲ Wyckoff spring 23-Oct [works in reverse]; ▲ 2B bottom / Turtle soup 22-Oct [no edge]; ▼ Hidden bearish divergence (MACD hist) 21-Oct [no edge] | Q489: Not checked
A490: ITI | B490: ITI Ltd. | C490: Telecom | D490: 215.38 | E490: Not rated | G490: Not rated | I490: Not rated | K490: Down | L490: Down | M490: Down | N490: 6 | O490: -0.38708027 | P490: ▼ Descending broadening wedge - down breakout 23-Oct [no edge]; ▼ 52-week low breakdown 21-Oct [no edge]; ▼ Wave-3 / ABC breakdown 21-Oct [no edge] | Q490: Not checked
A491: TRIDENT | B491: Trident Ltd. | C491: Textiles | D491: 20.49 | E491: Not rated | G491: Not rated | I491: Not rated | K491: Down | L491: Down | M491: Down | N491: 18 | O491: -0.33775047 | P491: ▼ Channel down - down breakout 23-Oct [no edge]; ▼ Hidden bearish divergence (MACD hist) 16-Oct [no edge]; ▼ Hidden bearish divergence (OBV) 16-Oct [no edge] | Q491: Not checked
A492: UTIAMC | B492: UTI Asset Management Company Ltd. | C492: Financial Services | D492: 817.05 | E492: Not rated | G492: Not rated | I492: Not rated | K492: Down | L492: Down | M492: Down | N492: 17 | O492: -0.42012066 | P492: ▼ 52-week low breakdown 22-Oct [no edge]; ▼ Descending triangle - down breakout 22-Oct [no edge]; ▼ Wave-3 / ABC breakdown 22-Oct [no edge] | Q492: Not checked
A493: VAML | B493: Vedanta Aluminium Metal Ltd. | C493: Metals & Mining | D493: 344.35 | E493: Not rated | G493: Not rated | I493: Not rated | K493: Down | L493: Down | M493: Sideways | P493: ▼ Bear flag 21-Oct [works in reverse] | Q493: Not checked
A494: VEDPOWER | B494: Vedanta Power Ltd. | C494: Power | D494: 28.26 | E494: Not rated | G494: Not rated | I494: Not rated | K494: Down | L494: Down | M494: Sideways | P494: ▼ Falling wedge - down breakout 23-Oct [no edge]; ▼ P&F double-bottom sell 22-Oct [works in reverse]; ▼ Hidden bearish divergence (MFI) 16-Oct [no edge] | Q494: Not checked
A495: VISL | B495: Vedanta Iron and Steel Ltd. | C495: Metals & Mining | D495: 26.22 | E495: Not rated | G495: Not rated | I495: Not rated | K495: Down | L495: Down | M495: Sideways | P495: ▲ 2B bottom / Turtle soup 21-Oct [no edge]; ▼ P&F bearish descending breakdown 21-Oct [works in reverse] | Q495: Not checked
A496: VOGL | B496: Vedanta Oil and Gas Ltd. | C496: Oil Gas & Consumable Fuels | D496: 27.17 | E496: Not rated | G496: Not rated | I496: Not rated | K496: Down | L496: Down | M496: Sideways | P496: ▲ 2B bottom / Turtle soup 21-Oct [no edge]; ▼ P&F bearish descending breakdown 21-Oct [works in reverse]; ▲ Bullish AB=CD 14-Oct [no edge] | Q496: Not checked
A497: ZYDUSWELL | B497: Zydus Wellness Ltd. | C497: Consumer Goods | D497: 463.35 | E497: Not rated | G497: Not rated | I497: Not rated | K497: Down | L497: Down | M497: Sideways | N497: 56 | O497: -0.24270655 | P497: ▼ Descending triangle - down breakout 22-Oct [no edge]; ▼ Horizontal support breakdown (3+ touches) 22-Oct [weak edge]; ▼ P&F bearish descending breakdown 22-Oct [works in reverse] | Q497: Not checked
A498: BAGMANE | B498: Bagmane Prime Office REIT | C498: Realty | E498: Not rated | G498: Not rated | I498: Not rated
A499: BIRET | B499: Brookfield India Real Estate Trust | C499: Realty | E499: Not rated | G499: Not rated | I499: Not rated
A500: DUMMYHEG | B500: Dummy HEG Ltd. | C500: Metals & Mining | E500: Not rated | G500: Not rated | I500: Not rated
...

Sheet Top Picks
A1: Every buy call per timeframe, the strongest 'avoid' flags, and the latest results where checked
A2: Buys: Strong Buy first, then by expected return. Latest quarterly results (Q1 FY27) were checked by web search on 27-Sep-2026 - context only. Levels use the rules on 'Read Me'; recheck the price at the open.
A4: Short term (up to 2 weeks) - all 29 buy calls
A5: # | B5: Symbol | C5: Company | D5: Call | E5: Buy confidence | F5: Average stock | G5: Chance of profit | H5: Expected return / trade | I5: Entry up to Rs | J5: Target Rs | K5: Stop Rs | L5: Max days | M5: Why | N5: Results check | O5: Results & news | P5: Source
A6: 1 | B6: JWL | C6: Jupiter Wagons Ltd. | D6: Strong Buy | E6: 0.21183931 | F6: 0.15396106 | G6: 0.42819519 | H6: 0.0018773479 | I6: 181.83 | J6: 198.72 | K6: 160.72 | L6: 10 | M6: AI model top 1% | N6: Not checked | O6: Not researched
A7: 2 | B7: JBMA | C7: JBM Auto Ltd. | D7: Strong Buy | E7: 0.21183931 | F7: 0.15396106 | G7: 0.42819519 | H7: 0.0018773479 | I7: 504.8 | J7: 540.11 | K7: 460.67 | L7: 10 | M7: AI model top 1% | N7: Not checked | O7: Not researched
A8: 3 | B8: RPOWER | C8: Reliance Power Ltd. | D8: Strong Buy | E8: 0.21183931 | F8: 0.15396106 | G8: 0.42819519 | H8: 0.0018773479 | I8: 17.16 | J8: 18.62 | K8: 15.33 | L8: 10 | M8: AI model top 1% | N8: Not checked | O8: Not researched
A9: 4 | B9: TRITURBINE | C9: Triveni Turbine Ltd. | D9: Strong Buy | E9: 0.21183931 | F9: 0.15396106 | G9: 0.42819519 | H9: 0.0018773479 | I9: 462.88 | J9: 498.55 | K9: 418.3 | L9: 10 | M9: AI model top 1% | N9: Mixed | O9: Q1 FY27 (Apr-Jun 2026) - revenue: +19.2% to Rs 443 Cr; profit: -21% to Rs 51 Cr. Margins compressed; export and aftermarket orders strong. | P9: https://www.business-standard.com/markets/capital-market-news/triveni-turbine-drops-after-q1-pat-declines-21-yoy-to-rs-51-cr-126081100796_1.html
A10: 5 | B10: EIDPARRY | C10: E.I.D. Parry (India) Ltd. | D10: Strong Buy | E10: 0.21183931 | F10: 0.15396106 | G10: 0.42819519 | H10: 0.0018773479 | I10: 647.52 | J10: 687.56 | K10: 597.47 | L10: 10 | M10: AI model top 1% | N10: Not checked | O10: Not researched
A11: 6 | B11: NBCC | C11: NBCC (India) Ltd. | D11: Strong Buy | E11: 0.21183931 | F11: 0.15396106 | G11: 0.42819519 | H11: 0.0018773479 | I11: 69.98 | J11: 74.13 | K11: 64.78 | L11: 10 | M11: AI model top 1% | N11: Not checked | O11: Not researched
A12: 7 | B12: GODFRYPHLP | C12: Godfrey Phillips India Ltd. | D12: Strong Buy | E12: 0.21183931 | F12: 0.15396106 | G12: 0.42819519 | H12: 0.0018773479 | I12: 1724.24 | J12: 1834.73 | K12: 1586.14 | L12: 10 | M12: AI model top 2% | N12: Not checked | O12: Not researched
A13: 8 | B13: GMDCLTD | C13: Gujarat Mineral Development Corporation Ltd. | D13: Strong Buy | E13: 0.21183931 | F13: 0.15396106 | G13: 0.42819519 | H13: 0.0018773479 | I13: 439.98 | J13: 470.75 | K13: 401.53 | L13: 10 | M13: AI model top 2% | N13: Not checked | O13: Not researched
A14: 9 | B14: OLECTRA | C14: Olectra Greentech Ltd. | D14: Strong Buy | E14: 0.21183931 | F14: 0.15396106 | G14: 0.42819519 | H14: 0.0018773479 | I14: 991.7 | J14: 1063.71 | K14: 901.7 | L14: 10 | M14: AI model top 2% | N14: Not checked | O14: Not researched
A15: 10 | B15: THERMAX | C15: Thermax Ltd. | D15: Strong Buy | E15: 0.21183931 | F15: 0.15396106 | G15: 0.42819519 | H15: 0.0018773479 | I15: 3208.32 | J15: 3432.96 | K15: 2927.52 | L15: 10 | M15: AI model top 2% | N15: Negative | O15: Q1 FY27 (Apr-Jun 2026) - revenue: +7% to Rs 2,303 Cr; profit: -83% to about Rs 25 Cr. Rs 91 Cr one-off project cost overrun; order book Rs 14,045 Cr. | P15: https://www.business-standard.com/amp/markets/capital-market-news/thermax-tumbles-after-q1-pat-drops-83-yoy-to-rs-25-cr-126073100562_1.html
A16: 11 | B16: VOLTAS | C16: Voltas Ltd. | D16: Strong Buy | E16: 0.21183931 | F16: 0.15396106 | G16: 0.42819519 | H16: 0.0018773479 | I16: 981 | J16: 1043.01 | K16: 903.5 | L16: 10 | M16: AI model top 3% | N16: Not checked | O16: Not researched
A17: 12 | B17: PGEL | C17: PG Electroplast Ltd. | D17: Strong Buy | E17: 0.21183931 | F17: 0.15396106 | G17: 0.42819519 | H17: 0.0018773479 | I17: 487.07 | J17: 521.1 | K17: 444.52 | L17: 10 | M17: AI model top 3% | N17: Not checked | O17: Not researched
A18: 13 | B18: AVANTIFEED | C18: Avanti Feeds Ltd. | D18: Strong Buy | E18: 0.21183931 | F18: 0.15396106 | G18: 0.42819519 | H18: 0.0018773479 | I18: 698.85 | J18: 745.16 | K18: 640.97 | L18: 10 | M18: AI model top 3% | N18: Not checked | O18: Not researched
A19: 14 | B19: ATGL | C19: Adani Total Gas Ltd. | D19: Strong Buy | E19: 0.21183931 | F19: 0.15396106 | G19: 0.42819519 | H19: 0.0018773479 | I19: 546.76 | J19: 581.29 | K19: 503.61 | L19: 10 | M19: AI model top 3% | N19: Not checked | O19: Not researched
A20: 15 | B20: CESC | C20: CESC Ltd. | D20: Strong Buy | E20: 0.21183931 | F20: 0.15396106 | G20: 0.42819519 | H20: 0.0018773479 | I20: 128.58 | J20: 136.16 | K20: 119.11 | L20: 10 | M20: AI model top 3% | N20: Not checked | O20: Not researched
A21: 16 | B21: KEC | C21: Kec International Ltd. | D21: Strong Buy | E21: 0.21183931 | F21: 0.15396106 | G21: 0.42819519 | H21: 0.0018773479 | I21: 339.91 | J21: 364.23 | K21: 309.51 | L21: 10 | M21: AI model top 4% | N21: Not checked | O21: Not researched
A22: 17 | B22: TITAGARH | C22: Titagarh Rail Systems Ltd. | D22: Strong Buy | E22: 0.21183931 | F22: 0.15396106 | G22: 0.42819519 | H22: 0.0018773479 | I22: 688.66 | J22: 739.27 | K22: 625.39 | L22: 10 | M22: AI model top 4% | N22: Not checked | O22: Not researched
A23: 18 | B23: RVNL | C23: Rail Vikas Nigam Ltd. | D23: Strong Buy | E23: 0.21183931 | F23: 0.15396106 | G23: 0.42819519 | H23: 0.0018773479 | I23: 187.34 | J23: 199.4 | K23: 172.27 | L23: 10 | M23: AI model top 4% | N23: Not checked | O23: Not researched
A24: 19 | B24: AIAENG | C24: AIA Engineering Ltd. | D24: Strong Buy | E24: 0.21183931 | F24: 0.15396106 | G24: 0.42819519 | H24: 0.0018773479 | I24: 3689.77 | J24: 3910.9 | K24: 3413.35 | L24: 10 | M24: AI model top 5% | N24: Not checked | O24: Not researched
A25: 20 | B25: SJVN | C25: SJVN Ltd. | D25: Strong Buy | E25: 0.21183931 | F25: 0.15396106 | G25: 0.42819519 | H25: 0.0018773479 | I25: 49.19 | J25: 52.78 | K25: 44.71 | L25: 10 | M25: AI model top 5% | N25: Not checked | O25: Not researched
A26: 21 | B26: KOTAKBANK | C26: Kotak Mahindra Bank Ltd. | D26: Buy | E26: 0.17817111 | F26: 0.15396106 | G26: 0.43614344 | H26: 0.0054175239 | I26: 440.04 | J26: 459.12 | K26: 416.19 | L26: 10 | M26: Holy Grail: ADX > 30 and pullback to 20 EMA (23-Oct); RSI(2) below 5 in an uptrend (Connors) (23-Oct) | N26: Supportive | O26: Q1 FY27 (Apr-Jun 2026) - revenue: NII +9%; profit: Standalone +26% to Rs 4,123 Cr; consolidated +23% to Rs 5,480 Cr. Steady earnings growth. | P26: https://www.business-standard.com/companies/quarterly-results/kotak-mahindra-bank-q1fy27-results-net-profit-rises-23-to-5-480-crore-126071800554_1.html
A27: 22 | B27: KPRMILL | C27: K.P.R. Mill Ltd. | D27: Buy | E27: 0.16342322 | F27: 0.15396106 | G27: 0.43804557 | H27: 0.0037491042 | I27: 1061.11 | J27: 1134.14 | K27: 969.83 | L27: 10 | M27: Three lower closes in an uptrend (22-Oct); RSI(2) below 5 in an uptrend (Connors) (22-Oct) | N27: Not checked | O27: Not researched
A28: 23 | B28: SOLARINDS | C28: Solar Industries India Ltd. | D28: Buy | E28: 0.16342322 | F28: 0.15396106 | G28: 0.43804557 | H28: 0.0037491042 | I28: 18985.04 | J28: 20225.12 | K28: 17434.94 | L28: 10 | M28: Three lower closes in an uptrend (22-Oct); RSI(2) below 5 in an uptrend (Connors) (22-Oct) | N28: Not checked | O28: Not researched
A29: 24 | B29: APLAPOLLO | C29: APL Apollo Tubes Ltd. | D29: Buy | E29: 0.16342322 | F29: 0.15396106 | G29: 0.43804557 | H29: 0.0037491042 | I29: 2094.51 | J29: 2216.14 | K29: 1942.48 | L29: 10 | M29: Three lower closes in an uptrend (22-Oct); RSI(2) below 5 in an uptrend (Connors) (22-Oct) | N29: Mixed | O29: Q1 FY27 (Apr-Jun 2026) - revenue: Volumes -6% YoY; profit: +11% to Rs 263 Cr. Management reaffirms ~20% EBITDA growth target. | P29: https://scanx.trade/stock-market-news/companies/apl-apollo-tubes-q1-results-net-profit-rises-11-yoy-to-263-crore/47121389
A30: 25 | B30: RKFORGE | C30: Ramkrishna Forgings Ltd. | D30: Buy | E30: 0.16342322 | F30: 0.15396106 | G30: 0.43804557 | H30: 0.0037491042 | I30: 616.82 | J30: 668.25 | K30: 552.52 | L30: 10 | M30: Three lower closes in an uptrend (22-Oct); RSI(2) below 5 in an uptrend (Connors) (22-Oct) | N30: Supportive | O30: Q1 FY27 (Apr-Jun 2026) - revenue: +19.8% to Rs 1,217 Cr; profit: about 4x to Rs 47 Cr. Margin expansion; Rs 170 Cr capex planned. | P30: https://www.business-standard.com/companies/quarterly-results/ramkrishna-forgings-q1-profit-nearly-quadruples-plans-170-crore-capex-126072701123_1.html
A31: 26 | B31: ACMESOLAR | C31: ACME Solar Holdings Ltd. | D31: Buy | E31: 0.16342322 | F31: 0.15396106 | G31: 0.43804557 | H31: 0.0037491042 | I31: 390.38 | J31: 427.45 | K31: 344.05 | L31: 10 | M31: Three lower closes in an uptrend (23-Oct); RSI(2) below 5 in an uptrend (Connors) (23-Oct) | N31: Not checked | O31: Not researched
A32: 27 | B32: NETWEB | C32: Netweb Technologies India Ltd. | D32: Buy | E32: 0.1722565 | F32: 0.15396106 | G32: 0.43318613 | H32: 0.0030396574 | I32: 4552.25 | J32: 4985.14 | K32: 4011.13 | L32: 10 | M32: Three lower closes in an uptrend (22-Oct); RSI(2) below 5 in an uptrend (Connors) (23-Oct) | N32: Not checked | O32: Not researched
A33: 28 | B33: RADICO | C33: Radico Khaitan Ltd | D33: Buy | E33: 0.1722565 | F33: 0.15396106 | G33: 0.43318613 | H33: 0.0030396574 | I33: 4292.09 | J33: 4561.66 | K33: 3955.12 | L33: 10 | M33: Three lower closes in an uptrend (22-Oct); RSI(2) below 5 in an uptrend (Connors) (22-Oct) | N33: Not checked | O33: Not researched
A34: 29 | B34: ATHERENERG | C34: Ather Energy Ltd. | D34: Buy | E34: 0.18398049 | F34: 0.15396106 | G34: 0.42801823 | H34: 0.0026079447 | I34: 1439.62 | J34: 1558.87 | K34: 1290.57 | L34: 10 | M34: Three lower closes in an uptrend (22-Oct); RSI(2) below 5 in an uptrend (Connors) (22-Oct) | N34: Not checked | O34: Not researched
A36: Short term (up to 2 weeks) - strongest avoid / reduce flags
A37: # | B37: Symbol | C37: Company | D37: Call | E37: Short-side rank | F37: Lag vs average stock (hist.) | G37: Warning signals
A38: 1 | B38: ANANDRATHI | C38: Anand Rathi Wealth Ltd. | D38: Avoid (likely underperformer) | E38: top 1% | F38: -0.0037663542 | G38: AI model flag
A39: 2 | B39: TENNIND | C39: Tenneco Clean Air India Ltd. | D39: Avoid (likely underperformer) | E39: top 1% | F39: -0.0037663542 | G39: AI model flag
A40: 3 | B40: NATCOPHARM | C40: NATCO Pharma Ltd. | D40: Avoid (likely underperformer) | E40: top 1% | F40: -0.0037663542 | G40: AI model flag
A41: 4 | B41: MRF | C41: MRF Ltd. | D41: Avoid (likely underperformer) | E41: top 1% | F41: -0.0037663542 | G41: AI model flag
A42: 5 | B42: SCHAEFFLER | C42: Schaeffler India Ltd. | D42: Avoid (likely underperformer) | E42: top 1% | F42: -0.0037663542 | G42: AI model flag
A43: 6 | B43: GILLETTE | C43: Gillette India Ltd. | D43: Avoid (likely underperformer) | E43: top 1% | F43: -0.0037663542 | G43: AI model flag
A44: 7 | B44: BAJAJHLDNG | C44: Bajaj Holdings & Investment Ltd. | D44: Avoid (likely underperformer) | E44: top 2% | F44: -0.0037663542 | G44: AI model flag
A45: 8 | B45: MSUMI | C45: Motherson Sumi Wiring India Ltd. | D45: Avoid (likely underperformer) | E45: top 2% | F45: -0.0037663542 | G45: AI model flag
A46: 9 | B46: PETRONET | C46: Petronet LNG Ltd. | D46: Avoid (likely underperformer) | E46: top 2% | F46: -0.0037663542 | G46: AI model flag
A47: 10 | B47: OIL | C47: Oil India Ltd. | D47: Avoid (likely underperformer) | E47: top 2% | F47: -0.0037663542 | G47: AI model flag
A50: Mid term (up to 3 months) - all 1 buy calls
A51: # | B51: Symbol | C51: Company | D51: Call | E51: Buy confidence | F51: Average stock | G51: Chance of profit | H51: Expected return / trade | I51: Entry up to Rs | J51: Target Rs | K51: Stop Rs | L51: Max days | M51: Why | N51: Results check | O51: Results & news | P51: Source
A52: 1 | B52: KOTAKBANK | C52: Kotak Mahindra Bank Ltd. | D52: Buy | E52: 0.31279249 | F52: 0.27432046 | G52: 0.50460817 | H52: 0.054241333 | I52: 444.81 | J52: 487.73 | K52: 401.88 | L52: 60 | M52: Holy Grail: ADX > 30 and pullback to 20 EMA (23-Oct); Three lower closes in an uptrend (21-Oct) | N52: Supportive | O52: Q1 FY27 (Apr-Jun 2026) - revenue: NII +9%; profit: Standalone +26% to Rs 4,123 Cr; consolidated +23% to Rs 5,480 Cr. Steady earnings growth. | P52: https://www.business-standard.com/companies/quarterly-results/kotak-mahindra-bank-q1fy27-results-net-profit-rises-23-to-5-480-crore-126071800554_1.html
A54: Mid term (up to 3 months) - strongest avoid / reduce flags
A55: # | B55: Symbol | C55: Company | D55: Call | E55: Short-side rank | F55: Lag vs average stock (hist.) | G55: Warning signals
A56: 1 | B56: WIPRO | C56: Wipro Ltd. | D56: Avoid (likely underperformer) | E56: top 1% | F56: -0.011073316 | G56: AI model flag
A57: 2 | B57: TCS | C57: Tata Consultancy Services Ltd. | D57: Avoid (likely underperformer) | E57: top 1% | F57: -0.011073316 | G57: AI model flag
A58: 3 | B58: HCLTECH | C58: HCL Technologies Ltd. | D58: Avoid (likely underperformer) | E58: top 1% | F58: -0.011073316 | G58: AI model flag
A59: 4 | B59: ANANDRATHI | C59: Anand Rathi Wealth Ltd. | D59: Avoid (likely underperformer) | E59: top 1% | F59: -0.011073316 | G59: Volatility stop flips long (21-Oct)
A60: 5 | B60: INFY | C60: Infosys Ltd. | D60: Avoid (likely underperformer) | E60: top 1% | F60: -0.011073316 | G60: AI model flag
A61: 6 | B61: TATAELXSI | C61: Tata Elxsi Ltd. | D61: Avoid (likely underperformer) | E61: top 1% | F61: -0.011073316 | G61: AI model flag
A62: 7 | B62: COFORGE | C62: Coforge Ltd. | D62: Avoid (likely underperformer) | E62: top 1% | F62: -0.011073316 | G62: AI model flag
A63: 8 | B63: INDUSTOWER | C63: Indus Towers Ltd. | D63: Avoid (likely underperformer) | E63: top 2% | F63: -0.011073316 | G63: AI model flag
A64: 9 | B64: NAUKRI | C64: Info Edge (India) Ltd. | D64: Avoid (likely underperformer) | E64: top 2% | F64: -0.011073316 | G64: Wyckoff spring (23-Oct)
A65: 10 | B65: MPHASIS | C65: MphasiS Ltd. | D65: Avoid (likely underperformer) | E65: top 2% | F65: -0.011073316 | G65: AI model flag
A68: Long term (up to 1 year) - all 2 buy calls
A69: # | B69: Symbol | C69: Company | D69: Call | E69: Buy confidence | F69: Average stock | G69: Chance of profit | H69: Expected return / trade | I69: Entry up to Rs | J69: Target Rs | K69: Stop Rs | L69: Max days | M69: Why | N69: Results check | O69: Results & news | P69: Source
A70: 1 | B70: TDPOWERSYS | C70: TD Power Systems Ltd. | D70: Accumulate (buy on dips) | E70: 0.42260949 | F70: 0.37535348 | G70: 0.55360279 | H70: 0.17754366 | I70: 723.04 | J70: 1057.01 | K70: 430.82 | L70: 250 | M70: Holy Grail: ADX > 30 and pullback to 20 EMA (14-Oct); Three lower closes in an uptrend (23-Oct) | N70: Not checked | O70: Not researched
A71: 2 | B71: KOTAKBANK | C71: Kotak Mahindra Bank Ltd. | D71: Accumulate (buy on dips) | E71: 0.39511908 | F71: 0.37535348 | G71: 0.5305555 | H71: 0.15576886 | I71: 449.58 | J71: 525.89 | K71: 382.81 | L71: 250 | M71: Holy Grail: ADX > 30 and pullback to 20 EMA (23-Oct); Three lower closes in an uptrend (21-Oct) | N71: Supportive | O71: Q1 FY27 (Apr-Jun 2026) - revenue: NII +9%; profit: Standalone +26% to Rs 4,123 Cr; consolidated +23% to Rs 5,480 Cr. Steady earnings growth. | P71: https://www.business-standard.com/companies/quarterly-results/kotak-mahindra-bank-q1fy27-results-net-profit-rises-23-to-5-480-crore-126071800554_1.html
A73: Long term (up to 1 year) - strongest avoid / reduce flags
A74: # | B74: Symbol | C74: Company | D74: Call | E74: Short-side rank | F74: Lag vs average stock (hist.) | G74: Warning signals
A75: 1 | B75: HCLTECH | C75: HCL Technologies Ltd. | D75: Reduce / Avoid | E75: top 1% | F75: -0.021375585 | G75: RSI(2) above 95 in a downtrend (13-Oct); Supertrend (10,3) turns up (13-Oct)
A76: 2 | B76: TECHM | C76: Tech Mahindra Ltd. | D76: Reduce / Avoid | E76: top 1% | F76: -0.021375585 | G76: Supertrend (10,3) turns up (15-Oct)
A77: 3 | B77: TCS | C77: Tata Consultancy Services Ltd. | D77: Reduce / Avoid | E77: top 1% | F77: -0.021375585 | G77: RSI(2) above 95 in a downtrend (15-Oct); Supertrend (10,3) turns up (13-Oct)
A78: 4 | B78: WIPRO | C78: Wipro Ltd. | D78: Reduce / Avoid | E78: top 1% | F78: -0.021375585 | G78: Elliott 5-wave decline complete (13-Oct); RSI(2) above 95 in a downtrend (15-Oct)
A79: 5 | B79: INFY | C79: Infosys Ltd. | D79: Reduce / Avoid | E79: top 1% | F79: -0.021375585 | G79: RSI(2) above 95 in a downtrend (14-Oct); Supertrend (10,3) turns up (14-Oct)
A80: 6 | B80: PERSISTENT | C80: Persistent Systems Ltd. | D80: Reduce / Avoid | E80: top 1% | F80: -0.021375585 | G80: Supertrend (10,3) turns up (09-Oct)
A81: 7 | B81: LTM | C81: LTM Ltd. (formerly LTIMindtree) | D81: Reduce / Avoid | E81: top 1% | F81: -0.021375585 | G81: RSI(2) above 95 in a downtrend (16-Oct); Supertrend (10,3) turns up (16-Oct)
A82: 8 | B82: COFORGE | C82: Coforge Ltd. | D82: Reduce / Avoid | E82: top 1% | F82: -0.021375585 | G82: Supertrend (10,3) turns up (15-Oct)
A83: 9 | B83: MPHASIS | C83: MphasiS Ltd. | D83: Reduce / Avoid | E83: top 2% | F83: -0.021375585 | G83: RSI(2) above 95 in a downtrend (09-Oct); Supertrend (10,3) turns up (13-Oct)
A84: 10 | B84: NAUKRI | C84: Info Edge (India) Ltd. | D84: Reduce / Avoid | E84: top 2% | F84: -0.021375585 | G84: AI model flag

Sheet Pattern Report Card
A1: Report card: does each pattern / signal beat the average stock? (NSE, Nifty 500 stocks, 2017-2026)
A2: Excess = result in the pattern's own direction minus the same-day result of an average eligible stock. Verdict needs |t| >= 3 (week-clustered) and the same sign in 2017-21 and 2022-26. 'Works in reverse' = the opposite trade would have worked. Pattern target = measured-move target reached before the pattern's own stop (chart patterns only). Caution: bearish results look worse than reality because stocks that collapsed left today's index; 'Survivorship illusion' marks crash-rebound effects that vanish on the full NSE universe.
A4: Source | B4: Family | C4: Pattern / signal | D4: Direction | E4: Events | F4: Stocks | G4: Events since 2024 | H4: 2-wk trade: hit % | I4: 2-wk: average stock hit % | J4: 2-wk: excess return / trade | K4: 2-wk: t-stat | L4: 2-wk verdict | M4: 3-mth trade: hit % | N4: 3-mth: average stock hit % | O4: 3-mth: excess return / trade | P4: 3-mth: t-stat | Q4: 3-mth verdict | R4: 1-yr: excess return / trade | S4: 1-yr: t-stat | T4: 1-yr verdict | U4: 20-day excess return | V4: 3-mth excess in rising mkts | W4: 3-mth excess in falling mkts | X4: Pattern target hit % | Y4: Median days to pattern target | Z4: Note
A5: Chart pattern | B5: Wyckoff | C5: Wyckoff upthrust | D5: Bearish | E5: 18507 | F5: 476 | G5: 6748 | H5: 0.13425901 | I5: 0.11996686 | J5: 0.00096097423 | K5: 1.9250103 | L5: No reliable edge | M5: 0.17792032 | N5: 0.15586861 | O5: 0.0053369366 | P5: 4.58441 | Q5: Works (significant) | R5: 0.0040867689 | S5: 2.180479 | T5: No reliable edge | U5: 0.0041138362 | V5: 0.0048167446 | W5: 0.0084912306 | X5: 0.10161299
A6: Chart pattern | B6: Event decline | C6: Event decline (>=15% in 2 days) | D6: Bullish | E6: 595 | F6: 264 | G6: 180 | H6: 0.14507772 | I6: 0.18366497 | J6: 0.012916529 | K6: 1.6436478 | L6: No reliable edge | M6: 0.17826825 | N6: 0.24385187 | O6: 0.037932407 | P6: 3.2293195 | Q6: Survivorship illusion | R6: 0.11143223 | S6: 3.4277911 | T6: Survivorship illusion | U6: 0.014541654 | V6: 0.02491084 | W6: 0.052046947 | Z6: Buying after a >=15% two-day fall looked profitable only because the stocks that kept falling later left the index. On the full NSE universe it lagged (1-yr median -14.7% vs average). Not used for any call.
A7: Chart pattern | B7: Fibonacci | C7: Fibonacci 38-62% rally failure (downtrend) | D7: Bearish | E7: 2047 | F7: 458 | G7: 908 | H7: 0.11486822 | I7: 0.11266984 | J7: 0.0035707985 | K7: 2.8447276 | L7: Weak edge | M7: 0.1548583 | N7: 0.13660787 | O7: 0.007725103 | P7: 3.0684273 | Q7: Works (significant) | R7: 0.011828247 | S7: 2.4389476 | T7: Weak edge | U7: 0.0080750837 | V7: 0.010152888 | W7: 0.0037448695 | X7: 0.34798345
A8: Chart pattern | B8: Gaps | C8: Breakaway gap down | D8: Bearish | E8: 537 | F8: 234 | G8: 249 | H8: 0.16370809 | I8: 0.14570086 | J8: 0.0066306367 | K8: 2.4286431 | L8: No reliable edge | M8: 0.16962525 | N8: 0.1725158 | O8: 0.014471817 | P8: 2.8941388 | Q8: Weak edge | R8: 0.03208929 | S8: 2.9239808 | T8: Weak edge | U8: 0.013056728 | V8: 0.026284077 | W8: 0.0022604394
A9: Chart pattern | B9: Support / resistance | C9: Horizontal support breakdown (3+ touches) | D9: Bearish | E9: 4859 | F9: 474 | G9: 2354 | H9: 0.12441811 | I9: 0.12653203 | J9: 0.001143431 | K9: 1.3970768 | L9: No reliable edge | M9: 0.15345884 | N9: 0.14976364 | O9: 0.0049674044 | P9: 2.8375817 | Q9: Weak edge | R9: 0.0042446164 | S9: 1.2468175 | T9: No reliable edge | U9: 0.0023036865 | V9: 0.0068338346 | W9: 0.0032142046
A10: Chart pattern | B10: Flag / pennant | C10: High tight flag | D10: Bullish | E10: 216 | F10: 63 | G10: 38 | H10: 0.385 | I10: 0.18557348 | J10: 0.016992448 | K10: 1.7164866 | L10: No reliable edge | M10: 0.51674641 | N10: 0.34667953 | O10: 0.04480868 | P10: 2.7878709 | Q10: No reliable edge | R10: 0.044528745 | S10: 1.4034016 | T10: No reliable edge | U10: 0.055622741 | V10: 0.032521281 | W10: 0.03420818 | X10: 0.75348837
A11: Chart pattern | B11: Gaps | C11: Runaway gap up | D11: Bullish | E11: 395 | F11: 194 | G11: 161 | H11: 0.23876404 | I11: 0.19074505 | J11: -0.0036705484 | K11: -0.67071939 | L11: No reliable edge | M11: 0.40616967 | N11: 0.32290646 | O11: 0.028779181 | P11: 2.7468396 | Q11: Weak edge | R11: 0.029596151 | S11: 1.4954357 | T11: No reliable edge | U11: 0.023821506 | V11: 0.01295445 | W11: 0.064111104
A12: Chart pattern | B12: False breakout | C12: 2B top / Turtle soup | D12: Bearish | E12: 20459 | F12: 489 | G12: 8216 | H12: 0.12469013 | I12: 0.11473019 | J12: 0.001828502 | K12: 4.5581409 | L12: Works (significant) | M12: 0.1513993 | N12: 0.14175028 | O12: 0.0019203734 | P12: 2.3789746 | Q12: Weak edge | R12: -0.0018351721 | S12: -1.2277849 | T12: No reliable edge | U12: 0.0013743879 | V12: 0.0009359212 | W12: 0.003525966
A13: Chart pattern | B13: New highs / lows | C13: 52-week high breakout | D13: Bullish | E13: 4404 | F13: 458 | G13: 1581 | H13: 0.20893439 | I13: 0.18275213 | J13: -0.00098805374 | K13: -0.94092384 | L13: No reliable edge | M13: 0.3430982 | N13: 0.31590826 | O13: 0.0046800648 | P13: 2.187683 | Q13: Weak edge | R13: 0.0040821133 | S13: 1.050153 | T13: No reliable edge | U13: 0.0038175033 | V13: 0.005773097 | W13: -0.020225217
A14: Chart pattern | B14: Island reversal | C14: Island top | D14: Bearish | E14: 329 | F14: 162 | G14: 132 | H14: 0.14473684 | I14: 0.10355208 | J14: 0.0051741731 | K14: 1.3273152 | L14: No reliable edge | M14: 0.12460064 | N14: 0.11005595 | O14: 0.017467646 | P14: 1.8208746 | Q14: No reliable edge | R14: -0.001972847 | S14: -0.1146215 | T14: No reliable edge | U14: 0.018546134 | V14: 0.02809713 | W14: 0.00879463
A15: Chart pattern | B15: Double bottom/top | C15: Double top | D15: Bearish | E15: 2635 | F15: 459 | G15: 1173 | H15: 0.12076354 | I15: 0.12407729 | J15: 0.0026380586 | K15: 2.4460464 | L15: Weak edge | M15: 0.15823293 | N15: 0.15325056 | O15: 0.0039143726 | P15: 1.7406485 | Q15: No reliable edge | R15: 0.01203294 | S15: 2.5909345 | T15: Weak edge | U15: 0.003832209 | V15: 0.0047841716 | W15: 0.0053866863 | X15: 0.49645948
A16: Chart pattern | B16: Darvas box | C16: Darvas box breakout | D16: Bullish | E16: 3795 | F16: 443 | G16: 1373 | H16: 0.20457604 | I16: 0.18660463 | J16: -0.0018836726 | K16: -1.5615466 | L16: No reliable edge | M16: 0.34282615 | N16: 0.32318924 | O16: 0.0037910854 | P16: 1.4245675 | Q16: No reliable edge | R16: 0.0099027829 | S16: 2.2459136 | T16: Weak edge | U16: 0.0045466592 | V16: 0.005651938 | W16: -0.020214846 | X16: 0.65415767
A17: Chart pattern | B17: New highs / lows | C17: Multi-year high breakout (since 2016) | D17: Bullish | E17: 2659 | F17: 402 | G17: 1132 | H17: 0.20454545 | I17: 0.1797891 | J17: -0.0013305878 | K17: -0.99398654 | L17: No reliable edge | M17: 0.34339915 | N17: 0.31464354 | O17: 0.0039443848 | P17: 1.4238066 | Q17: No reliable edge | R17: 0.0053126842 | S17: 1.0407357 | T17: No reliable edge | U17: 0.0026364983 | V17: 0.005093556 | W17: -0.030671456
A18: Chart pattern | B18: Divergence | C18: Hidden bullish divergence (MFI) | D18: Bullish | E18: 14669 | F18: 483 | G18: 5866 | H18: 0.18705882 | I18: 0.17527447 | J18: -0.00072485892 | K18: -1.3065012 | L18: No reliable edge | M18: 0.30593316 | N18: 0.29899427 | O18: 0.001701139 | P18: 1.3923362 | Q18: No reliable edge | R18: 0.0065297168 | S18: 2.9000873 | T18: Weak edge | U18: 0.0022651347 | V18: 0.0024374616 | W18: -0.0036942804
A19: Chart pattern | B19: Diamond | C19: Diamond - down breakout | D19: Bearish | E19: 2589 | F19: 457 | G19: 1191 | H19: 0.10906238 | I19: 0.12812561 | J19: -0.00076465713 | K19: -0.7658132 | L19: No reliable edge | M19: 0.16020985 | N19: 0.15261754 | O19: 0.0026542815 | P19: 1.2128254 | Q19: No reliable edge | R19: 0.0049296765 | S19: 1.1209344 | T19: No reliable edge | U19: 0.0016822826 | V19: 0.0025728413 | W19: -0.0006318154 | X19: 0.19117647
A20: Chart pattern | B20: Divergence | C20: Hidden bearish divergence (RSI) | D20: Bearish | E20: 7576 | F20: 480 | G20: 3440 | H20: 0.11967764 | I20: 0.11744429 | J20: 0.0011130445 | K20: 1.7443512 | L20: No reliable edge | M20: 0.15404736 | N20: 0.14792852 | O20: 0.00163309 | P20: 1.1816494 | Q20: No reliable edge | R20: 0.006087998 | S20: 2.2724646 | T20: Weak edge | U20: 0.0016331406 | V20: 0.005240547 | W20: -0.004900794
A21: Chart pattern | B21: Symmetrical triangle | C21: Symmetrical triangle - down breakout | D21: Bearish | E21: 2284 | F21: 456 | G21: 1034 | H21: 0.12322064 | I21: 0.13008849 | J21: 0.0020390984 | K21: 1.7790581 | L21: No reliable edge | M21: 0.14391144 | N21: 0.14647582 | O21: 0.0027122712 | P21: 1.0446116 | Q21: No reliable edge | R21: 0.0028686497 | S21: 0.61302401 | T21: No reliable edge | U21: 0.0024820852 | V21: 0.0041893956 | W21: -0.001979363 | X21: 0.1427285
A22: Chart pattern | B22: Point & figure | C22: P&F triple-bottom sell | D22: Bearish | E22: 1975 | F22: 452 | G22: 871 | H22: 0.11099585 | I22: 0.11429688 | J22: 0.0016845804 | K22: 1.1441048 | L22: No reliable edge | M22: 0.12718601 | N22: 0.12900297 | O22: 0.002813667 | P22: 1.0370528 | Q22: No reliable edge | R22: 0.0019272225 | S22: 0.34195998 | T22: No reliable edge | U22: 0.001875167 | V22: 0.00457745 | W22: -0.0037816554
A23: Chart pattern | B23: Flag / pennant | C23: Bull pennant | D23: Bullish | E23: 387 | F23: 245 | G23: 102 | H23: 0.21899736 | I23: 0.19274769 | J23: -0.003520385 | K23: -1.0529035 | L23: No reliable edge | M23: 0.38933333 | N23: 0.33979 | O23: 0.0076150016 | P23: 1.0333656 | Q23: No reliable edge | R23: 0.029142611 | S23: 2.5687142 | T23: Weak edge | U23: 0.0055924949 | V23: 0.015326333 | W23: -0.012191393 | X23: 0.43523316
A24: Chart pattern | B24: Broadening formation | C24: Broadening formation - down breakout | D24: Bearish | E24: 61 | F24: 55 | G24: 30 | H24: 0.1 | I24: 0.10794127 | J24: -0.0027161369 | K24: -0.34294905 | L24: No reliable edge | M24: 0.15517241 | N24: 0.15655458 | O24: 0.013490927 | P24: 0.99637152 | Q24: Too few events | R24: 0.008640587 | S24: 0.27134484 | T24: Too few events | U24: -0.0015998676 | V24: 0.00049768187 | W24: 0.0070631063 | X24: 0.50847458
A25: Chart pattern | B25: Divergence | C25: Hidden bullish divergence (RSI) | D25: Bullish | E25: 11278 | F25: 485 | G25: 4321 | H25: 0.18405405 | I25: 0.17557432 | J25: -0.0012253349 | K25: -2.0121026 | L25: Weak - tends to fail | M25: 0.31063046 | N25: 0.3018045 | O25: 0.0013591821 | P25: 0.97501698 | Q25: No reliable edge | R25: 0.008303064 | S25: 3.0802513 | T25: Works (significant) | U25: -2.0054382e-05 | V25: 0.001088137 | W25: -0.0012349786
A26: Chart pattern | B26: Gaps | C26: Breakaway gap up | D26: Bullish | E26: 1110 | F26: 378 | G26: 471 | H26: 0.20431115 | I26: 0.18085768 | J26: 0.0017553172 | K26: 1.0267172 | L26: No reliable edge | M26: 0.32925682 | N26: 0.31668764 | O26: 0.0043089104 | P26: 0.96033942 | Q26: No reliable edge | R26: -0.011470227 | S26: -1.3304861 | T26: No reliable edge | U26: 0.0029726443 | V26: 0.0038914406 | W26: 0.009755922
A27: Chart pattern | B27: Descending triangle | C27: Descending triangle - down breakout | D27: Bearish | E27: 2390 | F27: 455 | G27: 1165 | H27: 0.12300388 | I27: 0.12743158 | J27: 0.00016350657 | K27: 0.13327157 | L27: No reliable edge | M27: 0.15248227 | N27: 0.14810369 | O27: 0.0022467939 | P27: 0.93797485 | Q27: No reliable edge | R27: 0.0036815001 | S27: 0.81994199 | T27: No reliable edge | U27: 0.00058225059 | V27: 0.0048369938 | W27: -0.0041845194 | X27: 0.21733506
A28: Chart pattern | B28: Point & figure | C28: P&F double-top buy | D28: Bullish | E28: 9274 | F28: 483 | G28: 3740 | H28: 0.19226979 | I28: 0.17275045 | J28: -0.00017598642 | K28: -0.25054193 | L28: No reliable edge | M28: 0.29153744 | N28: 0.29004684 | O28: 0.0015450797 | P28: 0.93669659 | Q28: No reliable edge | R28: 0.0038274937 | S28: 1.1623905 | T28: No reliable edge | U28: 0.0023463006 | V28: 0.00013959191 | W28: 0.0003374309
A29: Chart pattern | B29: Trendline break | C29: Uptrend-line breakdown | D29: Bearish | E29: 17761 | F29: 492 | G29: 7586 | H29: 0.11489826 | I29: 0.12045657 | J29: 0.00019578714 | K29: 0.49322335 | L29: No reliable edge | M29: 0.1413461 | N29: 0.14385027 | O29: 0.00080994904 | P29: 0.92911761 | Q29: No reliable edge | R29: 0.0018658189 | S29: 1.1656109 | T29: No reliable edge | U29: 0.0012063128 | V29: -0.00027619632 | W29: 0.0008409544 | X29: 0.49017076
A30: Chart pattern | B30: Right-angled broadening (ascending) | C30: Right-angled broadening (ascending) - down breakout | D30: Bearish | E30: 432 | F30: 279 | G30: 209 | H30: 0.10688836 | I30: 0.11812203 | J30: -0.0019571195 | K30: -0.71820822 | L30: No reliable edge | M30: 0.14039409 | N30: 0.13920447 | O30: 0.0052944657 | P30: 0.83171265 | Q30: No reliable edge | R30: 0.0015666359 | S30: 0.12870659 | T30: No reliable edge | U30: 0.0012281455 | V30: -0.00013844852 | W30: 0.010385408 | X30: 0.44736842
A31: Chart pattern | B31: Divergence | C31: Hidden bullish divergence (MACD hist) | D31: Bullish | E31: 14652 | F31: 486 | G31: 5723 | H31: 0.18388974 | I31: 0.17530754 | J31: -0.0013918493 | K31: -2.4631413 | L31: Weak - tends to fail | M31: 0.30471618 | N31: 0.2976354 | O31: 0.00093040494 | P31: 0.79512633 | Q31: No reliable edge | R31: 0.0046752606 | S31: 2.0040274 | T31: Weak edge | U31: -0.00045185195 | V31: 0.0006171332 | W31: -0.0007733383
A32: Chart pattern | B32: Right-angled broadening (ascending) | C32: Right-angled broadening (ascending) - up breakout | D32: Bullish | E32: 477 | F32: 298 | G32: 204 | H32: 0.22294372 | I32: 0.18672071 | J32: -0.00018706631 | K32: -0.068599319 | L32: No reliable edge | M32: 0.32826087 | N32: 0.31176573 | O32: 0.0049286453 | P32: 0.76634408 | Q32: No reliable edge | R32: 0.013975202 | S32: 1.2921092 | T32: No reliable edge | U32: 0.0023890754 | V32: 0.0048729455 | W32: 0.014227741 | X32: 0.64946237
A33: Chart pattern | B33: VCP | C33: VCP breakout | D33: Bullish | E33: 1658 | F33: 418 | G33: 584 | H33: 0.22262997 | I33: 0.18256199 | J33: 0.00080456571 | K33: 0.45508355 | L33: No reliable edge | M33: 0.32924586 | N33: 0.31833876 | O33: 0.0029308743 | P33: 0.75831294 | Q33: No reliable edge | R33: 0.018155575 | S33: 2.412318 | T33: Weak edge | U33: 0.00767463 | V33: 0.0012694281 | W33: -0.019853436 | X33: 0.49817073
A34: Chart pattern | B34: Divergence | C34: Hidden bearish divergence (MACD hist) | D34: Bearish | E34: 11053 | F34: 481 | G34: 5099 | H34: 0.11523924 | I34: 0.11894153 | J34: 0.00065167968 | K34: 1.3484651 | L34: No reliable edge | M34: 0.14548023 | N34: 0.14838709 | O34: 0.00079074775 | P34: 0.7378707 | Q34: No reliable edge | R34: 0.0051406131 | S34: 2.4688859 | T34: Weak edge | U34: 0.0011415957 | V34: 0.0033452561 | W34: -0.0018975429
A35: Chart pattern | B35: Rising wedge | C35: Rising wedge - up breakout | D35: Bullish | E35: 1227 | F35: 386 | G35: 409 | H35: 0.22864322 | I35: 0.190017 | J35: -0.0014837462 | K35: -0.82520298 | L35: No reliable edge | M35: 0.33502538 | N35: 0.31589273 | O35: 0.0030203528 | P35: 0.73513075 | Q35: No reliable edge | R35: 0.0038831041 | S35: 0.54305139 | T35: No reliable edge | U35: 0.0051059815 | V35: 0.0019048546 | W35: 0.006333823 | X35: 0.46794338
A36: Chart pattern | B36: New highs / lows | C36: 52-week low breakdown | D36: Bearish | E36: 1615 | F36: 401 | G36: 683 | H36: 0.16018158 | I36: 0.14240855 | J36: 0.0046179088 | K36: 2.6078908 | L36: Weak edge | M36: 0.14983713 | N36: 0.14787835 | O36: 0.0021903484 | P36: 0.7312089 | Q36: No reliable edge | R36: 0.0086411884 | S36: 1.208536 | T36: No reliable edge | U36: 0.0056674176 | V36: 0.010674784 | W36: -0.008293092
A37: Chart pattern | B37: Harmonic | C37: Bullish Deep crab | D37: Bullish | E37: 168 | F37: 134 | G37: 80 | H37: 0.14110429 | I37: 0.15472778 | J37: -0.00010517223 | K37: -0.024225593 | L37: No reliable edge | M37: 0.28301887 | N37: 0.28078884 | O37: 0.0079433336 | P37: 0.66822961 | Q37: No reliable edge | R37: 0.026310391 | S37: 0.87115238 | T37: No reliable edge | U37: 0.0028473423 | V37: -0.012999272 | W37: 0.023911371 | X37: 0.4382716
A38: Chart pattern | B38: Broadening formation | C38: Broadening formation - up breakout | D38: Bullish | E38: 89 | F38: 86 | G38: 44 | H38: 0.1954023 | I38: 0.18662056 | J38: 0.00080306563 | K38: 0.11784469 | L38: No reliable edge | M38: 0.35632184 | N38: 0.30010166 | O38: 0.009990672 | P38: 0.65756159 | Q38: No reliable edge | R38: 0.011105589 | S38: 0.39164736 | T38: No reliable edge | U38: 0.01442692 | V38: 0.0058648586 | W38: -0.09158816 | X38: 0.70930233
A39: Chart pattern | B39: Harmonic | C39: Bearish Gartley | D39: Bearish | E39: 689 | F39: 329 | G39: 266 | H39: 0.1202346 | I39: 0.12146957 | J39: 1.4679023e-05 | K39: 0.0076799943 | L39: No reliable edge | M39: 0.15082956 | N39: 0.15252355 | O39: 0.002493995 | P39: 0.57647257 | Q39: No reliable edge | R39: 0.007714265 | S39: 0.92534978 | T39: No reliable edge | U39: 0.00088607636 | V39: -0.0015480143 | W39: 0.005233127 | X39: 0.64251969
A40: Chart pattern | B40: Harmonic | C40: Bullish Crab | D40: Bullish | E40: 32 | F40: 31 | G40: 17 | H40: 0.12903226 | I40: 0.13586768 | J40: 0.0015112397 | K40: 0.15827715 | L40: Too few events | M40: 0.19354839 | N40: 0.24616106 | O40: 0.012626929 | P40: 0.50369761 | Q40: Too few events | R40: -0.0022044219 | S40: -0.03945634 | T40: Too few events | U40: -0.002401351 | V40: -0.013979647 | W40: -0.0041689783 | X40: 0.46875
A41: Chart pattern | B41: Divergence | C41: Hidden bearish divergence (OBV) | D41: Bearish | E41: 11667 | F41: 485 | G41: 5303 | H41: 0.11275238 | I41: 0.11836722 | J41: 0.0014496048 | K41: 2.8189767 | L41: Weak edge | M41: 0.13775144 | N41: 0.14343347 | O41: 0.0005616569 | P41: 0.49588338 | Q41: No reliable edge | R41: -0.0016400853 | S41: -0.7954169 | T41: No reliable edge | U41: 0.0010841004 | V41: 0.0027307343 | W41: -0.002228521
A42: Chart pattern | B42: Rising wedge | C42: Rising wedge - down breakout | D42: Bearish | E42: 5389 | F42: 479 | G42: 2076 | H42: 0.11484066 | I42: 0.11672793 | J42: -0.00027486799 | K42: -0.37048151 | L42: No reliable edge | M42: 0.13941748 | N42: 0.14134826 | O42: 0.00075499226 | P42: 0.47513157 | Q42: No reliable edge | R42: -0.0025682803 | S42: -0.93974577 | T42: No reliable edge | U42: 0.00013879378 | V42: -0.00037253086 | W42: 1.8484661e-05 | X42: 0.27343159
A43: Chart pattern | B43: Point & figure | C43: P&F bullish ascending breakout | D43: Bullish | E43: 8148 | F43: 479 | G43: 2886 | H43: 0.19722708 | I43: 0.17892317 | J43: -0.0031012397 | K43: -3.6108731 | L43: Works in reverse (fade it) | M43: 0.31387415 | N43: 0.30378574 | O43: 0.00080411497 | P43: 0.43776668 | Q43: No reliable edge | R43: 0.011949107 | S43: 3.5170019 | T43: Works (significant) | U43: 0.0027116144 | V43: 0.0026310566 | W43: -0.012578386
A44: Chart pattern | B44: Cup (no handle) | C44: Inverted cup breakdown | D44: Bearish | E44: 249 | F44: 144 | G44: 111 | H44: 0.14285714 | I44: 0.15394057 | J44: -0.0043125319 | K44: -0.89612684 | L44: No reliable edge | M44: 0.15254237 | N44: 0.16012533 | O44: 0.0037511192 | P44: 0.42806651 | Q44: No reliable edge | R44: 0.020008285 | S44: 0.9811482 | T44: No reliable edge | U44: 0.012582726 | V44: -0.007405232 | W44: 0.010170712 | X44: 0.41004184
A45: Chart pattern | B45: Three drives | C45: Three drives top | D45: Bearish | E45: 678 | F45: 329 | G45: 268 | H45: 0.095310136 | I45: 0.11555696 | J45: 5.7858707e-05 | K45: 0.027929934 | L45: No reliable edge | M45: 0.12735849 | N45: 0.13558748 | O45: 0.0014722841 | P45: 0.33212227 | Q45: No reliable edge | R45: -0.0052778657 | S45: -0.6739863 | T45: No reliable edge | U45: 0.0028237625 | V45: -0.0030620858 | W45: 0.02575533 | X45: 0.70704846
A46: Chart pattern | B46: Harmonic | C46: Bullish Butterfly | D46: Bullish | E46: 582 | F46: 320 | G46: 282 | H46: 0.16168717 | I46: 0.16410728 | J46: 0.0023891705 | K46: 0.98264903 | L46: No reliable edge | M46: 0.26978417 | N46: 0.2762543 | O46: 0.0018408409 | P46: 0.29921419 | Q46: No reliable edge | R46: 0.0073158824 | S46: 0.56874604 | T46: No reliable edge | U46: -0.0021315283 | V46: 0.0018516183 | W46: -0.012394153 | X46: 0.54107143
A47: Chart pattern | B47: Quasimodo | C47: Bearish Quasimodo | D47: Bearish | E47: 6848 | F47: 481 | G47: 2893 | H47: 0.10778175 | I47: 0.11655704 | J47: -6.390339e-05 | K47: -0.098293001 | L47: No reliable edge | M47: 0.1323217 | N47: 0.13858487 | O47: 0.00037975801 | P47: 0.28444717 | Q47: No reliable edge | R47: 0.00012504346 | S47: 0.050014846 | T47: No reliable edge | U47: 0.00017246518 | V47: 0.0013479677 | W47: -0.0007627391 | X47: 0.56862442
A48: Chart pattern | B48: Harmonic | C48: Bearish Cypher | D48: Bearish | E48: 696 | F48: 338 | G48: 288 | H48: 0.098981077 | I48: 0.11337224 | J48: -0.0012184936 | K48: -0.58182446 | L48: No reliable edge | M48: 0.13004484 | N48: 0.13343029 | O48: 0.0010079821 | P48: 0.2590153 | Q48: No reliable edge | R48: 0.002679314 | S48: 0.36774665 | T48: No reliable edge | U48: -0.0013401873 | V48: 0.0005751942 | W48: 0.012518313 | X48: 0.61335404
A49: Chart pattern | B49: Diamond | C49: Diamond - up breakout | D49: Bullish | E49: 2739 | F49: 458 | G49: 1144 | H49: 0.1823573 | I49: 0.16915865 | J49: 0.0002465037 | K49: 0.22972755 | L49: No reliable edge | M49: 0.28571429 | N49: 0.28532028 | O49: 0.00051902788 | P49: 0.21395557 | Q49: No reliable edge | R49: -0.0025037293 | S49: -0.55873329 | T49: No reliable edge | U49: -0.0001207774 | V49: 0.003755852 | W49: -0.008226987 | X49: 0.28565574
A50: Chart pattern | B50: Volume patterns | C50: Selling climax (reversal) | D50: Bullish | E50: 105 | F50: 82 | G50: 28 | H50: 0.12745098 | I50: 0.13302311 | J50: 0.0029894574 | K50: 0.36697588 | L50: No reliable edge | M50: 0.1047619 | N50: 0.19358458 | O50: 0.0031918132 | P50: 0.16866747 | Q50: No reliable edge | R50: -0.042593085 | S50: -1.0470902 | T50: No reliable edge | U50: 0.0029727159 | V50: 0.015234302 | W50: 0.023401346
A51: Chart pattern | B51: Reversal bars | C51: Key reversal day (bearish) | D51: Bearish | E51: 6154 | F51: 474 | G51: 2323 | H51: 0.13311313 | I51: 0.1216995 | J51: 0.00040902745 | K51: 0.54507091 | L51: No reliable edge | M51: 0.15435112 | N51: 0.14417183 | O51: 0.0001734622 | P51: 0.11913934 | Q51: No reliable edge | R51: -0.0029693409 | S51: -1.1587022 | T51: No reliable edge | U51: -0.00014254008 | V51: -0.00019003026 | W51: -0.00077252135
A52: Chart pattern | B52: Pipes & horns | C52: Horn top (weekly) | D52: Bearish | E52: 171 | F52: 135 | G52: 57 | H52: 0.095808383 | I52: 0.11300786 | J52: -0.0013770447 | K52: -0.29327425 | L52: No reliable edge | M52: 0.090361446 | N52: 0.13835306 | O52: 0.00029543204 | P52: 0.031589639 | Q52: No reliable edge | R52: -0.027820539 | S52: -1.8985466 | T52: No reliable edge | U52: -0.0094907823 | V52: -0.005418863 | W52: 0.029147186
A53: Chart pattern | B53: Right-angled broadening (descending) | C53: Right-angled broadening (descending) - down breakout | D53: Bearish | E53: 276 | F53: 204 | G53: 126 | H53: 0.094339623 | I53: 0.12435088 | J53: -0.0043390117 | K53: -1.3766009 | L53: No reliable edge | M53: 0.12403101 | N53: 0.14172141 | O53: 4.9228594e-05 | P53: 0.006682956 | Q53: No reliable edge | R53: -0.0056724084 | S53: -0.35121886 | T53: No reliable edge | U53: -0.002192038 | V53: 0.0039686775 | W53: -0.020318017 | X53: 0.47348485
A54: Chart pattern | B54: Wolfe wave | C54: Bearish Wolfe wave | D54: Bearish | E54: 3678 | F54: 464 | G54: 1433 | H54: 0.11499312 | I54: 0.11680271 | J54: -0.00010677461 | K54: -0.11011533 | L54: No reliable edge | M54: 0.13597734 | N54: 0.14040332 | O54: 5.0724748e-06 | P54: 0.0026203171 | Q54: No reliable edge | R54: -0.0079802751 | S54: -2.3068047 | T54: Weak - tends to fail | U54: 0.00028761937 | V54: 9.428932e-05 | W54: 0.0018119349 | X54: 0.25332594
A55: Chart pattern | B55: Cup (no handle) | C55: Cup (no handle) breakout | D55: Bullish | E55: 564 | F55: 287 | G55: 212 | H55: 0.21415608 | I55: 0.18717875 | J55: -0.0055254745 | K55: -1.7839437 | L55: No reliable edge | M55: 0.33522727 | N55: 0.31991869 | O55: -8.3108237e-05 | P55: -0.012396136 | Q55: No reliable edge | R55: 0.01032792 | S55: 0.76243183 | T55: No reliable edge | U55: 0.00077433329 | V55: 0.007402225 | W55: 0.023000731 | X55: 0.5965251
A56: Chart pattern | B56: Island reversal | C56: Island bottom | D56: Bullish | E56: 548 | F56: 236 | G56: 287 | H56: 0.22328244 | I56: 0.1893944 | J56: 0.0066176797 | K56: 1.2386494 | L56: No reliable edge | M56: 0.29755179 | N56: 0.30576954 | O56: -0.00048027527 | P56: -0.054996864 | Q56: No reliable edge | R56: 0.0006576177 | S56: 0.038270382 | T56: No reliable edge | U56: 0.014220611 | V56: -0.011826092 | W56: 0.007671829
A57: Chart pattern | B57: Head & shoulders | C57: Head & shoulders top | D57: Bearish | E57: 2023 | F57: 445 | G57: 855 | H57: 0.11251901 | I57: 0.12932137 | J57: -0.00037754683 | K57: -0.36884473 | L57: No reliable edge | M57: 0.14285714 | N57: 0.15081965 | O57: -0.00012914795 | P57: -0.058015725 | Q57: No reliable edge | R57: 0.00024252804 | S57: 0.053389356 | T57: No reliable edge | U57: 0.003055763 | V57: -0.0004160299 | W57: -0.0004372714 | X57: 0.31288344
A58: Chart pattern | B58: Descending broadening wedge | C58: Descending broadening wedge - down breakout | D58: Bearish | E58: 272 | F58: 195 | G58: 120 | H58: 0.13513514 | I58: 0.14109739 | J58: -0.000586365 | K58: -0.15560229 | L58: No reliable edge | M58: 0.12643678 | N58: 0.15638469 | O58: -0.00045202854 | P58: -0.059364455 | Q58: No reliable edge | R58: 0.008905394 | S58: 0.55836522 | T58: No reliable edge | U58: 0.0050677862 | V58: -0.0037741265 | W58: -0.012453705 | X58: 0.54580153
A59: Chart pattern | B59: Rectangle | C59: Rectangle - up breakout | D59: Bullish | E59: 684 | F59: 313 | G59: 295 | H59: 0.17883756 | I59: 0.1780077 | J59: -0.0050018943 | K59: -2.2763737 | L59: Weak - tends to fail | M59: 0.30521472 | N59: 0.29458237 | O59: -0.00038230431 | P59: -0.071767016 | Q59: No reliable edge | R59: -0.0077275067 | S59: -0.77358621 | T59: No reliable edge | U59: -0.0008342037 | V59: -0.0009282815 | W59: -0.006466333 | X59: 0.61480363
A60: Chart pattern | B60: Gaps | C60: Exhaustion gap (up, filled) | D60: Bearish | E60: 307 | F60: 129 | G60: 77 | H60: 0.098540146 | I60: 0.08713847 | J60: -0.0082322849 | K60: -1.6208077 | L60: No reliable edge | M60: 0.11803279 | N60: 0.10111869 | O60: -0.0010717965 | P60: -0.091800501 | Q60: No reliable edge | R60: -0.046163465 | S60: -2.581761 | T60: Weak - tends to fail | U60: 0.0073963386 | V60: 0.00051910896 | W60: -0.043333063
A61: Chart pattern | B61: Gaps | C61: Runaway gap down | D61: Bearish | E61: 270 | F61: 182 | G61: 68 | H61: 0.14068441 | I61: 0.14223738 | J61: -0.0059080517 | K61: -0.90222783 | L61: No reliable edge | M61: 0.12030075 | N61: 0.12779135 | O61: -0.0012010737 | P61: -0.1042656 | Q61: No reliable edge | R61: -0.029983009 | S61: -1.6821708 | T61: No reliable edge | U61: 0.010038096 | V61: -0.04038161 | W61: 0.010475059
A62: Chart pattern | B62: Ascending broadening wedge | C62: Ascending broadening wedge - up breakout | D62: Bullish | E62: 747 | F62: 345 | G62: 272 | H62: 0.23651452 | I62: 0.18931568 | J62: -0.00085152306 | K62: -0.36614184 | L62: No reliable edge | M62: 0.34583333 | N62: 0.32018707 | O62: -0.00080498219 | P62: -0.1450687 | Q62: No reliable edge | R62: 0.0081949454 | S62: 0.89762203 | T62: No reliable edge | U62: 0.0036363244 | V62: 0.00053578738 | W62: -0.0041243705 | X62: 0.67125172
A63: Chart pattern | B63: Falling wedge | C63: Falling wedge - up breakout | D63: Bullish | E63: 4382 | F63: 466 | G63: 2099 | H63: 0.1766488 | I63: 0.16682955 | J63: 0.0010282588 | K63: 1.0704475 | L63: No reliable edge | M63: 0.27958015 | N63: 0.27802711 | O63: -0.00032404525 | P63: -0.15574398 | Q63: No reliable edge | R63: -0.010222645 | S63: -2.3149142 | T63: Weak - tends to fail | U63: 7.2344224e-06 | V63: 0.0025924093 | W63: -0.0024365322 | X63: 0.38238051
A64: Chart pattern | B64: Three drives | C64: Three drives bottom | D64: Bullish | E64: 603 | F64: 304 | G64: 252 | H64: 0.17369309 | I64: 0.17051966 | J64: -0.0023383353 | K64: -1.0105042 | L64: No reliable edge | M64: 0.27739726 | N64: 0.28461617 | O64: -0.00086340336 | P64: -0.16063297 | Q64: No reliable edge | R64: 0.00035951857 | S64: 0.034705687 | T64: No reliable edge | U64: -0.0025941085 | V64: -7.0505957e-05 | W64: -0.0038810465 | X64: 0.80748663
A65: Chart pattern | B65: Fibonacci | C65: Fibonacci 38-62% pullback bounce (uptrend) | D65: Bullish | E65: 2706 | F65: 463 | G65: 1174 | H65: 0.13235294 | I65: 0.17200321 | J65: -0.004455565 | K65: -3.463975 | L65: Works in reverse (fade it) | M65: 0.26888803 | N65: 0.28752974 | O65: -0.00063177287 | P65: -0.19915748 | Q65: No reliable edge | R65: 0.00025349211 | S65: 0.033679752 | T65: No reliable edge | U65: -0.0066070134 | V65: -0.0046143466 | W65: -0.0026846036 | X65: 0.51806303
A66: Chart pattern | B66: IBD bases | C66: Flat base breakout (25d) | D66: Bullish | E66: 1863 | F66: 386 | G66: 651 | H66: 0.20589842 | I66: 0.18666098 | J66: -0.0012378357 | K66: -0.7710028 | L66: No reliable edge | M66: 0.33485714 | N66: 0.31536583 | O66: -0.00075382969 | P66: -0.21268479 | Q66: No reliable edge | R66: -0.010913052 | S66: -2.0187735 | T66: Weak - tends to fail | U66: -4.9244713e-05 | V66: 0.0004861164 | W66: -0.028891673
A67: Chart pattern | B67: Harmonic | C67: Bullish Bat | D67: Bullish | E67: 273 | F67: 196 | G67: 115 | H67: 0.18113208 | I67: 0.16907282 | J67: -0.0015235351 | K67: -0.4064651 | L67: No reliable edge | M67: 0.28076923 | N67: 0.2810004 | O67: -0.0020212311 | P67: -0.25785645 | Q67: No reliable edge | R67: -0.017790299 | S67: -1.0965883 | T67: No reliable edge | U67: -0.0001116618 | V67: -0.0060551596 | W67: 0.0051204723 | X67: 0.65882353
A68: Chart pattern | B68: Channel up | C68: Channel up - down breakout | D68: Bearish | E68: 2076 | F68: 453 | G68: 803 | H68: 0.12128713 | I68: 0.12236614 | J68: 0.00011523806 | K68: 0.099228439 | L68: No reliable edge | M68: 0.14300203 | N68: 0.14326434 | O68: -0.00062963412 | P68: -0.26328643 | Q68: No reliable edge | R68: -0.00054310341 | S68: -0.11494895 | T68: No reliable edge | U68: 0.0009970123 | V68: -0.004904065 | W68: 0.010974449 | X68: 0.48063555
A69: Chart pattern | B69: Flag / pennant | C69: Bear pennant | D69: Bearish | E69: 188 | F69: 143 | G69: 92 | H69: 0.096256684 | I69: 0.13816597 | J69: -0.0052039831 | K69: -1.2468536 | L69: No reliable edge | M69: 0.11413043 | N69: 0.15051052 | O69: -0.0025774278 | P69: -0.26761664 | Q69: No reliable edge | R69: -0.029519142 | S69: -1.2380705 | T69: No reliable edge | U69: 0.0023133567 | V69: 0.0296166 | W69: -0.025397274 | X69: 0.14754098
A70: Chart pattern | B70: Flag / pennant | C70: Bull flag | D70: Bullish | E70: 3500 | F70: 453 | G70: 1223 | H70: 0.20005816 | I70: 0.1847266 | J70: -0.0030052831 | K70: -2.8894751 | L70: Weak - tends to fail | M70: 0.3350059 | N70: 0.31607449 | O70: -0.00071130728 | P70: -0.29994079 | Q70: No reliable edge | R70: 0.0027807933 | S70: 0.64708899 | T70: No reliable edge | U70: 0.00011669364 | V70: -0.0013349378 | W70: -0.012297003 | X70: 0.37315592
A71: Chart pattern | B71: Gaps | C71: Exhaustion gap (down, filled) | D71: Bullish | E71: 92 | F71: 73 | G71: 12 | H71: 0.13333333 | I71: 0.13022359 | J71: -0.016660689 | K71: -1.5853327 | L71: No reliable edge | M71: 0.17391304 | N71: 0.19882471 | O71: -0.0075823908 | P71: -0.32413396 | Q71: No reliable edge | R71: 0.048328959 | S71: 1.0113886 | T71: No reliable edge | U71: 0.022937365 | V71: 0.038298917 | W71: -0.00753935
A72: Chart pattern | B72: Ascending triangle | C72: Ascending triangle - down breakout | D72: Bearish | E72: 4085 | F72: 466 | G72: 1770 | H72: 0.11050137 | I72: 0.11947144 | J72: -0.00033287115 | K72: -0.39700566 | L72: No reliable edge | M72: 0.13948112 | N72: 0.14270431 | O72: -0.00062130689 | P72: -0.34169841 | Q72: No reliable edge | R72: -0.0033359759 | S72: -1.0343948 | T72: No reliable edge | U72: 8.4352541e-05 | V72: -0.0015222874 | W72: 0.0005600747 | X72: 0.2124183
A73: Chart pattern | B73: Channel down | C73: Channel down - up breakout | D73: Bullish | E73: 1701 | F73: 438 | G73: 801 | H73: 0.20227409 | I73: 0.17550322 | J73: 0.0017919946 | K73: 1.2577385 | L73: No reliable edge | M73: 0.28352725 | N73: 0.28979063 | O73: -0.0014345455 | P73: -0.41840928 | Q73: No reliable edge | R73: -0.0084980848 | S73: -1.1306243 | T73: No reliable edge | U73: 0.0020585002 | V73: -0.0017265232 | W73: 0.00046867613 | X73: 0.6163142
A74: Chart pattern | B74: Triple bottom/top | C74: Triple top | D74: Bearish | E74: 459 | F74: 261 | G74: 213 | H74: 0.093959732 | I74: 0.11159697 | J74: -3.0989199e-05 | K74: -0.013296213 | L74: No reliable edge | M74: 0.11899314 | N74: 0.14336175 | O74: -0.0022552731 | P74: -0.43953787 | Q74: No reliable edge | R74: 0.008316036 | S74: 0.85328729 | T74: No reliable edge | U74: -0.00026777689 | V74: 0.0024844582 | W74: 0.0057983595 | X74: 0.421875
A75: Chart pattern | B75: Ascending triangle | C75: Ascending triangle - up breakout | D75: Bullish | E75: 2687 | F75: 451 | G75: 1023 | H75: 0.20392749 | I75: 0.18192648 | J75: -0.001487335 | K75: -1.205834 | L75: No reliable edge | M75: 0.31995413 | N75: 0.30615234 | O75: -0.0012491843 | P75: -0.46676448 | Q75: No reliable edge | R75: -0.0058831444 | S75: -1.2050179 | T75: No reliable edge | U75: 0.0015295177 | V75: -0.0010475024 | W75: -0.0029567945 | X75: 0.375
A76: Chart pattern | B76: Harmonic | C76: Bullish AB=CD | D76: Bullish | E76: 3853 | F76: 464 | G76: 1747 | H76: 0.15877216 | I76: 0.16344673 | J76: -0.00039299369 | K76: -0.41494554 | L76: No reliable edge | M76: 0.2675142 | N76: 0.27896273 | O76: -0.0010728019 | P76: -0.48883798 | Q76: No reliable edge | R76: -0.007575578 | S76: -1.7422348 | T76: No reliable edge | U76: -0.0014489827 | V76: -0.0033069697 | W76: 0.0013472435 | X76: 0.54840515
A77: Chart pattern | B77: Dow theory reversal | C77: Dow trend reversal down | D77: Bearish | E77: 5389 | F77: 474 | G77: 2348 | H77: 0.1061209 | I77: 0.12290606 | J77: -0.00067447734 | K77: -0.91516233 | L77: No reliable edge | M77: 0.12682074 | N77: 0.14117644 | O77: -0.00083365382 | P77: -0.50978587 | Q77: No reliable edge | R77: -0.0035308984 | S77: -1.0736706 | T77: No reliable edge | U77: -0.00087792709 | V77: -0.0015643956 | W77: -0.0046905202 | X77: 0.54743272
A78: Chart pattern | B78: Divergence | C78: Bearish divergence (OBV) | D78: Bearish | E78: 5670 | F78: 472 | G78: 2360 | H78: 0.1161915 | I78: 0.11814855 | J78: 0.0014560395 | K78: 1.9380467 | L78: No reliable edge | M78: 0.13236377 | N78: 0.14221211 | O78: -0.0010570842 | P78: -0.63927877 | Q78: No reliable edge | R78: -0.0084343577 | S78: -2.9019573 | T78: Weak - tends to fail | U78: 0.0018404127 | V78: -0.0030638286 | W78: 0.00581258
A79: Chart pattern | B79: Rectangle | C79: Rectangle - down breakout | D79: Bearish | E79: 570 | F79: 313 | G79: 276 | H79: 0.11985689 | I79: 0.11967687 | J79: 0.0016853251 | K79: 0.78235425 | L79: No reliable edge | M79: 0.13172542 | N79: 0.14086166 | O79: -0.0027993412 | P79: -0.69320434 | Q79: No reliable edge | R79: -0.0027930197 | S79: -0.36386238 | T79: No reliable edge | U79: 0.0042705002 | V79: -0.0028623822 | W79: -0.00023934852 | X79: 0.48892989
A80: Chart pattern | B80: Harmonic | C80: Bearish Bat | D80: Bearish | E80: 250 | F80: 196 | G80: 99 | H80: 0.1300813 | I80: 0.12568892 | J80: -0.0012711193 | K80: -0.40380418 | L80: No reliable edge | M80: 0.14225941 | N80: 0.14307634 | O80: -0.0044235456 | P80: -0.71334649 | Q80: No reliable edge | R80: 0.0092954293 | S80: 0.7562315 | T80: No reliable edge | U80: -0.001727916 | V80: -0.003122157 | W80: -0.013895965 | X80: 0.53556485
A81: Chart pattern | B81: Volume patterns | C81: Buying climax (reversal) | D81: Bearish | E81: 722 | F81: 311 | G81: 237 | H81: 0.13700565 | I81: 0.12242351 | J81: 0.0073786262 | K81: 2.2841305 | L81: Weak edge | M81: 0.093088858 | N81: 0.14195178 | O81: -0.0039631655 | P81: -0.71420647 | Q81: No reliable edge | R81: -0.020025646 | S81: -1.791641 | T81: No reliable edge | U81: 0.0012924057 | V81: -0.0045949894 | W81: 0.01966574
A82: Chart pattern | B82: Volume patterns | C82: Pocket pivot | D82: Bullish | E82: 28637 | F82: 482 | G82: 10863 | H82: 0.20881226 | I82: 0.17889204 | J82: 0.00022506534 | K82: 0.51035951 | L82: No reliable edge | M82: 0.32300885 | N82: 0.30281252 | O82: -0.00086230359 | P82: -0.76886672 | Q82: No reliable edge | R82: -0.0038794888 | S82: -1.9471989 | T82: No reliable edge | U82: 0.001014195 | V82: 0.00034783766 | W82: -0.012113397
A83: Chart pattern | B83: V reversal | C83: V-bottom | D83: Bullish | E83: 6243 | F83: 475 | G83: 2750 | H83: 0.18056693 | I83: 0.1796412 | J83: -0.0018320294 | K83: -1.8404279 | L83: No reliable edge | M83: 0.28703246 | N83: 0.29683008 | O83: -0.0018115932 | P83: -0.76980435 | Q83: No reliable edge | R83: 0.0015059605 | S83: 0.30048724 | T83: No reliable edge | U83: -0.00017318806 | V83: 0.0023350069 | W83: -0.016545691 | X83: 0.76743785
A84: Chart pattern | B84: Reversal bars | C84: Key reversal day (bullish) | D84: Bullish | E84: 4025 | F84: 474 | G84: 1836 | H84: 0.14679602 | I84: 0.15989887 | J84: -0.0010816963 | K84: -0.98222279 | L84: No reliable edge | M84: 0.24554876 | N84: 0.25881418 | O84: -0.0019824696 | P84: -0.88670811 | Q84: No reliable edge | R84: 0.00049953113 | S84: 0.095625502 | T84: No reliable edge | U84: -0.0018734588 | V84: -0.0045385244 | W84: 0.0033290917
A85: Chart pattern | B85: Harmonic | C85: Bullish Gartley | D85: Bullish | E85: 734 | F85: 359 | G85: 323 | H85: 0.14799447 | I85: 0.16229366 | J85: -0.0009179277 | K85: -0.43749267 | L85: No reliable edge | M85: 0.25 | N85: 0.2832845 | O85: -0.0049481654 | P85: -0.89258896 | Q85: No reliable edge | R85: -0.0039798113 | S85: -0.39279932 | T85: No reliable edge | U85: -0.0058185645 | V85: -0.011674504 | W85: -0.006836257 | X85: 0.70167428
A86: Chart pattern | B86: IBD bases | C86: Flat base breakout (40d) | D86: Bullish | E86: 569 | F86: 235 | G86: 198 | H86: 0.21364452 | I86: 0.17314224 | J86: 0.0021966272 | K86: 1.0363954 | L86: No reliable edge | M86: 0.29174312 | N86: 0.2813356 | O86: -0.0041989122 | P86: -0.9121004 | Q86: No reliable edge | R86: -0.012486859 | S86: -1.3385894 | T86: No reliable edge | U86: 0.00059884002 | V86: -0.004992639 | W86: -0.029378796
A87: Chart pattern | B87: Harmonic | C87: Bullish Cypher | D87: Bullish | E87: 862 | F87: 369 | G87: 351 | H87: 0.1584507 | I87: 0.1750001 | J87: -0.0021634158 | K87: -1.1690461 | L87: No reliable edge | M87: 0.27536232 | N87: 0.2896551 | O87: -0.0040155147 | P87: -0.91712882 | Q87: No reliable edge | R87: 0.013637436 | S87: 1.4583958 | T87: No reliable edge | U87: 0.00046333323 | V87: -0.0054965526 | W87: -0.0021921797 | X87: 0.70050761
A88: Chart pattern | B88: Cup & handle | C88: Cup & handle | D88: Bullish | E88: 13 | F88: 13 | G88: 3 | H88: 0.076923077 | I88: 0.14460787 | J88: 0.0063010737 | K88: 0.48984918 | L88: Too few events | M88: 0.16666667 | N88: 0.24657343 | O88: -0.019086777 | P88: -0.9514128 | Q88: Too few events | R88: -0.080289337 | S88: -1.3340828 | T88: Too few events | U88: 5.0350307e-05 | V88: -0.011646922
A89: Chart pattern | B89: Harmonic | C89: Bearish AB=CD | D89: Bearish | E89: 4990 | F89: 473 | G89: 1879 | H89: 0.12827278 | I89: 0.12121334 | J89: 0.0012428085 | K89: 1.4041141 | L89: No reliable edge | M89: 0.1411863 | N89: 0.14292847 | O89: -0.0016444862 | P89: -1.0350231 | Q89: No reliable edge | R89: -0.0049250523 | S89: -1.6731672 | T89: No reliable edge | U89: 0.00064391487 | V89: -0.0006323476 | W89: 0.0036153126 | X89: 0.44766949
A90: Chart pattern | B90: Divergence | C90: Hidden bullish divergence (OBV) | D90: Bullish | E90: 5901 | F90: 473 | G90: 2343 | H90: 0.17796465 | I90: 0.17060564 | J90: -0.0011847266 | K90: -1.6037451 | L90: No reliable edge | M90: 0.28899002 | N90: 0.28945232 | O90: -0.0019105797 | P90: -1.0641218 | Q90: No reliable edge | R90: 0.00054799432 | S90: 0.17132376 | T90: No reliable edge | U90: -0.0018113505 | V90: -0.000896359 | W90: -0.008650068
A91: Chart pattern | B91: Divergence | C91: Hidden bearish divergence (MFI) | D91: Bearish | E91: 10115 | F91: 486 | G91: 4626 | H91: 0.11930958 | I91: 0.12091162 | J91: 0.0011090824 | K91: 1.9858129 | L91: No reliable edge | M91: 0.1452295 | N91: 0.14788129 | O91: -0.0011678898 | P91: -1.0863499 | Q91: No reliable edge | R91: 0.00098087227 | S91: 0.43651437 | T91: No reliable edge | U91: 8.9224159e-05 | V91: -0.00054549914 | W91: -0.0028458288
A92: Chart pattern | B92: Channel down | C92: Channel down - down breakout | D92: Bearish | E92: 689 | F92: 337 | G92: 332 | H92: 0.10928144 | I92: 0.11750976 | J92: -0.0021823876 | K92: -1.0725041 | L92: No reliable edge | M92: 0.13657056 | N92: 0.13582854 | O92: -0.0050168879 | P92: -1.2082762 | Q92: No reliable edge | R92: -0.0088872068 | S92: -0.97443319 | T92: No reliable edge | U92: -0.0085688871 | V92: -0.005861301 | W92: -0.005065418 | X92: 0.46766917
A93: Chart pattern | B93: Descending triangle | C93: Descending triangle - up breakout | D93: Bullish | E93: 4462 | F93: 473 | G93: 1942 | H93: 0.1889674 | I93: 0.17011843 | J93: 0.00078854813 | K93: 0.89279244 | L93: No reliable edge | M93: 0.28671329 | N93: 0.2815548 | O93: -0.002487536 | P93: -1.2747933 | Q93: No reliable edge | R93: -0.0032930937 | S93: -0.90640217 | T93: No reliable edge | U93: -0.00015803432 | V93: -0.0028386325 | W93: -0.006393163 | X93: 0.31790053
A94: Chart pattern | B94: Rounding | C94: Rounding bottom (saucer) | D94: Bullish | E94: 592 | F94: 281 | G94: 201 | H94: 0.18197574 | I94: 0.18409132 | J94: -0.0025678262 | K94: -1.0177776 | L94: No reliable edge | M94: 0.33631485 | N94: 0.32046318 | O94: -0.0085360832 | P94: -1.3432859 | Q94: No reliable edge | R94: -0.012660631 | S94: -1.2534339 | T94: No reliable edge | U94: -0.0040621183 | V94: -0.0099602365 | W94: 0.042720346 | X94: 0.50896057
A95: Chart pattern | B95: Right-angled broadening (descending) | C95: Right-angled broadening (descending) - up breakout | D95: Bullish | E95: 374 | F95: 253 | G95: 173 | H95: 0.14088398 | I95: 0.17734463 | J95: -0.0058042718 | K95: -2.0444793 | L95: Weak - tends to fail | M95: 0.27855153 | N95: 0.30396023 | O95: -0.008719088 | P95: -1.3738973 | Q95: No reliable edge | R95: -0.012968778 | S95: -0.90446083 | T95: No reliable edge | U95: -0.0071597864 | V95: -0.012806971 | W95: 0.0016178599 | X95: 0.62395543
A96: Chart pattern | B96: Descending broadening wedge | C96: Descending broadening wedge - up breakout | D96: Bullish | E96: 1136 | F96: 394 | G96: 482 | H96: 0.15446429 | I96: 0.16697845 | J96: -0.0018919355 | K96: -1.0040823 | L96: No reliable edge | M96: 0.25835592 | N96: 0.28447756 | O96: -0.0057895705 | P96: -1.4479209 | Q96: No reliable edge | R96: -0.0010230098 | S96: -0.13130054 | T96: No reliable edge | U96: -0.0037005992 | V96: -0.002131863 | W96: -0.01710588 | X96: 0.57142857
